Workbook

Sheet AUCROC Weight
B1: Sector | D1: Corporate | V1: Households | AI1: Government | AX1: Banking | BM1: External | BZ1: Недвижимость
B2: Indicator | D2: Debt service ratio, % | I2: All Debt to GDP ratio, % | N2: Прирост реального кредита банков ЮЛ (дефлятор ВВП 2018=1) | Q2: Складские запасы в промышленности к среднемесячному ОПП, % | V2: Debt_service ratio_annual | AA2: Кредит ФЛ к ВВП | AF2: Прирост реального кредита банков ФЛ (ИПЦ 2018=1) | AI2: Обслуживание внешнего долга органов государственного управления к ВВП, % | AN2: Отношение сальдо консолидированного бюджета к ВВП, % | AS2: Долг сектора государственного управления к ВВП, % (внешний + внутренний) | AX2: Требования банков к экономике к ВВП, % | BC2: Требования банков к депозитам банков, % | BH2: Леверидж (активы к собственному капиталу), раз | BM2: Счет текущих операций за год, в % к ВВП | BR2: Валовый внешний долг к ВВП | BW2: Логарифм цен на коммерческую недвижимость, скорректированных на дефлятор, *100 | CB2: Логарифм цен на жилую недвижимость, скорректированных на ИПЦ
D3: dsr | E3: dsr1 | F3: dsr2 | G3: dsr_av2 | H3: dsr_av3 | I3: ggr | J3: ggr1 | K3: ggr2 | L3: ggr_av2 | M3: ggr_av3 | N3: rcgr_c1 | O3: rcgr_c2 | P3: rcgr_c3 | Q3: invr | R3: invr1 | S3: invr2 | T3: invr_av2 | U3: invr_av3 | V3: d_srv | W3: d_srv1 | X3: d_srv2 | Y3: d_srv_av2 | Z3: d_srv_av3 | AA3: l_gdp | AB3: l_gdp1 | AC3: l_gdp2 | AD3: l_gdp_av2 | AE3: l_gdp_av3 | AF3: rcgr_h1 | AG3: rcgr_h2 | AH3: rcgr_h3 | AI3: exd_s | AJ3: exd_s1 | AK3: exd_s2 | AL3: exd_s_av2 | AM3: exd_s_av3 | AN3: bb_gdp | AO3: bb_gdp1 | AP3: bb_gdp2 | AQ3: bb_gdp_av2 | AR3: bb_gdp_av3 | AS3: ggd | AT3: ggd1 | AU3: ggd2 | AV3: ggd_av2 | AW3: ggd_av3 | AX3: crr | AY3: crr1 | AZ3: crr2 | BA3: crr_av2 | BB3: crr_av3 | BC3: d_as | BD3: d_as1 | BE3: d_as2 | BF3: d_as_av2 | BG3: d_as_av3 | BH3: lvr | BI3: lvr1 | BJ3: lvr2 | BK3: lvr_av2 | BL3: lvr_av3 | BM3: ca | BN3: ca1 | BO3: ca2 | BP3: ca_av2 | BQ3: ca_av3 | BR3: gd_gdp | BS3: gd_gdp1 | BT3: gd_gdp2 | BU3: gd_gdp_av2 | BV3: gd_gdp_av3 | BW3: cest | BX3: cest1 | BY3: cest2 | BZ3: cest_av2 | CA3: cest_av3 | CB3: pest | CC3: pest1 | CD3: pest2 | CE3: pest_av2 | CF3: pest_av3
C4: 12 | D4: 0.48846154 | E4: 0.65053763 | F4: 0.74712644 | G4: 0.74137931 | H4: 0.67272727 | I4: 0.56617647 | J4: 0.6171875 | K4: 0.50273224 | L4: 0.53005464 | M4: 0.54385965 | N4: 0.72426471 | O4: 0.65441176 | P4: 0.70522388 | Q4: 0.76102941 | R4: 0.58203125 | S4: 0.72131148 | T4: 0.59016393 | U4: 0.62573099 | V4: 0.5546875 | W4: 0.6010929 | X4: 0.57309942 | Y4: 0.59064327 | Z4: 0.52777778 | AA4: 0.50367647 | AB4: 0.69921875 | AC4: 0.45901639 | AD4: 0.63387978 | AE4: 0.58479532 | AF4: 0.59191176 | AG4: 0.51838235 | AH4: 0.49626866 | AI4: 0.65441176 | AJ4: 0.66015625 | AK4: 0.4863388 | AL4: 0.54644809 | AM4: 0.58479532 | AN4: 0.69117647 | AO4: 0.49609375 | AP4: 0.87431694 | AQ4: 0.72677596 | AR4: 0.81871345 | AS4: 0.50367647 | AT4: 0.53515625 | AU4: 0.57923497 | AV4: 0.53551913 | AW4: 0.5380117 | AX4: 0.54411765 | AY4: 0.70703125 | AZ4: 0.47540984 | BA4: 0.59016393 | BB4: 0.50877193 | BC4: 0.56985294 | BD4: 0.66015625 | BE4: 0.46994536 | BF4: 0.6010929 | BG4: 0.55555556 | BH4: 0.45895522 | BI4: 0.76041667 | BJ4: 0.73888889 | BK4: 0.75 | BL4: 0.77380952 | BM4: 0.56617647 | BN4: 0.7109375 | BO4: 0.55737705 | BP4: 0.66120219 | BQ4: 0.61403509 | BR4: 0.52941176 | BS4: 0.55078125 | BT4: 0.61748634 | BU4: 0.55737705 | BV4: 0.57309942 | BW4: 0.73461538 | BX4: 0.65591398 | BY4: 0.52873563 | BZ4: 0.63218391 | CA4: 0.66363636 | CB4: 0.61458333 | CC4: 0.82222222 | CD4: 0.625 | CE4: 0.83928571 | CF4: 0.5
C5: 11 | D5: 0.57954545 | E5: 0.54497354 | F5: 0.65536723 | G5: 0.53107345 | H5: 0.49107143 | I5: 0.67028986 | J5: 0.68846154 | K5: 0.60752688 | L5: 0.65053763 | M5: 0.61494253 | N5: 0.71014493 | O5: 0.66666667 | P5: 0.70955882 | Q5: 0.76630435 | R5: 0.61923077 | S5: 0.6827957 | T5: 0.59139785 | U5: 0.6954023 | V5: 0.53846154 | W5: 0.53225806 | X5: 0.57471264 | Y5: 0.57471264 | Z5: 0.5 | AA5: 0.61594203 | AB5: 0.67307692 | AC5: 0.56451613 | AD5: 0.63978495 | AE5: 0.5862069 | AF5: 0.54710145 | AG5: 0.51086957 | AH5: 0.54779412 | AI5: 0.68115942 | AJ5: 0.64615385 | AK5: 0.47849462 | AL5: 0.58602151 | AM5: 0.56321839 | AN5: 0.72463768 | AO5: 0.46538462 | AP5: 0.84946237 | AQ5: 0.72580645 | AR5: 0.82758621 | AS5: 0.60869565 | AT5: 0.50769231 | AU5: 0.64516129 | AV5: 0.61827957 | AW5: 0.63218391 | AX5: 0.66666667 | AY5: 0.71153846 | AZ5: 0.66129032 | BA5: 0.69354839 | BB5: 0.6954023 | BC5: 0.5326087 | BD5: 0.61923077 | BE5: 0.54301075 | BF5: 0.55376344 | BG5: 0.53448276 | BH5: 0.55514706 | BI5: 0.54296875 | BJ5: 0.67213115 | BK5: 0.5136612 | BL5: 0.59064327 | BM5: 0.57246377 | BN5: 0.6 | BO5: 0.5483871 | BP5: 0.62365591 | BQ5: 0.56896552 | BR5: 0.58333333 | BS5: 0.55384615 | BT5: 0.60215054 | BU5: 0.55376344 | BV5: 0.56896552 | BW5: 0.64015152 | BX5: 0.5978836 | BY5: 0.66666667 | BZ5: 0.54237288 | CA5: 0.58035714 | CB5: 0.48828125 | CC5: 0.7431694 | CD5: 0.78947368 | CE5: 0.92982456 | CF5: 0.66666667
C6: 10 | D6: 0.62313433 | E6: 0.70833333 | F6: 0.50555556 | G6: 0.67222222 | H6: 0.52380952 | I6: 0.81428571 | J6: 0.76515152 | K6: 0.72486772 | L6: 0.7989418 | M6: 0.74576271 | N6: 0.59285714 | O6: 0.70714286 | P6: 0.68478261 | Q6: 0.78928571 | R6: 0.48863636 | S6: 0.58201058 | T6: 0.57142857 | U6: 0.64971751 | V6: 0.54924242 | W6: 0.47089947 | X6: 0.56497175 | Y6: 0.57062147 | Z6: 0.5 | AA6: 0.53928571 | AB6: 0.56818182 | AC6: 0.56084656 | AD6: 0.57671958 | AE6: 0.5480226 | AF6: 0.47857143 | AG6: 0.50357143 | AH6: 0.60507246 | AI6: 0.65357143 | AJ6: 0.56818182 | AK6: 0.53968254 | AL6: 0.52380952 | AM6: 0.50282486 | AN6: 0.7 | AO6: 0.52272727 | AP6: 0.6031746 | AQ6: 0.55026455 | AR6: 0.71186441 | AS6: 0.65714286 | AT6: 0.5719697 | AU6: 0.7037037 | AV6: 0.65608466 | AW6: 0.72316384 | AX6: 0.78214286 | AY6: 0.67424242 | AZ6: 0.71957672 | BA6: 0.73015873 | BB6: 0.6779661 | BC6: 0.50357143 | BD6: 0.53030303 | BE6: 0.51322751 | BF6: 0.52910053 | BG6: 0.52542373 | BH6: 0.7173913 | BI6: 0.6 | BJ6: 0.5483871 | BK6: 0.67204301 | BL6: 0.55747126 | BM6: 0.60714286 | BN6: 0.5530303 | BO6: 0.5978836 | BP6: 0.6031746 | BQ6: 0.5480226 | BR6: 0.65 | BS6: 0.54166667 | BT6: 0.62962963 | BU6: 0.64021164 | BV6: 0.63841808 | BW6: 0.64925373 | BX6: 0.5625 | BY6: 0.58333333 | BZ6: 0.56111111 | CA6: 0.46428571 | CB6: 0.53461538 | CC6: 0.56989247 | CD6: 0.8045977 | CE6: 0.6954023 | CF6: 0.7
C7: 9 | D7: 0.70955882 | E7: 0.8359375 | F7: 0.59562842 | G7: 0.81967213 | H7: 0.66666667 | I7: 0.71478873 | J7: 0.6119403 | K7: 0.69791667 | L7: 0.671875 | M7: 0.67222222 | N7: 0.59507042 | O7: 0.53169014 | P7: 0.525 | Q7: 0.58450704 | R7: 0.69776119 | S7: 0.61979167 | T7: 0.71354167 | U7: 0.59444444 | V7: 0.58955224 | W7: 0.44270833 | X7: 0.58333333 | Y7: 0.57222222 | Z7: 0.5952381 | AA7: 0.45070423 | AB7: 0.45895522 | AC7: 0.515625 | AD7: 0.47916667 | AE7: 0.46111111 | AF7: 0.44014085 | AG7: 0.50352113 | AH7: 0.6 | AI7: 0.66197183 | AJ7: 0.62313433 | AK7: 0.53645833 | AL7: 0.60416667 | AM7: 0.51666667 | AN7: 0.69366197 | AO7: 0.53358209 | AP7: 0.53125 | AQ7: 0.59895833 | AR7: 0.53888889 | AS7: 0.58802817 | AT7: 0.51119403 | AU7: 0.63020833 | AV7: 0.55208333 | AW7: 0.65555556 | AX7: 0.6443662 | AY7: 0.55970149 | AZ7: 0.63541667 | BA7: 0.59895833 | BB7: 0.58888889 | BC7: 0.56338028 | BD7: 0.46641791 | BE7: 0.52604167 | BF7: 0.52604167 | BG7: 0.49444444 | BH7: 0.725 | BI7: 0.67045455 | BJ7: 0.58730159 | BK7: 0.77777778 | BL7: 0.63276836 | BM7: 0.54577465 | BN7: 0.64552239 | BO7: 0.51041667 | BP7: 0.47916667 | BQ7: 0.45555556 | BR7: 0.6971831 | BS7: 0.57089552 | BT7: 0.64583333 | BU7: 0.63020833 | BV7: 0.66666667 | BW7: 0.82720588 | BX7: 0.8359375 | BY7: 0.71584699 | BZ7: 0.8852459 | CA7: 0.80701754 | CB7: 0.54166667 | CC7: 0.53968254 | CD7: 0.81355932 | CE7: 0.61016949 | CF7: 0.66071429
C8: 8 | D8: 0.71014493 | E8: 0.82692308 | F8: 0.6827957 | G8: 0.82258065 | H8: 0.6954023 | I8: 0.53819444 | J8: 0.41911765 | K8: 0.578125 | L8: 0.43359375 | M8: 0.53005464 | N8: 0.73958333 | O8: 0.50694444 | P8: 0.54225352 | Q8: 0.59027778 | R8: 0.77941176 | S8: 0.69335938 | T8: 0.7578125 | U8: 0.73770492 | V8: 0.58455882 | W8: 0.62890625 | X8: 0.61202186 | Y8: 0.61202186 | Z8: 0.60818713 | AA8: 0.43055556 | AB8: 0.41911765 | AC8: 0.515625 | AD8: 0.43359375 | AE8: 0.3989071 | AF8: 0.64236111 | AG8: 0.51041667 | AH8: 0.61267606 | AI8: 0.66666667 | AJ8: 0.54044118 | AK8: 0.66796875 | AL8: 0.62109375 | AM8: 0.46448087 | AN8: 0.56597222 | AO8: 0.66176471 | AP8: 0.53125 | AQ8: 0.64453125 | AR8: 0.71584699 | AS8: 0.66319444 | AT8: 0.57352941 | AU8: 0.59375 | AV8: 0.58203125 | AW8: 0.63934426 | AX8: 0.5 | AY8: 0.45588235 | AZ8: 0.59765625 | BA8: 0.48046875 | BB8: 0.53551913 | BC8: 0.49305556 | BD8: 0.57352941 | BE8: 0.48828125 | BF8: 0.56640625 | BG8: 0.48087432 | BH8: 0.62323944 | BI8: 0.62313433 | BJ8: 0.515625 | BK8: 0.63020833 | BL8: 0.5 | BM8: 0.63194444 | BN8: 0.66911765 | BO8: 0.4453125 | BP8: 0.65625 | BQ8: 0.57923497 | BR8: 0.6875 | BS8: 0.61029412 | BT8: 0.66796875 | BU8: 0.62890625 | BV8: 0.66666667 | BW8: 0.7826087 | BX8: 0.83076923 | BY8: 0.68817204 | BZ8: 0.80107527 | CA8: 0.79885057 | CB8: 0.5261194 | CC8: 0.609375 | CD8: 0.65 | CE8: 0.48333333 | CF8: 0.64285714
C9: 7 | D9: 0.68571429 | E9: 0.59848485 | F9: 0.68253968 | G9: 0.75132275 | H9: 0.63841808 | I9: 0.52054795 | J9: 0.67391304 | K9: 0.47692308 | L9: 0.62692308 | M9: 0.58064516 | N9: 0.85958904 | O9: 0.6369863 | P9: 0.61111111 | Q9: 0.76712329 | R9: 0.87318841 | S9: 0.76153846 | T9: 0.9 | U9: 0.91397849 | V9: 0.48913043 | W9: 0.66923077 | X9: 0.62365591 | Y9: 0.60752688 | Z9: 0.63793103 | AA9: 0.56164384 | AB9: 0.59057971 | AC9: 0.5 | AD9: 0.46538462 | AE9: 0.40860215 | AF9: 0.6130137 | AG9: 0.5239726 | AH9: 0.58680556 | AI9: 0.62671233 | AJ9: 0.60144928 | AK9: 0.58846154 | AL9: 0.52307692 | AM9: 0.53225806 | AN9: 0.63356164 | AO9: 0.73188406 | AP9: 0.72307692 | AQ9: 0.72307692 | AR9: 0.83333333 | AS9: 0.65410959 | AT9: 0.52173913 | AU9: 0.56153846 | AV9: 0.55769231 | AW9: 0.56451613 | AX9: 0.45547945 | AY9: 0.64855072 | AZ9: 0.51538462 | BA9: 0.60769231 | BB9: 0.53763441 | BC9: 0.65068493 | BD9: 0.69927536 | BE9: 0.45384615 | BF9: 0.62692308 | BG9: 0.56451613 | BH9: 0.55555556 | BI9: 0.52573529 | BJ9: 0.58203125 | BK9: 0.51953125 | BL9: 0.53551913 | BM9: 0.69178082 | BN9: 0.82608696 | BO9: 0.57692308 | BP9: 0.75769231 | BQ9: 0.65053763 | BR9: 0.56849315 | BS9: 0.43115942 | BT9: 0.59230769 | BU9: 0.49230769 | BV9: 0.61827957 | BW9: 0.79285714 | BX9: 0.78409091 | BY9: 0.76719577 | BZ9: 0.77248677 | CA9: 0.78531073 | CB9: 0.55882353 | CC9: 0.5390625 | CD9: 0.57377049 | CE9: 0.54098361 | CF9: 0.58479532
C10: 6 | D10: 0.67253521 | E10: 0.50373134 | F10: 0.71875 | G10: 0.66666667 | H10: 0.61666667 | I10: 0.52702703 | J10: 0.68928571 | K10: 0.45833333 | L10: 0.61742424 | M10: 0.5978836 | N10: 0.86148649 | O10: 0.63175676 | P10: 0.54452055 | Q10: 0.71959459 | R10: 0.875 | S10: 0.79545455 | T10: 0.8030303 | U10: 0.87301587 | V10: 0.53214286 | W10: 0.6780303 | X10: 0.61904762 | Y10: 0.62433862 | Z10: 0.62711864 | AA10: 0.55405405 | AB10: 0.66071429 | AC10: 0.48484848 | AD10: 0.53030303 | AE10: 0.58730159 | AF10: 0.55067568 | AG10: 0.50337838 | AH10: 0.53424658 | AI10: 0.61486486 | AJ10: 0.55357143 | AK10: 0.56439394 | AL10: 0.49621212 | AM10: 0.51851852 | AN10: 0.57432432 | AO10: 0.66785714 | AP10: 0.6780303 | AQ10: 0.64772727 | AR10: 0.76190476 | AS10: 0.52027027 | AT10: 0.53571429 | AU10: 0.51515152 | AV10: 0.52272727 | AW10: 0.59259259 | AX10: 0.53040541 | AY10: 0.76785714 | AZ10: 0.45833333 | BA10: 0.60227273 | BB10: 0.56613757 | BC10: 0.69594595 | BD10: 0.825 | BE10: 0.60606061 | BF10: 0.6780303 | BG10: 0.58201058 | BH10: 0.53767123 | BI10: 0.5942029 | BJ10: 0.48076923 | BK10: 0.55769231 | BL10: 0.46774194 | BM10: 0.72635135 | BN10: 0.85357143 | BO10: 0.61742424 | BP10: 0.78409091 | BQ10: 0.70899471 | BR10: 0.48310811 | BS10: 0.63214286 | BT10: 0.48106061 | BU10: 0.60606061 | BV10: 0.52380952 | BW10: 0.50352113 | BX10: 0.55597015 | BY10: 0.64583333 | BZ10: 0.63020833 | CA10: 0.61111111 | CB10: 0.63768116 | CC10: 0.59230769 | CD10: 0.47311828 | CE10: 0.52688172 | CF10: 0.5862069
C11: 5 | D11: 0.66319444 | E11: 0.59926471 | F11: 0.6171875 | G11: 0.4921875 | H11: 0.64480874 | I11: 0.57666667 | J11: 0.73943662 | K11: 0.5858209 | L11: 0.64552239 | M11: 0.609375 | N11: 0.73333333 | O11: 0.77666667 | P11: 0.60810811 | Q11: 0.59333333 | R11: 0.59859155 | S11: 0.74253731 | T11: 0.63059701 | U11: 0.76041667 | V11: 0.57042254 | W11: 0.70522388 | X11: 0.60416667 | Y11: 0.57291667 | Z11: 0.59444444 | AA11: 0.58333333 | AB11: 0.63028169 | AC11: 0.48134328 | AD11: 0.54850746 | AE11: 0.55729167 | AF11: 0.52666667 | AG11: 0.51 | AH11: 0.52364865 | AI11: 0.55 | AJ11: 0.60211268 | AK11: 0.54104478 | AL11: 0.56716418 | AM11: 0.55729167 | AN11: 0.74333333 | AO11: 0.8028169 | AP11: 0.73134328 | AQ11: 0.83208955 | AR11: 0.859375 | AS11: 0.52 | AT11: 0.52816901 | AU11: 0.51865672 | AV11: 0.51492537 | AW11: 0.59895833 | AX11: 0.54333333 | AY11: 0.74647887 | AZ11: 0.59328358 | BA11: 0.61940299 | BB11: 0.57291667 | BC11: 0.74 | BD11: 0.84507042 | BE11: 0.65298507 | BF11: 0.75746269 | BG11: 0.609375 | BH11: 0.5 | BI11: 0.69642857 | BJ11: 0.53030303 | BK11: 0.56818182 | BL11: 0.47619048 | BM11: 0.67 | BN11: 0.6443662 | BO11: 0.71268657 | BP11: 0.71641791 | BQ11: 0.65104167 | BR11: 0.56666667 | BS11: 0.66901408 | BT11: 0.57835821 | BU11: 0.64552239 | BV11: 0.59375 | BW11: 0.82746479 | BX11: 0.90298507 | BY11: 0.53571429 | BZ11: 0.8531746 | CA11: 0.84444444 | CB11: 0.66785714 | CC11: 0.59090909 | CD11: 0.44444444 | CE11: 0.49206349 | CF11: 0.59887006
C12: 4 | D12: 0.59246575 | E12: 0.61956522 | F12: 0.55384615 | G12: 0.53076923 | H12: 0.6344086 | I12: 0.58552632 | J12: 0.66666667 | K12: 0.59191176 | L12: 0.66544118 | M12: 0.58984375 | N12: 0.64473684 | O12: 0.78947368 | P12: 0.59666667 | Q12: 0.50493421 | R12: 0.68055556 | S12: 0.66176471 | T12: 0.51838235 | U12: 0.57421875 | V12: 0.60069444 | W12: 0.59558824 | X12: 0.609375 | Y12: 0.625 | Z12: 0.56284153 | AA12: 0.57894737 | AB12: 0.5625 | AC12: 0.52573529 | AD12: 0.58455882 | AE12: 0.5 | AF12: 0.49671053 | AG12: 0.61184211 | AH12: 0.51333333 | AI12: 0.59210526 | AJ12: 0.58680556 | AK12: 0.52205882 | AL12: 0.55882353 | AM12: 0.52734375 | AN12: 0.74671053 | AO12: 0.73958333 | AP12: 0.74632353 | AQ12: 0.79779412 | AR12: 0.78125 | AS12: 0.47368421 | AT12: 0.62847222 | AU12: 0.47058824 | AV12: 0.58455882 | AW12: 0.5546875 | AX12: 0.50986842 | AY12: 0.65277778 | AZ12: 0.5625 | BA12: 0.62867647 | BB12: 0.5390625 | BC12: 0.72697368 | BD12: 0.78125 | BE12: 0.66544118 | BF12: 0.75367647 | BG12: 0.6875 | BH12: 0.53333333 | BI12: 0.64788732 | BJ12: 0.52985075 | BK12: 0.64925373 | BL12: 0.44270833 | BM12: 0.64802632 | BN12: 0.50347222 | BO12: 0.69117647 | BP12: 0.63235294 | BQ12: 0.6640625 | BR12: 0.60197368 | BS12: 0.72569444 | BT12: 0.60661765 | BU12: 0.67279412 | BV12: 0.64453125 | BW12: 0.82746479 | BX12: 0.88059701 | BY12: 0.51984127 | BZ12: 0.81746032 | CA12: 0.82777778 | CB12: 0.70422535 | CC12: 0.65298507 | CD12: 0.49479167 | CE12: 0.546875 | CF12: 0.62777778
C14: -12 | D14: -0.011538462 | E14: 0.15053763 | F14: 0.24712644 | G14: 0.24137931 | H14: 0.17272727 | I14: 0.066176471 | J14: 0.1171875 | K14: 0.0027322404 | L14: 0.030054645 | M14: 0.043859649 | N14: 0.22426471 | O14: 0.15441176 | P14: 0.20522388 | Q14: 0.26102941 | R14: 0.08203125 | S14: 0.22131148 | T14: 0.090163934 | U14: 0.12573099 | V14: 0.0546875 | W14: 0.1010929 | X14: 0.073099415 | Y14: 0.090643275 | Z14: 0.027777778 | AA14: 0.0036764706 | AB14: 0.19921875 | AC14: -0.040983607 | AD14: 0.13387978 | AE14: 0.084795322 | AF14: 0.091911765 | AG14: 0.018382353 | AH14: -0.0037313433 | AI14: 0.15441176 | AJ14: 0.16015625 | AK14: -0.013661202 | AL14: 0.046448087 | AM14: 0.084795322 | AN14: 0.19117647 | AO14: -0.00390625 | AP14: 0.37431694 | AQ14: 0.22677596 | AR14: 0.31871345 | AS14: 0.0036764706 | AT14: 0.03515625 | AU14: 0.079234973 | AV14: 0.035519126 | AW14: 0.038011696 | AX14: 0.044117647 | AY14: 0.20703125 | AZ14: -0.024590164 | BA14: 0.090163934 | BB14: 0.0087719298 | BC14: 0.069852941 | BD14: 0.16015625 | BE14: -0.030054645 | BF14: 0.1010929 | BG14: 0.055555556 | BH14: -0.041044776 | BI14: 0.26041667 | BJ14: 0.23888889 | BK14: 0.25 | BL14: 0.27380952 | BM14: 0.066176471 | BN14: 0.2109375 | BO14: 0.057377049 | BP14: 0.16120219 | BQ14: 0.11403509 | BR14: 0.029411765 | BS14: 0.05078125 | BT14: 0.11748634 | BU14: 0.057377049 | BV14: 0.073099415 | BW14: 0.23461538 | BX14: 0.15591398 | BY14: 0.028735632 | BZ14: 0.13218391 | CA14: 0.16363636 | CB14: 0.11458333 | CC14: 0.32222222 | CD14: 0.125 | CE14: 0.33928571 | CF14: 0
C15: -11 | D15: 0.079545455 | E15: 0.044973545 | F15: 0.15536723 | G15: 0.031073446 | H15: -0.0089285714 | I15: 0.17028986 | J15: 0.18846154 | K15: 0.10752688 | L15: 0.15053763 | M15: 0.11494253 | N15: 0.21014493 | O15: 0.16666667 | P15: 0.20955882 | Q15: 0.26630435 | R15: 0.11923077 | S15: 0.1827957 | T15: 0.091397849 | U15: 0.1954023 | V15: 0.038461538 | W15: 0.032258065 | X15: 0.074712644 | Y15: 0.074712644 | Z15: 0 | AA15: 0.11594203 | AB15: 0.17307692 | AC15: 0.064516129 | AD15: 0.13978495 | AE15: 0.086206897 | AF15: 0.047101449 | AG15: 0.010869565 | AH15: 0.047794118 | AI15: 0.18115942 | AJ15: 0.14615385 | AK15: -0.021505376 | AL15: 0.086021505 | AM15: 0.063218391 | AN15: 0.22463768 | AO15: -0.034615385 | AP15: 0.34946237 | AQ15: 0.22580645 | AR15: 0.32758621 | AS15: 0.10869565 | AT15: 0.0076923077 | AU15: 0.14516129 | AV15: 0.11827957 | AW15: 0.13218391 | AX15: 0.16666667 | AY15: 0.21153846 | AZ15: 0.16129032 | BA15: 0.19354839 | BB15: 0.1954023 | BC15: 0.032608696 | BD15: 0.11923077 | BE15: 0.043010753 | BF15: 0.053763441 | BG15: 0.034482759 | BH15: 0.055147059 | BI15: 0.04296875 | BJ15: 0.17213115 | BK15: 0.013661202 | BL15: 0.090643275 | BM15: 0.072463768 | BN15: 0.1 | BO15: 0.048387097 | BP15: 0.12365591 | BQ15: 0.068965517 | BR15: 0.083333333 | BS15: 0.053846154 | BT15: 0.10215054 | BU15: 0.053763441 | BV15: 0.068965517 | BW15: 0.14015152 | BX15: 0.097883598 | BY15: 0.16666667 | BZ15: 0.042372881 | CA15: 0.080357143 | CB15: -0.01171875 | CC15: 0.2431694 | CD15: 0.28947368 | CE15: 0.42982456 | CF15: 0.16666667
C16: -10 | D16: 0.12313433 | E16: 0.20833333 | F16: 0.0055555556 | G16: 0.17222222 | H16: 0.023809524 | I16: 0.31428571 | J16: 0.26515152 | K16: 0.22486772 | L16: 0.2989418 | M16: 0.24576271 | N16: 0.092857143 | O16: 0.20714286 | P16: 0.18478261 | Q16: 0.28928571 | R16: -0.011363636 | S16: 0.082010582 | T16: 0.071428571 | U16: 0.14971751 | V16: 0.049242424 | W16: -0.029100529 | X16: 0.064971751 | Y16: 0.070621469 | Z16: 0 | AA16: 0.039285714 | AB16: 0.068181818 | AC16: 0.060846561 | AD16: 0.076719577 | AE16: 0.048022599 | AF16: -0.021428571 | AG16: 0.0035714286 | AH16: 0.10507246 | AI16: 0.15357143 | AJ16: 0.068181818 | AK16: 0.03968254 | AL16: 0.023809524 | AM16: 0.0028248588 | AN16: 0.2 | AO16: 0.022727273 | AP16: 0.1031746 | AQ16: 0.05026455 | AR16: 0.21186441 | AS16: 0.15714286 | AT16: 0.071969697 | AU16: 0.2037037 | AV16: 0.15608466 | AW16: 0.22316384 | AX16: 0.28214286 | AY16: 0.17424242 | AZ16: 0.21957672 | BA16: 0.23015873 | BB16: 0.1779661 | BC16: 0.0035714286 | BD16: 0.03030303 | BE16: 0.013227513 | BF16: 0.029100529 | BG16: 0.025423729 | BH16: 0.2173913 | BI16: 0.1 | BJ16: 0.048387097 | BK16: 0.17204301 | BL16: 0.057471264 | BM16: 0.10714286 | BN16: 0.053030303 | BO16: 0.097883598 | BP16: 0.1031746 | BQ16: 0.048022599 | BR16: 0.15 | BS16: 0.041666667 | BT16: 0.12962963 | BU16: 0.14021164 | BV16: 0.13841808 | BW16: 0.14925373 | BX16: 0.0625 | BY16: 0.083333333 | BZ16: 0.061111111 | CA16: -0.035714286 | CB16: 0.034615385 | CC16: 0.069892473 | CD16: 0.3045977 | CE16: 0.1954023 | CF16: 0.2
C17: -9 | D17: 0.20955882 | E17: 0.3359375 | F17: 0.095628415 | G17: 0.31967213 | H17: 0.16666667 | I17: 0.21478873 | J17: 0.1119403 | K17: 0.19791667 | L17: 0.171875 | M17: 0.17222222 | N17: 0.095070423 | O17: 0.031690141 | P17: 0.025 | Q17: 0.084507042 | R17: 0.19776119 | S17: 0.11979167 | T17: 0.21354167 | U17: 0.094444444 | V17: 0.089552239 | W17: -0.057291667 | X17: 0.083333333 | Y17: 0.072222222 | Z17: 0.095238095 | AA17: -0.049295775 | AB17: -0.041044776 | AC17: 0.015625 | AD17: -0.020833333 | AE17: -0.038888889 | AF17: -0.059859155 | AG17: 0.0035211268 | AH17: 0.1 | AI17: 0.16197183 | AJ17: 0.12313433 | AK17: 0.036458333 | AL17: 0.10416667 | AM17: 0.016666667 | AN17: 0.19366197 | AO17: 0.03358209 | AP17: 0.03125 | AQ17: 0.098958333 | AR17: 0.038888889 | AS17: 0.088028169 | AT17: 0.01119403 | AU17: 0.13020833 | AV17: 0.052083333 | AW17: 0.15555556 | AX17: 0.1443662 | AY17: 0.059701493 | AZ17: 0.13541667 | BA17: 0.098958333 | BB17: 0.088888889 | BC17: 0.063380282 | BD17: -0.03358209 | BE17: 0.026041667 | BF17: 0.026041667 | BG17: -0.0055555556 | BH17: 0.225 | BI17: 0.17045455 | BJ17: 0.087301587 | BK17: 0.27777778 | BL17: 0.13276836 | BM17: 0.045774648 | BN17: 0.14552239 | BO17: 0.010416667 | BP17: -0.020833333 | BQ17: -0.044444444 | BR17: 0.1971831 | BS17: 0.070895522 | BT17: 0.14583333 | BU17: 0.13020833 | BV17: 0.16666667 | BW17: 0.32720588 | BX17: 0.3359375 | BY17: 0.21584699 | BZ17: 0.3852459 | CA17: 0.30701754 | CB17: 0.041666667 | CC17: 0.03968254 | CD17: 0.31355932 | CE17: 0.11016949 | CF17: 0.16071429
C18: -8 | D18: 0.21014493 | E18: 0.32692308 | F18: 0.1827957 | G18: 0.32258065 | H18: 0.1954023 | I18: 0.038194444 | J18: -0.080882353 | K18: 0.078125 | L18: -0.06640625 | M18: 0.030054645 | N18: 0.23958333 | O18: 0.0069444444 | P18: 0.042253521 | Q18: 0.090277778 | R18: 0.27941176 | S18: 0.19335938 | T18: 0.2578125 | U18: 0.23770492 | V18: 0.084558824 | W18: 0.12890625 | X18: 0.11202186 | Y18: 0.11202186 | Z18: 0.10818713 | AA18: -0.069444444 | AB18: -0.080882353 | AC18: 0.015625 | AD18: -0.06640625 | AE18: -0.1010929 | AF18: 0.14236111 | AG18: 0.010416667 | AH18: 0.11267606 | AI18: 0.16666667 | AJ18: 0.040441176 | AK18: 0.16796875 | AL18: 0.12109375 | AM18: -0.035519126 | AN18: 0.065972222 | AO18: 0.16176471 | AP18: 0.03125 | AQ18: 0.14453125 | AR18: 0.21584699 | AS18: 0.16319444 | AT18: 0.073529412 | AU18: 0.09375 | AV18: 0.08203125 | AW18: 0.13934426 | AX18: 0 | AY18: -0.044117647 | AZ18: 0.09765625 | BA18: -0.01953125 | BB18: 0.035519126 | BC18: -0.0069444444 | BD18: 0.073529412 | BE18: -0.01171875 | BF18: 0.06640625 | BG18: -0.019125683 | BH18: 0.12323944 | BI18: 0.12313433 | BJ18: 0.015625 | BK18: 0.13020833 | BL18: 0 | BM18: 0.13194444 | BN18: 0.16911765 | BO18: -0.0546875 | BP18: 0.15625 | BQ18: 0.079234973 | BR18: 0.1875 | BS18: 0.11029412 | BT18: 0.16796875 | BU18: 0.12890625 | BV18: 0.16666667 | BW18: 0.2826087 | BX18: 0.33076923 | BY18: 0.18817204 | BZ18: 0.30107527 | CA18: 0.29885057 | CB18: 0.026119403 | CC18: 0.109375 | CD18: 0.15 | CE18: -0.016666667 | CF18: 0.14285714
C19: -7 | D19: 0.18571429 | E19: 0.098484848 | F19: 0.18253968 | G19: 0.25132275 | H19: 0.13841808 | I19: 0.020547945 | J19: 0.17391304 | K19: -0.023076923 | L19: 0.12692308 | M19: 0.080645161 | N19: 0.35958904 | O19: 0.1369863 | P19: 0.11111111 | Q19: 0.26712329 | R19: 0.37318841 | S19: 0.26153846 | T19: 0.4 | U19: 0.41397849 | V19: -0.010869565 | W19: 0.16923077 | X19: 0.12365591 | Y19: 0.10752688 | Z19: 0.13793103 | AA19: 0.061643836 | AB19: 0.09057971 | AC19: 0 | AD19: -0.034615385 | AE19: -0.091397849 | AF19: 0.1130137 | AG19: 0.023972603 | AH19: 0.086805556 | AI19: 0.12671233 | AJ19: 0.10144928 | AK19: 0.088461538 | AL19: 0.023076923 | AM19: 0.032258065 | AN19: 0.13356164 | AO19: 0.23188406 | AP19: 0.22307692 | AQ19: 0.22307692 | AR19: 0.33333333 | AS19: 0.15410959 | AT19: 0.02173913 | AU19: 0.061538462 | AV19: 0.057692308 | AW19: 0.064516129 | AX19: -0.044520548 | AY19: 0.14855072 | AZ19: 0.015384615 | BA19: 0.10769231 | BB19: 0.037634409 | BC19: 0.15068493 | BD19: 0.19927536 | BE19: -0.046153846 | BF19: 0.12692308 | BG19: 0.064516129 | BH19: 0.055555556 | BI19: 0.025735294 | BJ19: 0.08203125 | BK19: 0.01953125 | BL19: 0.035519126 | BM19: 0.19178082 | BN19: 0.32608696 | BO19: 0.076923077 | BP19: 0.25769231 | BQ19: 0.15053763 | BR19: 0.068493151 | BS19: -0.06884058 | BT19: 0.092307692 | BU19: -0.0076923077 | BV19: 0.11827957 | BW19: 0.29285714 | BX19: 0.28409091 | BY19: 0.26719577 | BZ19: 0.27248677 | CA19: 0.28531073 | CB19: 0.058823529 | CC19: 0.0390625 | CD19: 0.073770492 | CE19: 0.040983607 | CF19: 0.084795322
C20: -6 | D20: 0.17253521 | E20: 0.0037313433 | F20: 0.21875 | G20: 0.16666667 | H20: 0.11666667 | I20: 0.027027027 | J20: 0.18928571 | K20: -0.041666667 | L20: 0.11742424 | M20: 0.097883598 | N20: 0.36148649 | O20: 0.13175676 | P20: 0.044520548 | Q20: 0.21959459 | R20: 0.375 | S20: 0.29545455 | T20: 0.3030303 | U20: 0.37301587 | V20: 0.032142857 | W20: 0.1780303 | X20: 0.11904762 | Y20: 0.12433862 | Z20: 0.12711864 | AA20: 0.054054054 | AB20: 0.16071429 | AC20: -0.015151515 | AD20: 0.03030303 | AE20: 0.087301587 | AF20: 0.050675676 | AG20: 0.0033783784 | AH20: 0.034246575 | AI20: 0.11486486 | AJ20: 0.053571429 | AK20: 0.064393939 | AL20: -0.0037878788 | AM20: 0.018518519 | AN20: 0.074324324 | AO20: 0.16785714 | AP20: 0.1780303 | AQ20: 0.14772727 | AR20: 0.26190476 | AS20: 0.02027027 | AT20: 0.035714286 | AU20: 0.015151515 | AV20: 0.022727273 | AW20: 0.092592593 | AX20: 0.030405405 | AY20: 0.26785714 | AZ20: -0.041666667 | BA20: 0.10227273 | BB20: 0.066137566 | BC20: 0.19594595 | BD20: 0.325 | BE20: 0.10606061 | BF20: 0.1780303 | BG20: 0.082010582 | BH20: 0.037671233 | BI20: 0.094202899 | BJ20: -0.019230769 | BK20: 0.057692308 | BL20: -0.032258065 | BM20: 0.22635135 | BN20: 0.35357143 | BO20: 0.11742424 | BP20: 0.28409091 | BQ20: 0.20899471 | BR20: -0.016891892 | BS20: 0.13214286 | BT20: -0.018939394 | BU20: 0.10606061 | BV20: 0.023809524 | BW20: 0.0035211268 | BX20: 0.055970149 | BY20: 0.14583333 | BZ20: 0.13020833 | CA20: 0.11111111 | CB20: 0.13768116 | CC20: 0.092307692 | CD20: -0.02688172 | CE20: 0.02688172 | CF20: 0.086206897
C21: -5 | D21: 0.16319444 | E21: 0.099264706 | F21: 0.1171875 | G21: -0.0078125 | H21: 0.14480874 | I21: 0.076666667 | J21: 0.23943662 | K21: 0.085820896 | L21: 0.14552239 | M21: 0.109375 | N21: 0.23333333 | O21: 0.27666667 | P21: 0.10810811 | Q21: 0.093333333 | R21: 0.098591549 | S21: 0.24253731 | T21: 0.13059701 | U21: 0.26041667 | V21: 0.070422535 | W21: 0.20522388 | X21: 0.10416667 | Y21: 0.072916667 | Z21: 0.094444444 | AA21: 0.083333333 | AB21: 0.13028169 | AC21: -0.018656716 | AD21: 0.048507463 | AE21: 0.057291667 | AF21: 0.026666667 | AG21: 0.01 | AH21: 0.023648649 | AI21: 0.05 | AJ21: 0.10211268 | AK21: 0.041044776 | AL21: 0.067164179 | AM21: 0.057291667 | AN21: 0.24333333 | AO21: 0.3028169 | AP21: 0.23134328 | AQ21: 0.33208955 | AR21: 0.359375 | AS21: 0.02 | AT21: 0.028169014 | AU21: 0.018656716 | AV21: 0.014925373 | AW21: 0.098958333 | AX21: 0.043333333 | AY21: 0.24647887 | AZ21: 0.093283582 | BA21: 0.11940299 | BB21: 0.072916667 | BC21: 0.24 | BD21: 0.34507042 | BE21: 0.15298507 | BF21: 0.25746269 | BG21: 0.109375 | BH21: 0 | BI21: 0.19642857 | BJ21: 0.03030303 | BK21: 0.068181818 | BL21: -0.023809524 | BM21: 0.17 | BN21: 0.1443662 | BO21: 0.21268657 | BP21: 0.21641791 | BQ21: 0.15104167 | BR21: 0.066666667 | BS21: 0.16901408 | BT21: 0.078358209 | BU21: 0.14552239 | BV21: 0.09375 | BW21: 0.32746479 | BX21: 0.40298507 | BY21: 0.035714286 | BZ21: 0.3531746 | CA21: 0.34444444 | CB21: 0.16785714 | CC21: 0.090909091 | CD21: -0.055555556 | CE21: -0.0079365079 | CF21: 0.098870056
C22: -4 | D22: 0.092465753 | E22: 0.11956522 | F22: 0.053846154 | G22: 0.030769231 | H22: 0.1344086 | I22: 0.085526316 | J22: 0.16666667 | K22: 0.091911765 | L22: 0.16544118 | M22: 0.08984375 | N22: 0.14473684 | O22: 0.28947368 | P22: 0.096666667 | Q22: 0.0049342105 | R22: 0.18055556 | S22: 0.16176471 | T22: 0.018382353 | U22: 0.07421875 | V22: 0.10069444 | W22: 0.095588235 | X22: 0.109375 | Y22: 0.125 | Z22: 0.06284153 | AA22: 0.078947368 | AB22: 0.0625 | AC22: 0.025735294 | AD22: 0.084558824 | AE22: 0 | AF22: -0.0032894737 | AG22: 0.11184211 | AH22: 0.013333333 | AI22: 0.092105263 | AJ22: 0.086805556 | AK22: 0.022058824 | AL22: 0.058823529 | AM22: 0.02734375 | AN22: 0.24671053 | AO22: 0.23958333 | AP22: 0.24632353 | AQ22: 0.29779412 | AR22: 0.28125 | AS22: -0.026315789 | AT22: 0.12847222 | AU22: -0.029411765 | AV22: 0.084558824 | AW22: 0.0546875 | AX22: 0.0098684211 | AY22: 0.15277778 | AZ22: 0.0625 | BA22: 0.12867647 | BB22: 0.0390625 | BC22: 0.22697368 | BD22: 0.28125 | BE22: 0.16544118 | BF22: 0.25367647 | BG22: 0.1875 | BH22: 0.033333333 | BI22: 0.14788732 | BJ22: 0.029850746 | BK22: 0.14925373 | BL22: -0.057291667 | BM22: 0.14802632 | BN22: 0.0034722222 | BO22: 0.19117647 | BP22: 0.13235294 | BQ22: 0.1640625 | BR22: 0.10197368 | BS22: 0.22569444 | BT22: 0.10661765 | BU22: 0.17279412 | BV22: 0.14453125 | BW22: 0.32746479 | BX22: 0.38059701 | BY22: 0.01984127 | BZ22: 0.31746032 | CA22: 0.32777778 | CB22: 0.20422535 | CC22: 0.15298507 | CD22: -0.0052083333 | CE22: 0.046875 | CF22: 0.12777778
C24: Max AUROC in indicator | D24: 0.21014493 | E24: 0.3359375 | F24: 0.24712644 | G24: 0.32258065 | H24: 0.1954023 | I24: 0.31428571 | J24: 0.26515152 | K24: 0.22486772 | L24: 0.2989418 | M24: 0.24576271 | N24: 0.36148649 | O24: 0.28947368 | P24: 0.20955882 | Q24: 0.28928571 | R24: 0.375 | S24: 0.29545455 | T24: 0.4 | U24: 0.41397849 | V24: 0.10069444 | W24: 0.20522388 | X24: 0.12365591 | Y24: 0.125 | Z24: 0.13793103 | AA24: 0.11594203 | AB24: 0.19921875 | AC24: 0.064516129 | AD24: 0.13978495 | AE24: 0.087301587 | AF24: 0.14236111 | AG24: 0.11184211 | AH24: 0.11267606 | AI24: 0.18115942 | AJ24: 0.16015625 | AK24: 0.16796875 | AL24: 0.12109375 | AM24: 0.084795322 | AN24: 0.24671053 | AO24: 0.3028169 | AP24: 0.37431694 | AQ24: 0.33208955 | AR24: 0.359375 | AS24: 0.16319444 | AT24: 0.12847222 | AU24: 0.2037037 | AV24: 0.15608466 | AW24: 0.22316384 | AX24: 0.28214286 | AY24: 0.26785714 | AZ24: 0.21957672 | BA24: 0.23015873 | BB24: 0.1954023 | BC24: 0.24 | BD24: 0.34507042 | BE24: 0.16544118 | BF24: 0.25746269 | BG24: 0.1875 | BH24: 0.225 | BI24: 0.26041667 | BJ24: 0.23888889 | BK24: 0.27777778 | BL24: 0.27380952 | BM24: 0.22635135 | BN24: 0.35357143 | BO24: 0.21268657 | BP24: 0.28409091 | BQ24: 0.20899471 | BR24: 0.1971831 | BS24: 0.22569444 | BT24: 0.16796875 | BU24: 0.17279412 | BV24: 0.16666667 | BW24: 0.32746479 | BX24: 0.40298507 | BY24: 0.26719577 | BZ24: 0.3852459 | CA24: 0.34444444 | CB24: 0.20422535 | CC24: 0.32222222 | CD24: 0.31355932 | CE24: 0.42982456 | CF24: 0.2
C25: Sum of max AUROC in Mj | D25: 1.3111918 | I25: 1.3490095 | N25: 0.86051899 | Q25: 1.7737188 | V25: 0.69250527 | AA25: 0.60676344 | AF25: 0.36687927 | AI25: 0.71517349 | AN25: 1.6153089 | AS25: 0.87461887 | AX25: 1.1951377 | BC25: 1.1954743 | BH25: 1.2758929 | BM25: 1.285695 | BR25: 0.93030708 | BW25: 1.727336 | CB25: 1.4698315
C26: Number of indicators in Mj | D26: 5 | I26: 5 | N26: 3 | Q26: 5 | V26: 5 | AA26: 5 | AF26: 3 | AI26: 5 | AN26: 5 | AS26: 5 | AX26: 5 | BC26: 5 | BH26: 5 | BM26: 5 | BR26: 5 | BW26: 5 | CB26: 5
C27: Average sum of max AUROC in Mj | D27: 0.26223836 | I27: 0.26980189 | N27: 0.28683966 | Q27: 0.35474375 | V27: 0.13850105 | AA27: 0.12135269 | AF27: 0.12229309 | AI27: 0.1430347 | AN27: 0.32306178 | AS27: 0.17492377 | AX27: 0.23902755 | BC27: 0.23909486 | BH27: 0.25517857 | BM27: 0.25713899 | BR27: 0.18606142 | BW27: 0.3454672 | CB27: 0.29396629
C28: Sum of average max in sector | D28: 1.1736237 | I28: 1.1736237 | N28: 1.1736237 | Q28: 1.1736237 | V28: 0.38214683 | AA28: 0.38214683 | AF28: 0.38214683 | AI28: 0.64102026 | AN28: 0.64102026 | AS28: 0.64102026 | AX28: 0.73330098 | BC28: 0.73330098 | BH28: 0.73330098 | BM28: 0.44320041 | BR28: 0.44320041 | BW28: 0.63943349 | CB28: 0.63943349
C29: Weight indicator in Mj | D29: 0.16027017 | E29: 0.25620775 | F29: 0.18847466 | G29: 0.24602094 | H29: 0.14902648 | I29: 0.23297517 | J29: 0.19655275 | K29: 0.16669099 | L29: 0.22160096 | M29: 0.18218012 | N29: 0.42007961 | O29: 0.3363943 | P29: 0.24352609 | Q29: 0.16309559 | R29: 0.21142021 | S29: 0.1665735 | T29: 0.2255149 | U29: 0.23339579 | V29: 0.14540603 | W29: 0.29634992 | X29: 0.17856314 | Y29: 0.18050404 | Z29: 0.19917687 | AA29: 0.19108275 | AB29: 0.32833018 | AC29: 0.10632831 | AD29: 0.230378 | AE29: 0.14388076 | AF29: 0.38803258 | AG29: 0.30484716 | AH29: 0.30712026 | AI29: 0.25330835 | AJ29: 0.22394042 | AK29: 0.23486434 | AL29: 0.1693208 | AM29: 0.11856609 | AN29: 0.15273272 | AO29: 0.18746687 | AP29: 0.23173087 | AQ29: 0.20558888 | AR29: 0.22248066 | AS29: 0.18658921 | AT29: 0.14688938 | AU29: 0.23290568 | AV29: 0.1784602 | AW29: 0.25515553 | AX29: 0.2360756 | AY29: 0.2241224 | AZ29: 0.18372503 | BA29: 0.19257925 | BB29: 0.16349772 | BC29: 0.20075714 | BD29: 0.2886473 | BE29: 0.13838957 | BF29: 0.21536447 | BG29: 0.15684152 | BH29: 0.1763471 | BI29: 0.20410544 | BJ29: 0.18723272 | BK29: 0.21771246 | BL29: 0.21460229 | BM29: 0.1760537 | BN29: 0.27500413 | BO29: 0.16542537 | BP29: 0.22096292 | BQ29: 0.16255388 | BR29: 0.21195485 | BS29: 0.24260209 | BT29: 0.18055194 | BU29: 0.1857388 | BV29: 0.17915232 | BW29: 0.18957794 | BX29: 0.23329861 | BY29: 0.15468662 | BZ29: 0.22302893 | CA29: 0.1994079 | CB29: 0.13894474 | CC29: 0.21922393 | CD29: 0.21333012 | CE29: 0.29243119 | CF29: 0.13607002
C30: Weight Mj in Sector | D30: 0.22344331 | E30: 0.22344331 | F30: 0.22344331 | G30: 0.22344331 | H30: 0.22344331 | I30: 0.22988791 | J30: 0.22988791 | K30: 0.22988791 | L30: 0.22988791 | M30: 0.22988791 | N30: 0.24440515 | O30: 0.24440515 | P30: 0.24440515 | Q30: 0.30226363 | R30: 0.30226363 | S30: 0.30226363 | T30: 0.30226363 | U30: 0.30226363 | V30: 0.36242889 | W30: 0.36242889 | X30: 0.36242889 | Y30: 0.36242889 | Z30: 0.36242889 | AA30: 0.31755513 | AB30: 0.31755513 | AC30: 0.31755513 | AD30: 0.31755513 | AE30: 0.31755513 | AF30: 0.32001597 | AG30: 0.32001597 | AH30: 0.32001597 | AI30: 0.223136 | AJ30: 0.223136 | AK30: 0.223136 | AL30: 0.223136 | AM30: 0.223136 | AN30: 0.50398062 | AO30: 0.50398062 | AP30: 0.50398062 | AQ30: 0.50398062 | AR30: 0.50398062 | AS30: 0.27288338 | AT30: 0.27288338 | AU30: 0.27288338 | AV30: 0.27288338 | AW30: 0.27288338 | AX30: 0.32596104 | AY30: 0.32596104 | AZ30: 0.32596104 | BA30: 0.32596104 | BB30: 0.32596104 | BC30: 0.32605283 | BD30: 0.32605283 | BE30: 0.32605283 | BF30: 0.32605283 | BG30: 0.32605283 | BH30: 0.34798613 | BI30: 0.34798613 | BJ30: 0.34798613 | BK30: 0.34798613 | BL30: 0.34798613 | BM30: 0.58018672 | BN30: 0.58018672 | BO30: 0.58018672 | BP30: 0.58018672 | BQ30: 0.58018672 | BR30: 0.41981328 | BS30: 0.41981328 | BT30: 0.41981328 | BU30: 0.41981328 | BV30: 0.41981328 | BW30: 0.54027073 | BX30: 0.54027073 | BY30: 0.54027073 | BZ30: 0.54027073 | CA30: 0.54027073 | CB30: 0.45972927 | CC30: 0.45972927 | CD30: 0.45972927 | CE30: 0.45972927 | CF30: 0.45972927
C31: Weight indicator in Sector | D31: 0.035811297 | E31: 0.057247908 | F31: 0.042113404 | G31: 0.054971735 | H31: 0.03329897 | I31: 0.053558176 | J31: 0.0451851 | K31: 0.038320244 | L31: 0.050943383 | M31: 0.041881008 | N31: 0.10266962 | O31: 0.082216498 | P31: 0.059519029 | Q31: 0.049297866 | R31: 0.063904642 | S31: 0.050349112 | T31: 0.068164951 | U31: 0.07054706 | V31: 0.052699348 | W31: 0.10740577 | X31: 0.06471644 | Y31: 0.06541988 | Z31: 0.072187454 | AA31: 0.060679309 | AB31: 0.10426293 | AC31: 0.033765099 | AD31: 0.073157715 | AE31: 0.045690075 | AF31: 0.12417662 | AG31: 0.097555961 | AH31: 0.098283388 | AI31: 0.056522214 | AJ31: 0.04996917 | AK31: 0.05240669 | AL31: 0.037781567 | AM31: 0.026456363 | AN31: 0.076974331 | AO31: 0.094479667 | AP31: 0.11678787 | AQ31: 0.10361281 | AR31: 0.11212594 | AS31: 0.050917094 | AT31: 0.04008367 | AU31: 0.063556089 | AV31: 0.048698822 | AW31: 0.069627704 | AX31: 0.076951447 | AY31: 0.073055171 | AZ31: 0.059887202 | BA31: 0.062773332 | BB31: 0.053293887 | BC31: 0.065457433 | BD31: 0.094114268 | BE31: 0.045122312 | BF31: 0.070220194 | BG31: 0.05113862 | BH31: 0.061366344 | BI31: 0.071025861 | BJ31: 0.06515439 | BK31: 0.075760918 | BL31: 0.07467862 | BM31: 0.10214402 | BN31: 0.15955375 | BO31: 0.095977604 | BP31: 0.12819975 | BQ31: 0.094311605 | BR31: 0.088981461 | BS31: 0.10184758 | BT31: 0.075798103 | BU31: 0.077975613 | BV31: 0.07521052 | BW31: 0.10242341 | BX31: 0.12604441 | BY31: 0.083572654 | BZ31: 0.120496 | CA31: 0.10773425 | CB31: 0.063876965 | CC31: 0.10078366 | CD31: 0.098074101 | CE31: 0.13443918 | CF31: 0.062555373
CG35: =BM35+AX35+AI35+V35+D35+BW35

Sheet Indicators Data
B1: Binary | C1: Corporate | U1: Households | AH1: Government | AW1: Banking | BL1: External | BV1: Недвижимость
B2: Бинарная переменная стрессов | C2: Debt service ratio, % | H2: All Debt to GDP ratio, % | M2: Прирост реального кредита банков ЮЛ (дефлятор ВВП 2018=1) | P2: Складские запасы в промышленности к среднемесячному ОПП, % | U2: Debt_service ratio | Z2: Кредит ФЛ к ВВП | AE2: Прирост реального кредита банков ФЛ (ИПЦ 2018=1) | AH2: Обслуживание внешнего долга органов государственного управления к ВВП, % | AM2: Отношение сальдо консолидированного бюджета к ВВП, % | AR2: Долг сектора государственного управления к ВВП, % (внешний + внутренний) | AW2: Требования банков к экономике к ВВП, % | BB2: Требования банков к депозитам, % | BG2: Леверидж (активы к собственному капиталу), раз | BL2: Счет текущих операций за год, в % к ВВП | BQ2: Валовый внешний долг к ВВП | BV2: Логарифм цен на коммерческую недвижимость, скорректированных на ИПЦ, *100 | CA2: Логарифм цен на жилую недвижимость, скорректированных на ИПЦ
B3: annual SD | C3: 4.6519717 | D3: 4.5874562 | E3: 3.344885 | F3: 4.0662463 | G3: 4.7976559 | H3: 12.289269 | I3: 9.4683274 | J3: 7.1708064 | K3: 8.804995 | L3: 10.966004 | M3: 25.315729 | N3: 21.741362 | O3: 21.298855 | P3: 19.257253 | Q3: 26.908695 | R3: 15.188733 | S3: 21.530215 | T3: 22.187541 | U3: 1.9671837 | V3: 1.4948964 | W3: 1.2372818 | X3: 1.4801426 | Y3: 1.843982 | Z3: 2.9701119 | AA3: 2.7624205 | AB3: 2.1645514 | AC3: 2.6306483 | AD3: 3.2053462 | AE3: 29.186373 | AF3: 22.950311 | AG3: 20.321762 | AH3: 2.9159313 | AI3: 2.3942872 | AJ3: 1.5222995 | AK3: 2.0151551 | AL3: 2.2639326 | AM3: 3.2751737 | AN3: 4.1668575 | AO3: 2.5313914 | AP3: 3.3494982 | AQ3: 3.545354 | AR3: 16.240044 | AS3: 9.9047783 | AT3: 7.5546253 | AU3: 9.3791123 | AV3: 11.553597 | AW3: 8.9834262 | AX3: 10.291725 | AY3: 7.8287166 | AZ3: 9.6046932 | BA3: 11.680181 | BB3: 55.394634 | BC3: 39.448113 | BD3: 28.801685 | BE3: 35.909605 | BF3: 42.783588 | BG3: 1.68852 | BH3: 1.699438 | BI3: 1.0185932 | BJ3: 1.3705545 | BK3: 1.4188324 | BL3: 10.06924 | BM3: 8.350912 | BN3: 4.8284243 | BO3: 6.6101871 | BP3: 7.1536312 | BQ3: 23.416131 | BR3: 15.843223 | BS3: 12.375885 | BT3: 15.076645 | BU3: 18.896752 | BV3: 34.453306 | BW3: 32.336979 | BX3: 17.107065 | BY3: 25.815382 | BZ3: 27.248781 | CA3: 26.111375 | CB3: 21.666264 | CC3: 16.260936 | CD3: 19.668319 | CE3: 22.575179
C4: dsr | D4: dsr1 | E4: dsr2 | F4: dsr_av2 | G4: dsr_av3 | H4: ggr | I4: ggr1 | J4: ggr2 | K4: ggr_av2 | L4: ggr_av3 | M4: rcgr1 | N4: rcgr2 | O4: rcgr3 | P4: invr | Q4: invr1 | R4: invr2 | S4: invr_av2 | T4: invr_av3 | U4: d_srv | V4: d_srv1 | W4: d_srv2 | X4: d_srv_av2 | Y4: d_srv_av3 | Z4: l_gdp | AA4: l_gdp1 | AB4: l_gdp2 | AC4: l_gdp_av2 | AD4: l_gdp_av3 | AE4: rcgr1 | AF4: rcgr2 | AG4: rcgr3 | AH4: exd_s | AI4: exd_s1 | AJ4: exd_s2 | AK4: exd_s_av2 | AL4: exd_s_av3 | AM4: bb_gdp | AN4: bb_gdp1 | AO4: bb_gdp2 | AP4: bb_gdp_av2 | AQ4: bb_gdp_av3 | AR4: ggd | AS4: ggd1 | AT4: ggd2 | AU4: ggd_av2 | AV4: ggd_av3 | AW4: crr | AX4: crr1 | AY4: crr2 | AZ4: crr_av2 | BA4: crr_av3 | BB4: d_as | BC4: d_as1 | BD4: d_as2 | BE4: d_as_av2 | BF4: d_as_av3 | BG4: lvr | BH4: lvr1 | BI4: lvr2 | BJ4: lvr_av2 | BK4: lvr_av3 | BL4: ca | BM4: ca1 | BN4: ca1 | BO4: ca_av2 | BP4: ca_av3 | BQ4: gd_gdp | BR4: gd_gdp1 | BS4: gd_gdp2 | BT4: gd_gdp_av2 | BU4: gd_gdp_av3 | BV4: cest | BW4: cest1 | BX4: cest2 | BY4: cest_av2 | BZ4: cest_av3 | CA4: pest | CB4: pest1 | CC4: pest2 | CD4: pest_av2 | CE4: pest_av3
A5: Date | B5: bnr | C5: dsr | D5: dsr1 | E5: dsr2 | F5: dsr_av2 | G5: dsr_av3 | H5: ggr | I5: ggr1 | J5: ggr2 | K5: ggr_av2 | L5: ggr_av3 | M5: rcgr_c1 | N5: rcgr_c2 | O5: rcgr_c3 | P5: invr | Q5: invr1 | R5: invr2 | S5: invr_av2 | T5: invr_av3 | U5: d_srv | V5: d_srv1 | W5: d_srv2 | X5: d_srv_av2 | Y5: d_srv_av3 | Z5: l_gdp | AA5: l_gdp1 | AB5: l_gdp2 | AC5: l_gdp_av2 | AD5: l_gdp_av3 | AE5: rcgr_h1 | AF5: rcgr_h2 | AG5: rcgr_h3 | AH5: exd_s | AI5: exd_s1 | AJ5: exd_s2 | AK5: exd_s_av2 | AL5: exd_s_av3 | AM5: bb_gdp | AN5: bb_gdp1 | AO5: bb_gdp2 | AP5: bb_gdp_av2 | AQ5: bb_gdp_av3 | AR5: ggd | AS5: ggd1 | AT5: ggd2 | AU5: ggd_av2 | AV5: ggd_av3 | AW5: crr | AX5: crr1 | AY5: crr2 | AZ5: crr_av2 | BA5: crr_av3 | BB5: d_as | BC5: d_as1 | BD5: d_as2 | BE5: d_as_av2 | BF5: d_as_av3 | BG5: lvr | BH5: lvr1 | BI5: lvr2 | BJ5: lvr_av2 | BK5: lvr_av3 | BL5: ca | BM5: ca1 | BN5: ca2 | BO5: ca_av2 | BP5: ca_av3 | BQ5: gd_gdp | BR5: gd_gdp1 | BS5: gd_gdp2 | BT5: gd_gdp_av2 | BU5: gd_gdp_av3 | BV5: cest | BW5: cest1 | BX5: cest2 | BY5: cest_av2 | BZ5: cest_av3 | CA5: pest | CB5: pest1 | CC5: pest2 | CD5: pest_av2 | CE5: pest_av3
A6: 38353 | B6: 0 | H6: 16.675423 | M6: 6.2907127 | N6: 8.8411801 | P6: 59.1 | Z6: 3.8187311 | AE6: 51.524277 | AF6: 52.841901 | AH6: 0.40475931 | AM6: -1.2488304 | AR6: 8.2298964 | AW6: 18.853249 | BB6: 132.67042 | BL6: 2.4342395 | BQ6: 19.209828
A7: 38443 | B7: 0 | H7: 16.382032 | M7: 1.4126309 | N7: 5.7004646 | O7: 6.7834313 | P7: 63.15 | Z7: 4.0644619 | AE7: 49.532693 | AF7: 52.456259 | AG7: 48.62299 | AH7: 0.43814534 | AM7: -1.6460877 | AR7: 7.6678247 | AW7: 18.67585 | BB7: 130.66244 | BG7: 4.9014984 | BL7: 0.83933408 | BQ7: 17.554198
A8: 38534 | B8: 0 | H8: 16.33283 | M8: 0.0072750087 | N8: 7.0487854 | O8: 9.5492335 | P8: 59.05 | Z8: 4.3668435 | AE8: 46.268116 | AF8: 51.111797 | AG8: 49.381424 | AH8: 0.41194889 | AM8: -1.3732718 | AR8: 7.3006273 | AW8: 18.72328 | BB8: 129.78912 | BG8: 5.1501882 | BL8: 0.6544386 | BQ8: 16.877142
A9: 38626 | B9: 0 | C9: 13.16004 | H9: 16.32813 | M9: 2.2997053 | N9: 6.6219865 | O9: 7.2060843 | P9: 54.05 | Z9: 4.707525 | AE9: 45.215353 | AF9: 49.60723 | AG9: 49.549393 | AH9: 0.44572862 | AM9: 0.58508832 | AR9: 7.2359532 | AW9: 18.990089 | BB9: 126.6871 | BG9: 5.1826044 | BL9: -1.5175289 | BQ9: 16.483521 | BV9: -45.134197
A10: 38718 | B10: 0 | C10: 13.245163 | H10: 16.575235 | I10: -0.10018769 | M10: 14.625582 | N10: 10.458147 | O10: 10.769314 | P10: 56.2 | Q10: -2.9 | U10: 2.286064 | Z10: 5.0414813 | AA10: 1.2227502 | AE10: 44.916934 | AF10: 48.220606 | AG10: 50.200246 | AH10: 0.44489534 | AI10: 0.040136031 | AM10: 0.80965225 | AN10: 2.0584827 | AR10: 7.8677004 | AS10: -0.36219596 | AW10: 19.907957 | AX10: 1.0547081 | BB10: 127.69285 | BC10: -4.9775734 | BG10: 5.0544193 | BL10: 0.43100222 | BM10: -2.0032373 | BQ10: 16.171109 | BR10: -3.0387192 | BV10: -32.048771
A11: 38808 | B11: 0 | C11: 12.699248 | H11: 17.216057 | I11: 0.83402451 | M11: 16.510777 | N11: 8.9617038 | O11: 9.303902 | P11: 59.05 | Q11: -4.1 | U11: 2.4397472 | Z11: 5.4044867 | AA11: 1.3400248 | AE11: 44.709732 | AF11: 47.121212 | AG11: 49.874083 | AH11: 0.40794178 | AI11: -0.030203561 | AM11: 0.79283493 | AN11: 2.4389226 | AR11: 7.4696967 | AS11: -0.19812798 | AW11: 21.05811 | AX11: 2.3822603 | BB11: 131.82011 | BC11: 1.1576676 | BG11: 5.2274262 | BH11: 0.32592783 | BL11: 1.8554286 | BM11: 1.0160946 | BQ11: 15.823752 | BR11: -1.7304458 | BV11: -21.398699 | CA11: -42.103447
A12: 38899 | B12: 0 | C12: 13.340778 | H12: 18.479285 | I12: 2.1464542 | M12: 23.074398 | N12: 11.540837 | O12: 12.390656 | P12: 55.2 | Q12: -3.85 | U12: 2.5830591 | Z12: 5.9206695 | AA12: 1.553826 | AE12: 45.555138 | AF12: 45.911627 | AG12: 49.259577 | AH12: 0.39408454 | AI12: -0.017864354 | AM12: 0.10352778 | AN12: 1.4767996 | AR12: 7.4483027 | AS12: 0.14767534 | AW12: 22.5339 | AX12: 3.8106208 | BB12: 134.6714 | BC12: 4.8822879 | BG12: 5.7016375 | BH12: 0.55144924 | BL12: 2.0937165 | BM12: 1.4392779 | BQ12: 16.488053 | BR12: -0.38908907 | BV12: 31.800243 | CA12: -40.269724
A13: 38991 | B13: 0 | C13: 13.424932 | D13: 0.26489147 | H13: 20.242207 | I13: 3.9140769 | M13: 31.683959 | N13: 16.991832 | O13: 14.975977 | P13: 55.1 | Q13: 1.05 | U13: 2.7536503 | Z13: 6.4667516 | AA13: 1.7592266 | AE13: 44.982142 | AF13: 45.098747 | AG13: 48.065534 | AH13: 0.44900435 | AI13: 0.0032757274 | AM13: -1.4321131 | AN13: -2.0172014 | AR13: 8.1688787 | AS13: 0.93292558 | AW13: 24.027624 | AX13: 5.0375358 | BB13: 137.1408 | BC13: 10.453695 | BG13: 5.7799677 | BH13: 0.5973633 | BL13: 3.7540551 | BM13: 5.271584 | BQ13: 17.598536 | BR13: 1.1150152 | BV13: 32.548217 | BW13: 77.682414 | CA13: -38.444899
A14: 39083 | B14: 0 | C14: 14.017774 | D14: 0.77261072 | H14: 21.924816 | I14: 5.3495804 | J14: 2.6246964 | K14: 4.6459158 | M14: 36.496466 | N14: 25.561024 | O14: 19.137587 | P14: 59.8 | Q14: 3.6 | R14: 0.35 | S14: 2.1875 | U14: 2.9764717 | V14: 0.69040771 | Z14: 6.8191671 | AA14: 1.7776858 | AB14: 1.500218 | AC14: 1.8452983 | AE14: 42.62421 | AF14: 43.770572 | AG14: 46.35514 | AH14: 0.39751233 | AI14: -0.047383005 | AJ14: -0.0036234868 | AK14: -0.027051189 | AM14: -2.7861548 | AN14: -3.595807 | AO14: -0.76866217 | AP14: -2.3600048 | AR14: 8.1188797 | AS14: 0.25117924 | AT14: -0.05550836 | AU14: 0.44526966 | AW14: 26.368379 | AX14: 6.4604214 | AY14: 3.7575647 | AZ14: 6.0221213 | BB14: 149.67351 | BC14: 21.980654 | BD14: 8.5015404 | BE14: 18.281725 | BG14: 5.6616065 | BH14: 0.60718722 | BL14: 5.3531317 | BM14: 4.9221295 | BN14: 1.4594461 | BO14: 4.035046 | BQ14: 19.132312 | BR14: 2.9612037 | BS14: -0.038757768 | BT14: 2.1065451 | BV14: 29.289973 | BW14: 61.338744 | CA14: -31.589411
A15: 39173 | B15: 0 | C15: 16.174563 | D15: 3.4753144 | H15: 23.041693 | I15: 5.8256357 | J15: 3.3298301 | K15: 5.1066185 | M15: 37.305241 | N15: 26.908009 | O15: 18.40955 | P15: 61.45 | Q15: 2.4 | R15: -0.85 | S15: 3.75 | U15: 3.1902437 | V15: 0.75049657 | Z15: 7.0756237 | AA15: 1.671137 | AB15: 1.5055809 | AC15: 1.7267004 | AE15: 39.926943 | AF15: 42.318337 | AG15: 44.723123 | AH15: 0.37543675 | AI15: -0.032505034 | AJ15: -0.031354297 | AK15: -0.048220903 | AM15: -2.5001316 | AN15: -3.2929665 | AO15: -0.42702195 | AP15: -1.881816 | AR15: 7.4248061 | AS15: -0.044890594 | AT15: -0.12150928 | AU15: -0.2349268 | AW15: 27.507404 | AX15: 6.449294 | AY15: 4.4157772 | AZ15: 6.2217556 | BB15: 156.55514 | BC15: 24.735031 | BD15: 12.946349 | BE15: 23.037971 | BG15: 5.8983237 | BH15: 0.67089753 | BI15: 0.49841268 | BJ15: 0.56590518 | BL15: 5.7497351 | BM15: 3.8943065 | BN15: 2.4552005 | BO15: 4.0667879 | BQ15: 21.050502 | BR15: 5.2267505 | BS15: 1.7481523 | BT15: 4.0344246 | BV15: 30.692489 | BW15: 52.091188 | CA15: -17.894371 | CB15: 24.209076
A16: 39264 | B16: 0 | C16: 18.277911 | D16: 4.9371328 | H16: 23.761352 | I16: 5.2820675 | J16: 3.7142609 | K16: 4.9938206 | M16: 34.41798 | N16: 28.746189 | O16: 19.166551 | P16: 58.65 | Q16: 3.45 | R16: -0.2 | S16: 1.1625 | U16: 3.3580052 | V16: 0.77494602 | Z16: 7.4189492 | AA16: 1.4982796 | AB16: 1.5260528 | AC16: 1.6936306 | AE16: 34.691156 | AF16: 40.123147 | AG16: 42.17147 | AH16: 0.36113063 | AI16: -0.032953905 | AJ16: -0.025409129 | AK16: -0.054688443 | AM16: -2.4531495 | AN16: -2.5566772 | AO16: -0.53993881 | AP16: -1.7280785 | AR16: 7.310368 | AS16: -0.13793465 | AT16: 0.0048703484 | AU16: -0.3189876 | AW16: 28.239442 | AX16: 5.7055413 | AY16: 4.758081 | AZ16: 5.8498488 | BB16: 158.71795 | BC16: 24.046541 | BD16: 14.464415 | BE16: 21.964193 | BG16: 6.1965551 | BH16: 0.49491757 | BI16: 0.5231834 | BJ16: 0.73953334 | BL16: 6.3120975 | BM16: 4.218381 | BN16: 2.8288294 | BO16: 4.0153501 | BQ16: 21.865528 | BR16: 5.377475 | BS16: 2.4941929 | BT16: 4.4124118 | BV16: -7.843158 | BW16: -39.643401 | CA16: -5.0858263 | CB16: 35.183898
A17: 39356 | B17: 0 | C17: 20.64782 | D17: 7.2228879 | E17: 3.7438897 | F17: 6.3552686 | H17: 25.040424 | I17: 4.7982168 | J17: 4.3561469 | K17: 5.3443269 | M17: 27.025573 | N17: 29.354766 | O17: 20.336412 | P17: 53.4 | Q17: -1.7 | R17: -0.325 | S17: -4.0375 | U17: 3.5138487 | V17: 0.76019839 | Z17: 7.7915676 | AA17: 1.324816 | AB17: 1.5420213 | AC17: 1.6847358 | AE17: 28.81339 | AF17: 36.897766 | AG17: 39.670295 | AH17: 0.50235061 | AI17: 0.053346256 | AJ17: 0.028310992 | AK17: 0.092883815 | AM17: -0.43446455 | AN17: 0.99764851 | AO17: -0.50977643 | AP17: 0.42559115 | AR17: 8.353904 | AS17: 0.18502526 | AT17: 0.55897542 | AU17: 0.7233308 | AW17: 29.266775 | AX17: 5.2391509 | AY17: 5.1383433 | AZ17: 5.6876621 | BB17: 154.17769 | BC17: 17.036892 | BD17: 13.745294 | BE17: 13.807834 | BG17: 6.288273 | BH17: 0.50830524 | BI17: 0.55283427 | BJ17: 0.70045542 | BL17: 6.6549305 | BM17: 2.9008755 | BN17: 4.0862297 | BO17: 3.6509758 | BQ17: 24.434144 | BR17: 6.8356073 | BS17: 3.9753113 | BT17: 6.3574794 | BV17: -0.48920623 | BW17: -33.037423 | BX17: 22.322495 | BY17: -2.7274682 | CA17: 4.9622551 | CB17: 43.407154
A18: 39448 | B18: 0 | C18: 22.653454 | D18: 8.63568 | E18: 4.7041454 | F18: 7.4249306 | H18: 26.290964 | I18: 4.366148 | J18: 4.8578642 | K18: 5.5058302 | L18: 6.9576734 | M18: 24.252221 | N18: 30.374344 | O18: 25.124756 | P18: 51.55 | Q18: -8.25 | R18: -2.325 | S18: -5.80625 | T18: -6.3 | U18: 3.6276274 | V18: 0.65115573 | W18: 0.67078172 | X18: 0.7399912 | Z18: 8.0105638 | AA18: 1.1913967 | AB18: 1.4845413 | AC18: 1.5182267 | AD18: 2.269209 | AE18: 25.878325 | AF18: 34.251267 | AG18: 37.80649 | AH18: 0.50125969 | AI18: 0.10374736 | AJ18: 0.028182178 | AK18: 0.084715152 | AL18: 0.081848152 | AM18: -0.72159651 | AN18: 2.0645583 | AO18: -0.76562438 | AP18: 0.26590329 | AQ18: 0.24366183 | AR18: 10.726639 | AS18: 2.607759 | AT18: 1.4294691 | AU18: 2.9563216 | AV18: 3.0102355 | AW18: 29.982404 | AX18: 3.6140252 | AY18: 5.0372233 | AZ18: 5.1187049 | BA18: 7.136399 | BB18: 150.08425 | BC18: 0.41074588 | BD18: 11.1957 | BE18: 6.2780716 | BF18: 10.896041 | BG18: 6.5190988 | BH18: 0.85749222 | BI18: 0.73233972 | BJ18: 0.79307264 | BL18: 5.8676016 | BM18: 0.51446988 | BN18: 2.7182997 | BO18: 1.8420894 | BP18: 2.9830532 | BQ18: 27.177881 | BR18: 8.045569 | BS18: 5.5033863 | BT18: 8.1073894 | BU18: 8.620496 | BV18: 6.6351422 | BW18: -22.654831 | BX18: 19.341957 | BY18: -1.1837436 | CA18: 8.7623587 | CB18: 40.35177
A19: 39539 | B19: 0 | C19: 21.476071 | D19: 5.3015082 | E19: 4.3884113 | F19: 5.0715108 | H19: 26.644374 | I19: 3.6026819 | J19: 4.7141588 | K19: 4.6447749 | L19: 6.509789 | M19: 17.567241 | N19: 27.436241 | O19: 23.79442 | P19: 51.4 | Q19: -10.05 | R19: -3.825 | S19: -5.375 | T19: -5.8208333 | U19: 3.6711736 | V19: 0.48092984 | W19: 0.61571321 | X19: 0.61584191 | Z19: 8.2901858 | AA19: 1.2145621 | AB19: 1.4428496 | AC19: 1.4267134 | AD19: 2.1995116 | AE19: 26.168854 | AF19: 33.047899 | AG19: 36.935176 | AH19: 0.49930544 | AI19: 0.1238687 | AJ19: 0.045681831 | AK19: 0.075715357 | AL19: 0.071852203 | AM19: -1.5016271 | AN19: 0.99850445 | AO19: -1.147231 | AP19: -0.32272121 | AQ19: -0.58030493 | AR19: 10.037498 | AS19: 2.6126923 | AT19: 1.2839008 | AU19: 1.9098141 | AV19: 2.1130334 | AW19: 31.64562 | AX19: 4.1382154 | AY19: 5.2937547 | AZ19: 5.5226148 | BA19: 7.8721851 | BB19: 157.92951 | BC19: 1.3743779 | BD19: 13.054704 | BE19: 11.32441 | BF19: 17.290152 | BG19: 6.8756365 | BH19: 0.97731279 | BI19: 0.82410516 | BJ19: 0.96652545 | BK19: 1.2455033 | BL19: 6.0248883 | BM19: 0.27515318 | BN19: 2.0847298 | BO19: 1.3198013 | BP19: 2.8542264 | BQ19: 26.713033 | BR19: 5.6625307 | BS19: 5.4446406 | BT19: 6.2666946 | BU19: 7.4916433 | BV19: 8.8081578 | BW19: -21.884331 | BX19: 15.103428 | BY19: -3.8462173 | CA19: 5.2491375 | CB19: 23.143508 | CC19: 23.676292 | CD19: 25.457021
A20: 39630 | B20: 0 | C20: 19.947858 | D20: 1.6699469 | E20: 3.3035398 | F20: 2.4461949 | H20: 26.448995 | I20: 2.6876425 | J20: 3.984855 | K20: 3.2708554 | L20: 5.4592141 | M20: 16.360293 | N20: 25.389136 | O20: 24.617557 | P20: 49.6 | Q20: -9.05 | R20: -2.8 | S20: -6.21875 | T20: -6.6416667 | U20: 3.665369 | V20: 0.30736388 | W20: 0.54115495 | X20: 0.45610906 | Z20: 8.6753884 | AA20: 1.2564392 | AB20: 1.3773594 | AC20: 1.4512036 | AD20: 2.2325705 | AE20: 29.541766 | AF20: 32.116461 | AG20: 36.59602 | AH20: 0.46474925 | AI20: 0.10361862 | AJ20: 0.035332358 | AK20: 0.029738709 | AL20: 0.032199338 | AM20: -2.1475353 | AN20: 0.30561413 | AO20: -1.1255316 | AP20: -0.68182168 | AQ20: -1.2382515 | AR20: 9.0830575 | AS20: 1.7726894 | AT20: 0.8173774 | AU20: 0.63439793 | AV20: 0.96111963 | AW20: 32.70281 | AX20: 4.4633686 | AY20: 5.084455 | AZ20: 5.2563668 | BA20: 7.8485616 | BB20: 167.55236 | BC20: 8.8344129 | BD20: 16.440477 | BE20: 17.683578 | BF20: 24.64074 | BG20: 7.1281505 | BH20: 0.93159546 | BI20: 0.71325652 | BJ20: 1.0130132 | BK20: 1.3335058 | BL20: 7.0599115 | BM20: 0.74781402 | BN20: 2.4830975 | BO20: 1.8336419 | BP20: 3.4571201 | BQ20: 24.930589 | BR20: 3.0650617 | BS20: 4.2212683 | BT20: 3.1230908 | BU20: 4.9459634 | BV20: 16.88358 | BW20: 24.726738 | BX20: -7.4583313 | BY20: 0.45334796 | CA20: 0.22590377 | CB20: 5.3117301 | CC20: 20.247814 | CD20: 14.514714
A21: 39722 | B21: 0 | C21: 18.468258 | D21: -2.1795617 | E21: 2.5216631 | F21: 0.14071031 | G21: 1.8794571 | H21: 27.44976 | I21: 2.4093368 | J21: 3.6037768 | K21: 3.2754075 | L21: 5.6169663 | M21: 22.710833 | N21: 24.868203 | O21: 27.140122 | P21: 55.2 | Q21: 1.8 | R21: 0.05 | S21: 0.08125 | T21: -0.25416667 | U21: 3.8779545 | V21: 0.36410583 | W21: 0.56215211 | X21: 0.53340583 | Z21: 9.2428739 | AA21: 1.4513064 | AB21: 1.3880612 | AC21: 1.6743493 | AD21: 2.4410106 | AE21: 32.503341 | AF21: 30.658366 | AG21: 35.432958 | AH21: 0.47287937 | AI21: -0.029471239 | AJ21: 0.011937509 | AK21: 0.029035737 | AL21: 0.035929424 | AM21: -1.4269295 | AN21: -0.99246498 | AO21: 0.002591767 | AP21: 0.32016702 | AQ21: -0.45312377 | AR21: 9.9043302 | AS21: 1.5504262 | AT21: 0.86772572 | AU21: 1.2513263 | AV21: 1.6338565 | AW21: 33.959309 | AX21: 4.6925336 | AY21: 4.9658423 | AZ21: 5.2417516 | BA21: 7.9400993 | BB21: 174.0307 | BC21: 19.853007 | BD21: 18.444949 | BE21: 20.051797 | BF21: 27.972142 | BG21: 6.3720342 | BH21: 0.083761228 | BI21: 0.29603324 | BJ21: 0.078582728 | BK21: 0.41255927 | BL21: 8.1558944 | BM21: 1.5009638 | BN21: 2.2009197 | BO21: 2.3088505 | BP21: 4.0193136 | BQ21: 24.436185 | BR21: 0.0020417354 | BS21: 3.4188245 | BT21: 1.5733695 | BU21: 3.7804385 | BV21: 26.903725 | BW21: 27.392931 | BX21: -2.8222457 | BY21: 12.338076 | BZ21: 22.758411 | CA21: -4.006757 | CB21: -8.9690121 | CC21: 17.219071 | CD21: 5.2200996
A22: 39814 | B22: 1 | C22: 18.698334 | D22: -3.9551202 | E22: 2.3402799 | F22: -0.25962949 | G22: 1.6671816 | H22: 30.570673 | I22: 4.2797097 | J22: 4.3229288 | K22: 5.4953762 | L22: 7.8110766 | M22: 31.012043 | N22: 27.632132 | O22: 30.58691 | P22: 76.45 | Q22: 24.9 | R22: 8.325 | S22: 21.31875 | T22: 20.9 | U22: 4.3245341 | V22: 0.69690669 | W22: 0.67403121 | X22: 0.83944739 | Y22: 1.1625996 | Z22: 9.8879945 | AA22: 1.8774307 | AB22: 1.5344137 | AC22: 1.9724545 | AD22: 2.7081854 | AE22: 31.443085 | AF22: 28.660705 | AG22: 33.315207 | AH22: 0.52909298 | AI22: 0.027833288 | AJ22: 0.065790324 | AK22: 0.082264972 | AL22: 0.089880474 | AM22: -0.44069082 | AN22: 0.28090569 | AO22: 1.172732 | AP22: 1.3057578 | AQ22: 0.70078309 | AR22: 14.716939 | AS22: 3.9903005 | AT22: 3.2990297 | AU22: 5.8470038 | AV22: 6.2241007 | AW22: 38.439433 | AX22: 8.4570293 | AY22: 6.0355273 | AZ22: 8.4804154 | BA22: 11.172789 | BB22: 189.23989 | BC22: 39.155641 | BD22: 19.783193 | BE22: 30.649754 | BF22: 39.236037 | BG22: 5.7947277 | BH22: -0.72437104 | BI22: 0.066560592 | BJ22: -0.57273206 | BK22: -0.26386635 | BL22: 11.020645 | BM22: 5.153043 | BN22: 2.8337564 | BO22: 4.6233707 | BP22: 6.0779451 | BQ22: 26.764264 | BR22: -0.4136169 | BS22: 3.8159761 | BT22: 3.0467426 | BU22: 5.4457957 | BV22: 43.114196 | BW22: 36.479054 | BX22: 6.9121116 | BY22: 29.254108 | BZ22: 32.965722 | CA22: -3.9450134 | CB22: -12.707372 | CC22: 13.822199 | CD22: 0.97707535
A23: 39904 | B23: 0 | C23: 19.182676 | D23: -2.2933947 | E23: 1.5040567 | F23: -0.36035741 | G23: 1.6970927 | H23: 33.206088 | I23: 6.561714 | J23: 5.082198 | K23: 7.0500591 | L23: 9.2802052 | M23: 33.577862 | N23: 25.572552 | O23: 29.483448 | P23: 93.2 | Q23: 41.8 | R23: 15.875 | S23: 35.9875 | T23: 35.9625 | U23: 4.7664857 | V23: 1.0953121 | W23: 0.78812098 | X23: 1.1128912 | Y23: 1.4346786 | Z23: 10.36406 | AA23: 2.0738743 | AB23: 1.6442182 | AC23: 2.0649168 | AD23: 2.780375 | AE23: 28.084133 | AF23: 27.126494 | AG23: 31.39331 | AH23: 0.55903161 | AI23: 0.059726166 | AJ23: 0.091797431 | AK23: 0.095756018 | AL23: 0.11280263 | AM23: 1.0919179 | AN23: 2.593545 | AO23: 1.7960247 | AP23: 2.5451835 | AQ23: 2.337587 | AR23: 15.631417 | AS23: 5.5939189 | AT23: 4.1033056 | AU23: 5.9367246 | AV23: 6.567809 | AW23: 40.212605 | AX23: 8.5669856 | AY23: 6.3526005 | AZ23: 8.7447056 | BA23: 11.401671 | BB23: 193.146 | BC23: 35.216481 | BD23: 18.29543 | BE23: 29.61006 | BF23: 38.01322 | BG23: 5.9604112 | BH23: -0.91522534 | BI23: 0.031043725 | BJ23: -0.42368877 | BK23: -0.15987528 | BL23: 12.845886 | BM23: 6.8209978 | BN23: 3.5480755 | BO23: 5.7401732 | BP23: 7.0207165 | BQ23: 30.445963 | BR23: 3.7329297 | BS23: 4.6977302 | BT23: 5.774447 | BU23: 8.2447312 | BV23: 48.369317 | BW23: 39.561159 | BX23: 8.8384141 | BY23: 32.781201 | BZ23: 31.957262 | CA23: -6.6820011 | CB23: -11.931139 | CC23: 5.6061848 | CD23: -5.2154621 | CE23: 6.996315
A24: 39995 | B24: 0 | C24: 20.147829 | D24: 0.19997086 | E24: 0.93495887 | F24: 0.22878087 | G24: 2.1219595 | H24: 35.312668 | I24: 8.8636735 | J24: 5.775658 | K24: 7.8860893 | L24: 10.054282 | M24: 31.798425 | N24: 24.079359 | O24: 27.525566 | P24: 86.2 | Q24: 36.6 | R24: 13.775 | S24: 25.01875 | T24: 26.116667 | U24: 5.1690818 | V24: 1.5037128 | W24: 0.90553835 | X24: 1.3184571 | Y24: 1.6433799 | Z24: 10.604116 | AA24: 1.9287277 | AB24: 1.5925835 | AC24: 1.8939182 | AD24: 2.6071332 | AE24: 20.074578 | AF24: 24.808172 | AG24: 28.1025 | AH24: 0.68707515 | AI24: 0.2223259 | AJ24: 0.16297226 | AK24: 0.2008502 | AL24: 0.22825535 | AM24: 1.4387372 | AN24: 3.5862725 | AO24: 1.9459433 | AP24: 2.4429966 | AQ24: 2.6594828 | AR24: 17.938281 | AS24: 8.8552232 | AT24: 5.3139563 | AU24: 7.2177615 | AV24: 8.1945289 | AW24: 42.348551 | AX24: 9.6457408 | AY24: 7.0545547 | AZ24: 9.2925013 | BA24: 11.941409 | BB24: 203.02636 | BC24: 35.474 | BD24: 22.154206 | BE24: 34.916565 | BF24: 42.783092 | BG24: 6.1778416 | BH24: -0.95030896 | BI24: -0.0093567482 | BJ24: -0.21401931 | BK24: -0.0035269799 | BL24: 12.306031 | BM24: 5.2461193 | BN24: 2.9969666 | BO24: 4.313299 | BP24: 5.5649897 | BQ24: 35.596875 | BR24: 10.666286 | BS24: 6.8656739 | BT24: 9.750927 | BU24: 12.177126 | BV24: 42.766549 | BW24: 25.882969 | BX24: 25.304853 | BY24: 24.968829 | BZ24: 20.540493 | CA24: -10.381908 | CB24: -10.607812 | CC24: -2.6480409 | CD24: -10.316915 | CE24: 0.3446209
A25: 40087 | B25: 0 | C25: 21.817737 | D25: 3.3494786 | E25: 0.58495846 | F25: 1.6649493 | G25: 3.2246135 | H25: 37.051862 | I25: 9.6021012 | J25: 6.005719 | K25: 8.1813683 | L25: 10.390694 | M25: 28.347906 | N25: 25.52937 | O25: 26.028104 | P25: 72.85 | Q25: 17.65 | R25: 9.725 | S25: 8.225 | T25: 10.183333 | U25: 5.4644658 | V25: 1.5865112 | W25: 0.97530854 | X25: 1.3874564 | Y25: 1.723262 | Z25: 10.881595 | AA25: 1.6387212 | AB25: 1.5450138 | AC25: 1.7732514 | AD25: 2.494325 | AE25: 15.542781 | AF25: 24.023061 | AG25: 25.619837 | AH25: 0.58686987 | AI25: 0.1139905 | AJ25: 0.04225963 | AK25: 0.059901854 | AL25: 0.10363419 | AM25: -0.11385232 | AN25: 1.3130772 | AO25: 0.16030612 | AP25: 0.40392129 | AQ25: 0.99562582 | AR25: 20.74281 | AS25: 10.83848 | AT25: 6.1944532 | AU25: 8.6938022 | AV25: 10.124894 | AW25: 43.843407 | AX25: 9.8840979 | AY25: 7.2883158 | AZ25: 9.0237184 | BA25: 11.785044 | BB25: 201.33789 | BC25: 27.307188 | BD25: 23.580098 | BE25: 27.689541 | BF25: 35.398374 | BG25: 6.2935592 | BH25: -0.078474957 | BI25: 0.0026431356 | BJ25: -0.095962431 | BK25: 0.072507041 | BL25: 12.46636 | BM25: 4.3104657 | BN25: 2.9057148 | BO25: 3.7243866 | BP25: 4.8742928 | BQ25: 42.037426 | BR25: 17.60124 | BS25: 8.801641 | BT25: 14.475059 | BU25: 17.025274 | BV25: 31.693486 | BW25: 4.7897611 | BX25: 16.091346 | BY25: 7.5695537 | BZ25: 8.5535712 | CA25: -14.718193 | CB25: -10.711436 | CC25: -9.8402239 | CD25: -13.991189 | CE25: -6.4823149
A26: 40179 | B26: 0 | C26: 23.076513 | D26: 4.3781787 | E26: 0.21152927 | F26: 2.7774857 | G26: 3.7839891 | H26: 38.209211 | I26: 7.6385373 | J26: 5.9591235 | K26: 7.8372876 | L26: 10.147238 | M26: 24.301789 | N26: 27.656916 | O26: 26.522018 | P26: 69.55 | Q26: -6.9 | R26: 9 | S26: 2.49375 | T26: 5.4041667 | U26: 5.6845819 | V26: 1.3600478 | W26: 1.0284772 | X26: 1.3637454 | Y26: 1.7174768 | Z26: 11.253323 | AA26: 1.3653282 | AB26: 1.6213794 | AC26: 1.7587255 | AD26: 2.4981489 | AE26: 16.232827 | AF26: 23.837956 | AG26: 24.518079 | AH26: 0.63382843 | AI26: 0.10473545 | AJ26: 0.066284371 | AK26: 0.096295515 | AL26: 0.13910396 | AM26: 0.98275753 | AN26: 1.4234484 | AO26: 0.85217702 | AP26: 1.4604546 | AQ26: 1.9823806 | AR26: 21.582696 | AS26: 6.8657568 | AT26: 5.4280286 | AU26: 7.9850743 | AV26: 9.9169517 | AW26: 45.902725 | AX26: 7.4632914 | AY26: 7.9601604 | AZ26: 9.2609573 | BA26: 12.193046 | BB26: 205.55753 | BC26: 16.317634 | BD26: 27.736637 | BE26: 26.014157 | BF26: 34.268257 | BG26: 6.2816643 | BH26: 0.48693656 | BI26: -0.11871724 | BJ26: -0.10851817 | BK26: 0.017812794 | BL26: 10.787016 | BM26: -0.23362838 | BN26: 2.4597073 | BO26: 1.318614 | BP26: 2.4689235 | BQ26: 44.05575 | BR26: 17.291485 | BS26: 8.4389342 | BT26: 14.292973 | BU26: 17.007025 | BV26: 11.508041 | BW26: -31.606156 | BX26: 2.4364492 | BY26: -16.638729 | BZ26: -11.560647 | CA26: -20.264043 | CB26: -16.31903 | CC26: -14.513201 | CD26: -17.076984 | CE26: -14.005391
A27: 40269 | B27: 0 | C27: 25.025201 | D27: 5.8425247 | E27: 1.774565 | F27: 4.6732914 | G27: 4.9777823 | H27: 38.183741 | I27: 4.9776522 | J27: 5.7696831 | K27: 6.3220367 | L27: 8.7647353 | M27: 17.257501 | N27: 25.417682 | O27: 22.800868 | P27: 65.95 | Q27: -27.25 | R27: 7.275 | S27: -3.35625 | T27: 0.99166667 | U27: 5.6562794 | V27: 0.88979372 | W27: 0.99255291 | X27: 1.0783236 | Y27: 1.4634984 | Z27: 11.58142 | AA27: 1.21736 | AB27: 1.6456172 | AC27: 1.6814781 | AD27: 2.4567334 | AE27: 16.515541 | AF27: 22.299837 | AG27: 23.589509 | AH27: 0.64069802 | AI27: 0.081666409 | AJ27: 0.070696287 | AK27: 0.086594004 | AL27: 0.12628054 | AM27: 0.84883934 | AN27: -0.24307852 | AO27: 1.1752332 | AP27: 1.1134922 | AQ27: 1.5343864 | AR27: 21.825412 | AS27: 6.1939944 | AT27: 5.8939567 | AU27: 6.870783 | AV27: 9.0376828 | AW27: 47.520197 | AX27: 7.3075921 | AY27: 7.9372888 | AZ27: 8.8883898 | BA27: 12.182657 | BB27: 215.6691 | BC27: 22.5231 | BD27: 28.86979 | BE27: 29.191567 | BF27: 39.722824 | BG27: 6.5448822 | BH27: 0.58447107 | BI27: -0.16537713 | BJ27: 0.18437909 | BK27: 0.22935926 | BL27: 11.131214 | BM27: -1.714672 | BN27: 2.5531629 | BO27: 1.0478852 | BP27: 2.3602978 | BQ27: 43.689352 | BR27: 13.243389 | BS27: 8.4881592 | BT27: 11.816841 | BU27: 14.563673 | BV27: 3.3415766 | BW27: -45.027741 | BX27: -2.7332906 | BY27: -25.414305 | BZ27: -18.245283 | CA27: -21.343726 | CB27: -14.661725 | CC27: -13.296432 | CD27: -14.528367 | CE27: -16.028855
A28: 40360 | B28: 0 | C28: 25.289752 | D28: 5.1419232 | E28: 2.670947 | F28: 4.4942011 | G28: 4.50478 | H28: 39.217074 | I28: 3.9044061 | J28: 6.3840398 | K28: 5.9129495 | L28: 8.5362316 | M28: 14.053529 | N28: 22.925977 | O28: 20.737416 | P28: 57.55 | Q28: -28.65 | R28: 3.975 | S28: -13.575 | T28: -7.7833333 | U28: 5.4507563 | V28: 0.28167444 | W28: 0.89269363 | X28: 0.62466224 | Y28: 1.0524724 | Z28: 11.98152 | AA28: 1.3774034 | AB28: 1.6530656 | AC28: 1.6701732 | AD28: 2.4813498 | AE28: 19.86357 | AF28: 19.969074 | AG28: 23.159971 | AH28: 1.0123366 | AI28: 0.32526148 | AJ28: 0.27379369 | AK28: 0.44055854 | AL28: 0.47581404 | AM28: 1.562122 | AN28: 0.12338487 | AO28: 1.8548287 | AP28: 1.5329666 | AQ28: 1.9685882 | AR28: 21.895043 | AS28: 3.9567623 | AT28: 6.4059927 | AU28: 5.4669251 | AV28: 7.9072636 | AW28: 49.318771 | AX28: 6.9702195 | AY28: 8.3079802 | AZ28: 8.7026409 | BA28: 12.313497 | BB28: 217.24633 | BC28: 14.21997 | BD28: 24.846985 | BE28: 23.551352 | BF28: 36.373894 | BG28: 7.0303182 | BH28: 0.85247668 | BI28: -0.048916141 | BJ28: 0.71115936 | BK28: 0.66091538 | BL28: 12.997054 | BM28: 0.69102375 | BN28: 2.9685715 | BO28: 2.2754348 | BP28: 3.7776815 | BQ28: 44.894681 | BR28: 9.2978051 | BS28: 9.9820456 | BT28: 10.90013 | BU28: 13.882431 | BV28: 6.7688492 | BW28: -35.9977 | BX28: -5.0573654 | BY28: -21.30371 | BZ28: -12.538768 | CA28: -22.223072 | CB28: -11.841164 | CC28: -11.224488 | CD28: -12.083605 | CE28: -16.620754
A29: 40452 | B29: 0 | C29: 26.594993 | D29: 4.7772562 | E29: 4.0633674 | F29: 5.1317056 | G29: 5.2257012 | H29: 41.016226 | I29: 3.9643641 | J29: 6.7832327 | K29: 6.1160911 | L29: 9.0474063 | M29: 14.541239 | N29: 21.444572 | O29: 21.866659 | P29: 58.9 | Q29: -13.95 | R29: 1.85 | S29: -13.21875 | T29: -6.3416667 | U29: 5.2515724 | V29: -0.21289334 | W29: 0.68680895 | X29: 0.202305 | Y29: 0.67889259 | Z29: 12.546593 | AA29: 1.6649978 | AB29: 1.6518595 | AC29: 1.8219801 | AD29: 2.6662089 | AE29: 22.969804 | AF29: 19.256292 | AG29: 23.671975 | AH29: 1.3340519 | AI29: 0.74718206 | AJ29: 0.43058628 | AK29: 0.69382542 | AL29: 0.74326218 | AM29: 1.7058962 | AN29: 1.8197485 | AO29: 1.5664129 | AP29: 1.2130335 | AQ29: 1.7777564 | AR29: 21.904021 | AS29: 1.1612105 | AT29: 5.9998454 | AU29: 3.8744049 | AV29: 6.700852 | AW29: 51.214183 | AX29: 7.3707762 | AY29: 8.627437 | AZ29: 8.5210582 | BA29: 12.452299 | BB29: 214.95575 | BC29: 13.617866 | BD29: 20.462527 | BE29: 15.04903 | BF29: 29.205953 | BG29: 7.2797496 | BH29: 0.98619035 | BI29: 0.4538577 | BJ29: 0.97281976 | BK29: 0.84086648 | BL29: 14.494445 | BM29: 2.0280853 | BN29: 3.1692755 | BO29: 3.0306827 | BP29: 4.7179926 | BQ29: 47.260028 | BR29: 5.2226025 | BS29: 11.411921 | BT29: 10.769966 | BU29: 14.328683 | BV29: 18.824361 | BW29: -12.869126 | BX29: -4.0396823 | BY29: -7.9838569 | BZ29: -1.7009239 | CA29: -23.650752 | CB29: -8.932559 | CC29: -9.8219973 | CD29: -10.705162 | CE29: -16.62033
A30: 40544 | B30: 0 | C30: 25.788481 | D30: 2.7119683 | E30: 3.5450735 | F30: 3.3093519 | G30: 3.9235915 | H30: 41.946599 | I30: 3.7373884 | J30: 5.6879629 | K30: 5.3506562 | L30: 8.6464627 | M30: 9.001291 | N30: 16.65154 | O30: 21.438374 | P30: 58.3 | Q30: -11.25 | R30: -9.075 | S30: -14.28125 | T30: -7.4 | U30: 5.0934567 | V30: -0.59112523 | W30: 0.38446127 | X30: -0.12751302 | Y30: 0.3759665 | Z30: 12.911219 | AA30: 1.6578966 | AB30: 1.5116124 | AC30: 1.7736416 | AD30: 2.6345832 | AE30: 25.255089 | AF30: 20.743958 | AG30: 24.310334 | AH30: 1.3116254 | AI30: 0.67779693 | AJ30: 0.39126619 | AK30: 0.56375229 | AL30: 0.65152717 | AM30: 0.78786058 | AN30: -0.19489695 | AO30: 0.6142757 | AP30: -0.096605297 | AQ30: 0.68135737 | AR30: 22.287194 | AS30: 0.70449798 | AT30: 3.7851274 | AU30: 2.7576165 | AV30: 5.9548485 | AW30: 52.11948 | AX30: 6.2167551 | AY30: 6.8400232 | AZ30: 7.2694957 | BA30: 11.528645 | BB30: 222.62109 | BC30: 17.063563 | BD30: 16.690599 | BE30: 17.598735 | BF30: 31.806451 | BG30: 7.624862 | BH30: 1.3431977 | BI30: 0.91506715 | BJ30: 1.2044678 | BK30: 1.1033559 | BL30: 16.950399 | BM30: 6.1633826 | BN30: 2.9648771 | BO30: 4.6943173 | BP30: 6.5206531 | BQ30: 48.999346 | BR30: 4.9435959 | BS30: 11.117541 | BT30: 9.6563035 | BU30: 14.165843 | BV30: 16.276424 | BW30: 4.768383 | BX30: -13.418886 | BY30: -9.5218734 | BZ30: -5.8583249 | CA30: -27.165482 | CB30: -6.9014383 | CC30: -11.610234 | CD30: -11.764393 | CE30: -17.750643
A31: 40634 | B31: 1 | C31: 24.273766 | D31: -0.75143463 | E31: 2.545545 | F31: 0.90836857 | G31: 2.1476244 | H31: 44.245154 | I31: 6.0614135 | J31: 5.5195328 | K31: 6.2272205 | L31: 9.6403815 | M31: 6.3085359 | N31: 11.783018 | O31: 19.047966 | P31: 54 | Q31: -11.95 | R31: -19.6 | S31: -16.3125 | T31: -12.2625 | U31: 4.9253718 | V31: -0.73090765 | W31: 0.079443032 | X31: -0.39171325 | Y31: 0.085729146 | Z31: 12.534102 | AA31: 0.95268211 | AB31: 1.0850211 | AC31: 1.0186215 | AD31: 1.8490782 | AE31: 12.853571 | AF31: 14.684556 | AG31: 19.151082 | AH31: 1.3365566 | AI31: 0.69585857 | AJ31: 0.38876249 | AK31: 0.49086697 | AL31: 0.60892792 | AM31: -0.91877443 | AN31: -1.7676138 | AO31: -1.0053461 | AP31: -1.9568092 | AQ31: -1.1510657 | AR31: 25.5388 | AS31: 3.7133888 | AT31: 4.9536916 | AU31: 5.0629413 | AV31: 8.2430756 | AW31: 53.761207 | AX31: 6.2410093 | AY31: 6.7743007 | AZ31: 7.2012168 | BA31: 11.325616 | BB31: 224.28839 | BC31: 8.6192983 | BD31: 15.571199 | BE31: 15.09339 | BF31: 27.429019 | BG31: 8.6977264 | BH31: 2.1528442 | BI31: 1.3686576 | BJ31: 2.0485654 | BK31: 2.0840733 | BL31: 14.325876 | BM31: 3.1946618 | BN31: 0.73999489 | BO31: 1.3285752 | BP31: 2.9725639 | BQ31: 49.598725 | BR31: 5.909373 | BS31: 9.5763809 | BT31: 7.4762972 | BU31: 12.946767 | BV31: 16.547386 | BW31: 13.20581 | BX31: -15.910965 | BY31: -5.896189 | BZ31: -6.3908022 | CA31: -25.776497 | CB31: -4.432771 | CC31: -9.547248 | CD31: -7.4728501 | CE31: -13.367672
A32: 40725 | B32: 0 | C32: 25.275883 | D32: -0.01386842 | E32: 2.5640274 | F32: 1.2740995 | G32: 2.9166003 | H32: 44.384571 | I32: 5.1674968 | J32: 4.5359515 | K32: 4.9867543 | L32: 8.3130668 | M32: 2.3522397 | N32: 8.2028844 | O32: 16.068065 | P32: 54.1 | Q32: -3.45 | R32: -16.05 | S32: -11.3125 | T32: -12.379167 | U32: 4.8739884 | V32: -0.57676791 | W32: -0.14754673 | X32: -0.46295739 | Y32: -0.070170748 | Z32: 11.688722 | AA32: -0.29279712 | AB32: 0.54230315 | AC32: -0.098013572 | AD32: 0.65003869 | AE32: -8.1055473 | AF32: 5.8790114 | AG32: 10.610867 | AH32: 1.246142 | AI32: 0.23380534 | AJ32: 0.27953341 | AK32: 0.30326172 | AL32: 0.44874237 | AM32: -1.6767528 | AN32: -3.2388749 | AO32: -1.557745 | AP32: -2.4634511 | AQ32: -1.9576152 | AR32: 25.574263 | AS32: 3.6792205 | AT32: 3.8179914 | AU32: 3.8599813 | AV32: 6.9867633 | AW32: 52.60905 | AX32: 3.2902793 | AY32: 5.1302494 | AZ32: 4.3554849 | BA32: 8.3304934 | BB32: 208.94539 | BC32: -8.3009373 | BD32: 2.9595164 | BE32: -4.1424127 | BF32: 6.5561099 | BG32: 9.748428 | BH32: 2.7181098 | BI32: 1.7852932 | BJ32: 2.7571025 | BK32: 2.9829341 | BL32: 10.852208 | BM32: -2.1448465 | BN32: -0.72691136 | BO32: -2.3300914 | BP32: -1.192853 | BQ32: 50.4116 | BR32: 5.5169193 | BS32: 7.4073622 | BT32: 5.8950772 | BU32: 11.852501 | BV32: 7.5095129 | BW32: 0.74066367 | BX32: -17.628518 | BY32: -10.956321 | BZ32: -16.073611 | CA32: -24.003992 | CB32: -1.7809201 | CC32: -6.8110419 | CD32: -3.3135328 | CE32: -9.0096969
A33: 40817 | B33: 0 | C33: 25.547608 | D33: -1.047385 | E33: 1.8649356 | F33: 0.90481723 | G33: 2.7443227 | H33: 44.707972 | I33: 3.6917459 | J33: 3.828055 | K33: 4.176167 | L33: 7.141836 | M33: -15.271475 | N33: -0.36511787 | O33: 9.20589 | P33: 55.85 | Q33: -3.05 | R33: -8.5 | S33: -5.55 | T33: -11.004167 | U33: 4.716089 | V33: -0.53548341 | W33: -0.37418837 | X33: -0.58397004 | Y33: -0.32878836 | Z33: 10.050451 | AA33: -2.4961422 | AB33: -0.4155722 | AC33: -1.8718611 | AD33: -1.2393442 | AE33: -33.482878 | AF33: -5.2565369 | AG33: 1.6765691 | AH33: 1.0516756 | AI33: -0.28237628 | AJ33: 0.23240289 | AK33: 0.038912048 | AL33: 0.18915999 | AM33: -2.6862708 | AN33: -4.392167 | AO33: -1.2862093 | AP33: -3.0835328 | AQ33: -3.0063651 | AR33: 31.780072 | AS33: 9.876051 | AT33: 5.5186307 | AU33: 9.111292 | AV33: 11.818305 | AW33: 49.706529 | AX33: -1.5076544 | AY33: 2.9315609 | AZ33: 0.17040127 | BA33: 3.7691188 | BB33: 185.49636 | BC33: -29.459391 | BD33: -7.9207623 | BE33: -28.331321 | BF33: -20.342339 | BG33: 8.1332877 | BH33: 0.85353815 | BI33: 0.91986425 | BJ33: 0.69563899 | BK33: 1.1494374 | BL33: 7.9675982 | BM33: -6.5268472 | BN33: -2.2493809 | BO33: -5.0329734 | BP33: -4.3934876 | BQ33: 52.750467 | BR33: 5.4904392 | BS33: 5.3565209 | BT33: 6.382104 | BU33: 12.067951 | BV33: -5.4855267 | BW33: -24.309887 | BX33: -18.589507 | BY33: -19.544231 | BZ33: -28.287479 | CA33: -17.123662 | CB33: 6.5270899 | CC33: -1.2027346 | CD33: 5.2695578 | CE33: -0.1102087
A34: 40909 | B34: 0 | C34: 24.502959 | D34: -1.2855218 | E34: 0.71322324 | F34: -0.60606533 | G34: 1.1097282 | H34: 42.685352 | I34: 0.73875273 | J34: 2.2380706 | K34: 1.1965334 | L34: 3.6810319 | M34: -6.2140009 | N34: 1.3936451 | O34: 9.0296931 | P34: 52.35 | Q34: -5.95 | R34: -8.6 | S34: -6.925 | T34: -14.558333 | U34: 4.2556108 | V34: -0.83784584 | W34: -0.71448554 | X34: -0.95090116 | Y34: -0.85911112 | Z34: 8.7551585 | AA34: -4.1560607 | AB34: -1.2490821 | AC34: -3.0632602 | AD34: -2.6019345 | AE34: -42.653794 | AF34: -8.6993526 | AG34: -0.38862602 | AH34: 1.1840831 | AI34: -0.12754231 | AJ34: 0.27512731 | AK34: 0.11321873 | AL34: 0.27333437 | AM34: -3.1493594 | AN34: -3.9372199 | AO34: -2.0660584 | AP34: -3.2250691 | AQ34: -3.3645085 | AR34: 32.002884 | AS34: 9.7156898 | AT34: 5.2100939 | AU34: 7.954446 | AV34: 10.218138 | AW34: 43.184324 | AX34: -8.9351555 | AY34: -1.3592002 | AZ34: -7.0846933 | BA34: -4.0653538 | BB34: 155.99544 | BC34: -66.62565 | BD34: -24.781043 | BE34: -55.852052 | BF34: -50.798733 | BG34: 6.8097393 | BH34: -0.81512269 | BI34: 0.26403752 | BJ34: -0.85787548 | BK34: -0.32088218 | BL34: 2.896252 | BM34: -14.054147 | BN34: -3.9453821 | BO34: -9.5419743 | BP34: -9.4491423 | BQ34: 55.695555 | BR34: 6.6962087 | BS34: 5.8199023 | BT34: 7.988061 | BU34: 12.653515 | BV34: -7.0383029 | BW34: -23.314726 | BX34: -9.2731717 | BY34: -16.449631 | BZ34: -27.141151 | CA34: -11.791087 | CB34: 15.374395 | CC34: 4.2364783 | CD34: 10.902816 | CE34: 6.3154416
... A91: 46113 | B91: 0 | C91: 24.730656 | D91: 0.98597847 | E91: 0.45396216 | F91: 0.71674127 | G91: 0.58313265 | H91: 26.452444 | I91: -0.95979446 | J91: -1.1581694 | K91: -1.0121778 | L91: -1.8047247 | M91: -3.4647589 | N91: -2.2783946 | O91: -1.4703239 | P91: 83.8 | Q91: 3.6 | R91: 8.775 | S91: 10.45 | T91: 11.7875 | U91: 5.0730472 | V91: -0.13202706 | W91: 0.075782848 | X91: -0.0040079464 | Y91: 0.019490417 | Z91: 10.120893 | AA91: -0.088397807 | AB91: 0.38208169 | AC91: 0.14786874 | AD91: 0.47261886 | AE91: 7.1682019 | AF91: 11.256105 | AG91: 12.893481 | AH91: 5.1957047 | AI91: 2.2383181 | AJ91: 0.79105857 | AK91: 2.1398621 | AL91: 2.0647529 | AM91: -1.643901 | AN91: -0.16394647 | AO91: -0.43647193 | AP91: -0.66479385 | AQ91: -0.7165608 | AR91: 25.579984 | AS91: -5.9915181 | AT91: -4.582167 | AU91: -6.2880972 | AV91: -7.7949228 | AW91: 36.398517 | AX91: -0.95829044 | AY91: -0.36264001 | AZ91: -0.54315757 | BA91: -0.53093652 | BB91: 124.51236 | BC91: -5.4079085 | BD91: -3.1761689 | BE91: -4.3296623 | BF91: -5.0010346 | BG91: 5.7162289 | BH91: 0.0085407283 | BI91: -0.0019207015 | BJ91: 0.039282713 | BK91: 0.010733638 | BL91: 1.2074518 | BM91: -0.94274695 | BN91: 0.28109608 | BO91: -0.37286981 | BP91: 0.043311986 | BQ91: 35.218884 | BR91: -9.559952 | BS91: -7.1459719 | BT91: -8.9556017 | BU91: -10.884557 | BV91: 8.2772763 | BW91: 4 | BX91: 12.03338 | BY91: 22.43077 | BZ91: 22.892488 | CA91: 24.045634 | CB91: 7.6774713 | CC91: 6.8085809 | CD91: 8.671313 | CE91: 13.76104

Sheet Threshold
B1: Binary | C1: Corporate | U1: Households | AH1: Government | AW1: Banking | BL1: External | BV1: Недвижимость
B2: Binary | C2: Debt service ratio, % | H2: All Debt to GDP ratio, % | M2: Прирост реального кредита банков ЮЛ (дефлятор ВВП 2018=1) | P2: Складские запасы в промышленности к среднемесячному ОПП, % | U2: Debt_service ratio | Z2: Кредит ФЛ к ВВП | AE2: Прирост реального кредита банков ФЛ (ИПЦ 2018=1) | AH2: Обслуживание внешнего долга органов государственного управления к ВВП, % | AM2: Отношение сальдо консолидированного бюджета к ВВП, % | AR2: Долг сектора государственного управления к ВВП, % (внешний + внутренний) | AW2: Требования банков к экономике к ВВП, % | BB2: Требования банков к депозитам, % | BG2: Леверидж (активы к собственному капиталу), раз | BL2: Счет текущих операций за год, в % к ВВП | BQ2: Валовый внешний долг к ВВП | BV2: Логарифм цен на коммерческую недвижимость, скорректированных на дефлятор ВВП, *100 | CA2: Логарифм цен на жилую недвижимость, скорректированных на ИПЦ
A5: Date | B5: bnr | C5: dsr | D5: dsr1 | E5: dsr2 | F5: dsr_av2 | G5: dsr_av3 | H5: ggr | I5: ggr1 | J5: ggr2 | K5: ggr_av2 | L5: ggr_av3 | M5: rcgr_c1 | N5: rcgr_c2 | O5: rcgr_c3 | P5: invr | Q5: invr1 | R5: invr2 | S5: invr_av2 | T5: invr_av3 | U5: d_srv | V5: d_srv1 | W5: d_srv2 | X5: d_srv_av2 | Y5: d_srv_av3 | Z5: l_gdp | AA5: l_gdp1 | AB5: l_gdp2 | AC5: l_gdp_av2 | AD5: l_gdp_av3 | AE5: rcgr_h1 | AF5: rcgr_h2 | AG5: rcgr_h3 | AH5: exd_s | AI5: exd_s1 | AJ5: exd_s2 | AK5: exd_s_av2 | AL5: exd_s_av3 | AM5: bb_gdp | AN5: bb_gdp1 | AO5: bb_gdp2 | AP5: bb_gdp_av2 | AQ5: bb_gdp_av3 | AR5: ggd | AS5: ggd1 | AT5: ggd2 | AU5: ggd_av2 | AV5: ggd_av3 | AW5: crr | AX5: crr1 | AY5: crr2 | AZ5: crr_av2 | BA5: crr_av3 | BB5: d_as | BC5: d_as1 | BD5: d_as2 | BE5: d_as_av2 | BF5: d_as_av3 | BG5: lvr | BH5: lvr1 | BI5: lvr2 | BJ5: lvr_av2 | BK5: lvr_av3 | BL5: ca | BM5: ca1 | BN5: ca2 | BO5: ca_av2 | BP5: ca_av3 | BQ5: gd_gdp | BR5: gd_gdp1 | BS5: gd_gdp2 | BT5: gd_gdp_av2 | BU5: gd_gdp_av3 | BV5: cest | BW5: cest1 | BX5: cest2 | BY5: cest_av2 | BZ5: cest_av3 | CA5: pest | CB5: pest1 | CC5: pest2 | CD5: pest_av2 | CE5: pest_av3
A6: 38353 | B6: 0 | C6: 18 | H6: 18.074168 | M6: 15.214313 | N6: 14.400978 | P6: 65.578866 | U6: 11 | Z6: 4.0144385 | AE6: 47.452953 | AF6: 48.225954 | AH6: 1.4664637 | AM6: 0.62209932 | AR6: 7.0686775 | AW6: 19.27479 | BB6: 135.5174 | BL6: 2.3 | BQ6: 19.726616
A7: 38443 | B7: 0 | C7: 18 | H7: 18.463876 | M7: 15.827992 | N7: 14.851624 | O7: 14.274887 | P7: 65.578866 | U7: 11 | Z7: 4.3978406 | AE7: 46.777356 | AF7: 47.773835 | AG7: 48.273912 | AH7: 1.8356849 | AM7: 0.63387503 | AR7: 7.2449233 | AW7: 20.114835 | BB7: 135.5174 | BG7: 6.6089281 | BL7: 2.3 | BQ7: 19.674409
A8: 38534 | B8: 0 | C8: 18 | H8: 18.911651 | M8: 16.521666 | N8: 15.380846 | O8: 14.660373 | P8: 65.578866 | U8: 11 | Z8: 4.7811204 | AE8: 45.979159 | AF8: 47.211474 | AG8: 47.884708 | AH8: 2.220921 | AM8: 0.64595891 | AR8: 7.4416719 | AW8: 21.004087 | BB8: 135.5174 | BG8: 6.6089281 | BL8: 2.3 | BQ8: 19.712676
A9: 38626 | B9: 0 | C9: 18 | H9: 19.422453 | M9: 17.281659 | N9: 15.983477 | O9: 15.11279 | P9: 65.578866 | U9: 11 | Z9: 5.1639472 | AE9: 45.058859 | AF9: 46.533017 | AG9: 47.404029 | AH9: 2.2666885 | AM9: 0.65861253 | AR9: 7.6649841 | AW9: 21.945708 | BB9: 135.5174 | BG9: 6.6089281 | BL9: 2.3 | BQ9: 19.852427 | BV9: -5.6221092
A10: 38718 | B10: 0 | C10: 18 | D10: 0 | H10: 19.999629 | I10: 1.9254605 | M10: 18.083974 | N10: 16.649143 | O10: 15.628644 | P10: 65.578866 | Q10: 0 | U10: 11 | V10: 0 | Z10: 5.5457314 | AA10: 1.531293 | AE10: 44.017135 | AF10: 45.735044 | AG10: 46.823014 | AH10: 2.3207128 | AI10: 0.85424912 | AM10: 0.67207376 | AN10: 0.049974437 | AR10: 7.9208323 | AS10: 0.85215471 | AW10: 22.941432 | AX10: 3.6666416 | BB10: 135.5174 | BC10: 0 | BG10: 6.6089281 | BL10: 2.3 | BM10: 0 | BQ10: 20.102903 | BR10: 0.37628686 | BV10: -3.0427927
A11: 38808 | B11: 0 | C11: 18 | D11: 0 | H11: 20.644593 | I11: 2.1807166 | M11: 18.89525 | N11: 17.361621 | O11: 16.199499 | P11: 65.578866 | Q11: 0 | U11: 11 | V11: 0 | Z11: 5.9255982 | AA11: 1.5277576 | AE11: 42.854761 | AF11: 44.816058 | AG11: 46.134143 | AH11: 2.384216 | AI11: 0.54853108 | AM11: 0.68651094 | AN11: 0.0526359 | AR11: 8.2149208 | AS11: 0.96999748 | AW11: 23.991147 | AX11: 3.8763125 | BB11: 135.5174 | BC11: 0 | BG11: 6.6089281 | BH11: 0 | BL11: 2.3 | BM11: 0 | BQ11: 20.471236 | BR11: 0.79682715 | BV11: -0.4881712 | CA11: -24.784848
A12: 38899 | B12: 0 | C12: 18 | D12: 0 | H12: 21.356619 | I12: 2.4449677 | M12: 19.679965 | N12: 18.100815 | O12: 16.813885 | P12: 65.578866 | Q12: 0 | U12: 11 | V12: 0 | Z12: 6.3023574 | AA12: 1.521237 | AE12: 41.573076 | AF12: 43.776117 | AG12: 45.332008 | AH12: 2.4583079 | AI12: 0.23738689 | AM12: 0.70209034 | AN12: 0.056131433 | AR12: 8.5529207 | AS12: 1.1112488 | AW12: 25.092846 | AX12: 4.088759 | BB12: 135.5174 | BC12: 0 | BG12: 6.6089281 | BH12: 0 | BL12: 2.3 | BM12: 0 | BQ12: 20.962104 | BR12: 1.2494283 | BV12: 1.9989315 | CA12: -23.301475
A13: 38991 | B13: 0 | C13: 18 | D13: 0 | H13: 22.132838 | I13: 2.7103848 | M13: 20.401105 | N13: 18.841382 | O13: 17.45602 | P13: 65.578866 | Q13: 0 | U13: 11 | V13: 0 | Z13: 6.6744935 | AA13: 1.5105463 | AE13: 40.174577 | AF13: 42.616718 | AG13: 44.413537 | AH13: 2.5439381 | AI13: 0.27724964 | AM13: 0.71883204 | AN13: 0.060219518 | AR13: 8.9400374 | AS13: 1.2750534 | AW13: 26.242687 | AX13: 4.2969795 | BB13: 135.5174 | BC13: 0 | BG13: 6.6089281 | BH13: 0 | BL13: 2.3 | BM13: 0 | BQ13: 21.577278 | BR13: 1.7248506 | BV13: 4.3626224 | BW13: 9.9847316 | CA13: -21.828926
A14: 39083 | B14: 0 | C14: 18 | D14: 0 | E14: 0 | F14: 0 | H14: 22.968582 | I14: 2.9689527 | J14: 2.4472066 | K14: 3.0928531 | M14: 21.023781 | N14: 19.553878 | O14: 18.107356 | P14: 65.578866 | Q14: 0 | R14: 0 | S14: 0 | U14: 11 | V14: 0 | W14: 0 | X14: 0 | Z14: 7.0402521 | AA14: 1.4945207 | AB14: 1.5129068 | AC14: 1.6895612 | AE14: 38.664251 | AF14: 41.340693 | AG14: 43.378113 | AH14: 2.6417717 | AI14: 0.32105886 | AJ14: 0.58765399 | AK14: 0.45465504 | AM14: 0.73661817 | AN14: 0.064544416 | AO14: 0.057259426 | AP14: 0.069111564 | AR14: 9.380786 | AS14: 1.4599537 | AT14: 1.1560542 | AU14: 1.499665 | AW14: 27.43523 | AX14: 4.4937981 | AY14: 4.0802199 | AZ14: 4.8592884 | BB14: 135.5174 | BC14: 0 | BD14: 0 | BE14: 0 | BG14: 6.6089281 | BH14: 0 | BL14: 2.3 | BM14: 0 | BN14: 0 | BO14: 0 | BQ14: 22.315733 | BR14: 2.21283 | BS14: 1.2945584 | BT14: 2.0557767 | BV14: 6.5656346 | BW14: 9.6084272 | CA14: -20.38863
A15: 39173 | B15: 0 | C15: 18 | D15: 0 | E15: 0 | F15: 0 | H15: 23.858001 | I15: 3.2134082 | J15: 2.6970624 | K15: 3.3704711 | M15: 21.520153 | N15: 20.207701 | O15: 18.747798 | P15: 65.578866 | Q15: 0 | R15: 0 | S15: 0 | U15: 11 | V15: 0 | W15: 0 | X15: 0 | Z15: 7.3977491 | AA15: 1.4721509 | AB15: 1.4999543 | AC15: 1.6688315 | AE15: 37.050088 | AF15: 39.952424 | AG15: 42.227402 | AH15: 2.751988 | AI15: 0.367772 | AJ15: 0.45815154 | AK15: 0.41795784 | AM15: 0.75536217 | AN15: 0.068851239 | AO15: 0.06074357 | AP15: 0.073540708 | AR15: 9.8791992 | AS15: 1.6642785 | AT15: 1.317138 | AU15: 1.7090647 | AW15: 28.66365 | AX15: 4.6725021 | AY15: 4.2744073 | AZ15: 5.0676529 | BB15: 135.5174 | BC15: 0 | BD15: 0 | BE15: 0 | BG15: 6.6089281 | BH15: 0 | BI15: 0 | BJ15: 0 | BL15: 2.3 | BM15: 0 | BN15: 0 | BO15: 0 | BQ15: 23.173958 | BR15: 2.7027215 | BS15: 1.7497743 | BT15: 2.5903621 | BV15: 8.5883169 | BW15: 9.0764881 | CA15: -19.012403 | CB15: 5.7724455
A16: 39264 | B16: 0 | C16: 18 | D16: 0 | E16: 0 | F16: 0 | H16: 24.794595 | I16: 3.4379763 | J16: 2.941472 | K16: 3.6327996 | M16: 21.872051 | N16: 20.776008 | O16: 19.357894 | P16: 65.578866 | Q16: 0 | R16: 0 | S16: 0 | U16: 11 | V16: 0 | W16: 0 | X16: 0 | Z16: 7.7449622 | AA16: 1.4426048 | AB16: 1.4819209 | AC16: 1.6410561 | AE16: 35.342555 | AF16: 38.457815 | AG16: 40.96493 | AH16: 2.8742788 | AI16: 0.4159709 | AJ16: 0.3266789 | AK16: 0.42571084 | AM16: 0.77470459 | AN16: 0.072614246 | AO16: 0.06437284 | AP16: 0.077697232 | AR16: 10.438522 | AS16: 1.8856009 | AT16: 1.4984248 | AU16: 1.9391025 | AW16: 29.920454 | AX16: 4.8276078 | AY16: 4.4581834 | AZ16: 5.2558556 | BB16: 135.5174 | BC16: 0 | BD16: 0 | BE16: 0 | BG16: 6.6089281 | BH16: 0 | BI16: 0 | BJ16: 0 | BL16: 2.3 | BM16: 0 | BN16: 0 | BO16: 0 | BQ16: 24.146452 | BR16: 3.1843478 | BS16: 2.2168881 | BT16: 3.1254126 | BV16: 10.425221 | BW16: 8.4262896 | CA16: -17.739057 | CB16: 5.5624178
A17: 39356 | B17: 0 | C17: 18 | D17: 0 | E17: 0 | F17: 0 | H17: 25.771352 | I17: 3.6385143 | J17: 3.1744496 | K17: 3.8741883 | M17: 22.071173 | N17: 21.236139 | O17: 19.917979 | P17: 65.578866 | Q17: 0 | R17: 0 | S17: 0 | U17: 11 | V17: 0 | W17: 0 | X17: 0 | Z17: 8.0796679 | AA17: 1.4051744 | AB17: 1.4578603 | AC17: 1.6052815 | AE17: 33.553915 | AF17: 36.864246 | AG17: 39.595784 | AH17: 3.0078163 | AI17: 0.46387811 | AJ17: 0.37056388 | AK17: 0.47757853 | AM17: 0.79418378 | AN17: 0.075351738 | AO17: 0.067785628 | AP17: 0.081083215 | AR17: 11.060463 | AS17: 2.1204258 | AT17: 1.6977396 | AU17: 2.186438 | AW17: 31.197429 | AX17: 4.9547419 | AY17: 4.6258607 | AZ17: 5.418285 | BB17: 135.5174 | BC17: 0 | BD17: 0 | BE17: 0 | BG17: 6.6089281 | BH17: 0 | BI17: 0 | BJ17: 0 | BL17: 2.3 | BM17: 0 | BN17: 0 | BO17: 0 | BQ17: 25.226387 | BR17: 3.6491092 | BS17: 2.6869799 | BT17: 3.6511256 | BV17: 12.084714 | BW17: 7.7220914 | BX17: 8.8534115 | BY17: 9.2362572 | CA17: -16.60671 | CB17: 5.2222159
A18: 39448 | B18: 0 | C18: 18 | D18: 0 | E18: 0 | F18: 0 | G18: 0 | H18: 26.780614 | I18: 3.8120323 | J18: 3.3904925 | K18: 4.0898378 | L18: 5.4140841 | M18: 22.117057 | N18: 21.570419 | O18: 20.408271 | P18: 65.578866 | Q18: 0 | R18: 0 | S18: 0 | T18: 0 | U18: 11 | V18: 0 | W18: 0 | X18: 0 | Y18: 0 | Z18: 8.3994386 | AA18: 1.3591866 | AB18: 1.4268536 | AC18: 1.5605872 | AD18: 2.3104254 | AE18: 31.696025 | AF18: 35.180138 | AG18: 38.125804 | AH18: 3.1510985 | AI18: 0.50932681 | AJ18: 0.41519283 | AK18: 0.52821978 | AL18: 0.75336616 | AM18: 0.81319992 | AN18: 0.07658175 | AO18: 0.070563083 | AP18: 0.083152948 | AQ18: 0.11312312 | AR18: 11.74478 | AS18: 2.3639936 | AT18: 1.9119737 | AU18: 2.4463194 | AV18: 3.0941181 | AW18: 32.48531 | AX18: 5.0500801 | AY18: 4.7719391 | AZ18: 5.5497007 | BA18: 7.6666188 | BB18: 135.5174 | BC18: 0 | BD18: 0 | BE18: 0 | BF18: 0 | BG18: 6.6089281 | BH18: 0 | BI18: 0 | BJ18: 0 | BL18: 2.3 | BM18: 0 | BN18: 0 | BO18: 0 | BP18: 0 | BQ18: 26.405509 | BR18: 4.0897765 | BS18: 3.1513032 | BT18: 4.158503 | BU18: 4.9936611 | BV18: 13.563744 | BW18: 6.9981097 | BX18: 8.3032685 | BY18: 8.5019347 | CA18: -15.645569 | CB18: 4.7430613
A19: 39539 | B19: 0 | C19: 18 | D19: 0 | E19: 0 | F19: 0 | G19: 0 | H19: 27.814267 | I19: 3.9562652 | J19: 3.5848367 | K19: 4.2758673 | L19: 5.7221995 | M19: 22.012337 | N19: 21.766245 | O19: 20.809246 | P19: 65.578866 | Q19: 0 | R19: 0 | S19: 0 | T19: 0 | U19: 11 | V19: 0 | W19: 0 | X19: 0 | Y19: 0 | Z19: 8.7016671 | AA19: 1.303918 | AB19: 1.3880345 | AC19: 1.5061022 | AD19: 2.2472372 | AE19: 29.77778 | AF19: 33.413934 | AG19: 36.560876 | AH19: 3.3020163 | AI19: 0.55002836 | AJ19: 0.45890018 | AK19: 0.57533942 | AL19: 0.76389778 | AM19: 0.83120744 | AN19: 0.075845266 | AO19: 0.072348252 | AP19: 0.083519694 | AQ19: 0.11520559 | AR19: 12.489534 | AS19: 2.6103348 | AT19: 2.1373066 | AU19: 2.7130805 | AV19: 3.4491974 | AW19: 33.773625 | AX19: 5.1099755 | AY19: 4.8912388 | AZ19: 5.6450308 | BA19: 7.8540571 | BB19: 135.5174 | BC19: 0 | BD19: 0 | BE19: 0 | BF19: 0 | BG19: 6.6089281 | BH19: 0 | BI19: 0 | BJ19: 0 | BK19: 0 | BL19: 2.3 | BM19: 0 | BN19: 0 | BO19: 0 | BP19: 0 | BQ19: 27.67507 | BR19: 4.5011122 | BS19: 3.6019168 | BT19: 4.6402379 | BU19: 5.7066474 | BV19: 14.851403 | BW19: 6.2630857 | BX19: 7.6697869 | BY19: 7.7137759 | CA19: -14.872361 | CB19: 4.1400412 | CC19: 4.9562433 | CD19: 5.0410909
A20: 39630 | B20: 0 | C20: 18 | D20: 0 | E20: 0 | F20: 0 | G20: 0 | H20: 28.86389 | I20: 4.0692942 | J20: 3.7536352 | K20: 4.4292811 | L20: 5.9926234 | M20: 21.760981 | N20: 21.816516 | O20: 21.104332 | P20: 65.578866 | Q20: 0 | R20: 0 | S20: 0 | T20: 0 | U20: 11 | V20: 0 | W20: 0 | X20: 0 | Y20: 0 | Z20: 8.9835028 | AA20: 1.2385406 | AB20: 1.3405727 | AC20: 1.4409293 | AD20: 2.1704207 | AE20: 27.804436 | AF20: 31.573496 | AG20: 34.906689 | AH20: 3.4584424 | AI20: 0.58416357 | AJ20: 0.50006724 | AK20: 0.61704046 | AL20: 0.79812958 | AM20: 0.84803839 | AN20: 0.073333805 | AO20: 0.072974025 | AP20: 0.082263586 | AQ20: 0.11559218 | AR20: 13.292154 | AS20: 2.8536324 | AT20: 2.3696166 | AU20: 2.9813738 | AV20: 3.8147664 | AW20: 35.050338 | AX20: 5.129884 | AY20: 4.9787459 | AZ20: 5.6989341 | BA20: 7.9925375 | BB20: 135.5174 | BC20: 0 | BD20: 0 | BE20: 0 | BF20: 0 | BG20: 6.6089281 | BH20: 0 | BI20: 0 | BJ20: 0 | BK20: 0 | BL20: 2.3 | BM20: 0 | BN20: 0 | BO20: 0 | BP20: 0 | BQ20: 29.026803 | BR20: 4.8803511 | BS20: 4.0323495 | BT20: 5.0914917 | BU20: 6.3916587 | BV20: 15.932449 | BW20: 5.5072277 | BX20: 6.9667587 | BY20: 6.8773754 | CA20: -14.288559 | CB20: 3.4504981 | CC20: 4.506458 | CD20: 4.3858324
A21: 39722 | B21: 0 | C21: 18 | D21: 0 | E21: 0 | F21: 0 | G21: 0 | H21: 29.920331 | I21: 4.1489793 | J21: 3.8937468 | K21: 4.5473141 | L21: 6.219712 | M21: 21.364182 | N21: 21.717678 | O21: 21.27882 | P21: 65.578866 | Q21: 0 | R21: 0 | S21: 0 | T21: 0 | U21: 11 | V21: 0 | W21: 0 | X21: 0 | Y21: 0 | Z21: 9.241838 | AA21: 1.1621702 | AB21: 1.2836723 | AC21: 1.3641214 | AD21: 2.0785574 | AE21: 25.778997 | AF21: 29.666456 | AG21: 33.169163 | AH21: 3.6181005 | AI21: 0.6102842 | AJ21: 0.53708116 | AK21: 0.6516817 | AL21: 0.85466086 | AM21: 0.86381283 | AN21: 0.069629045 | AO21: 0.072490392 | AP21: 0.079794512 | AQ21: 0.11452665 | AR21: 14.148534 | AS21: 3.0880709 | AT21: 2.6042483 | AU21: 3.2453498 | AV21: 4.1836064 | AW21: 36.302083 | AX21: 5.1046538 | AY21: 5.0296979 | AZ21: 5.7059927 | BA21: 8.0737617 | BB21: 135.5174 | BC21: 0 | BD21: 0 | BE21: 0 | BF21: 0 | BG21: 6.6089281 | BH21: 0 | BI21: 0 | BJ21: 0 | BK21: 0 | BL21: 2.3 | BM21: 0 | BN21: 0 | BO21: 0 | BP21: 0 | BQ21: 30.451841 | BR21: 5.225454 | BS21: 4.4372816 | BT21: 5.5084423 | BU21: 7.0405193 | BV21: 16.787866 | BW21: 4.703152 | BX21: 6.2126217 | BY21: 5.9911028 | BZ21: 10.186202 | CA21: -13.883058 | CB21: 2.7236518 | CC21: 3.9729339 | CD21: 3.6647187
A22: 39814 | B22: 1 | C22: 18 | D22: 0 | E22: 0 | F22: 0 | G22: 0 | H22: 30.972931 | I22: 4.1923173 | J22: 4.0021748 | K22: 4.6264772 | L22: 6.3974886 | M22: 20.819754 | N22: 21.468405 | O22: 21.320197 | P22: 65.578866 | Q22: 0 | R22: 0 | S22: 0 | T22: 0 | U22: 11 | V22: 0 | W22: 0 | X22: 0 | Y22: 0 | Z22: 9.4733726 | AA22: 1.073934 | AB22: 1.2165603 | AC22: 1.2747379 | AD22: 1.9702677 | AE22: 23.705551 | AF22: 27.700788 | AG22: 31.355276 | AH22: 3.7784352 | AI22: 0.62733668 | AJ22: 0.56833174 | AK22: 0.6777461 | AL22: 0.90237788 | AM22: 0.87897437 | AN22: 0.065774451 | AO22: 0.0711781 | AP22: 0.076833461 | AQ22: 0.11258818 | AR22: 15.051939 | AS22: 3.307159 | AT22: 2.8355763 | AU22: 3.4976921 | AV22: 4.546715 | AW22: 37.514027 | AX22: 5.0287169 | AY22: 5.0393985 | AZ22: 5.6605121 | BA22: 8.089341 | BB22: 135.5174 | BC22: 0 | BD22: 0 | BE22: 0 | BF22: 0 | BG22: 6.6089281 | BH22: 0 | BI22: 0 | BJ22: 0 | BK22: 0 | BL22: 2.3 | BM22: 0 | BN22: 0 | BO22: 0 | BP22: 0 | BQ22: 31.938756 | BR22: 5.5332471 | BS22: 4.8115118 | BT22: 5.8860373 | BU22: 7.6441502 | BV22: 17.399231 | BW22: 3.8354869 | BX22: 5.4167983 | BY22: 5.0493126 | BZ22: 8.9300696 | CA22: -13.635684 | CB22: 2.0098853 | CC22: 3.3764733 | CD22: 2.9188597
A23: 39904 | B23: 0 | C23: 18 | D23: 0 | E23: 0 | F23: 0 | G23: 0 | H23: 32.009484 | I23: 4.1952175 | J23: 4.0757414 | K23: 4.6624863 | L23: 6.5195996 | M23: 20.126354 | N23: 21.069345 | O23: 21.219615 | P23: 65.578866 | Q23: 0 | R23: 0 | S23: 0 | T23: 0 | U23: 11 | V23: 0 | W23: 0 | X23: 0 | Y23: 0 | Z23: 9.6748069 | AA23: 0.97313979 | AB23: 1.1385289 | AC23: 1.1720321 | AD23: 1.8443986 | AE23: 21.592388 | AF23: 25.685084 | AG23: 29.473419 | AH23: 3.9366664 | AI23: 0.6346501 | AJ23: 0.59233923 | AK23: 0.69389444 | AL23: 0.93913229 | AM23: 0.89402779 | AN23: 0.062820353 | AO23: 0.06933281 | AP23: 0.074092355 | AQ23: 0.11039988 | AR23: 15.992979 | AS23: 3.5034447 | AT23: 3.0568897 | AU23: 3.7298382 | AV23: 4.8934963 | AW23: 38.669873 | AX23: 4.8962474 | AY23: 5.0031115 | AZ23: 5.5565079 | BA23: 8.0308035 | BB23: 135.5174 | BC23: 0 | BD23: 0 | BE23: 0 | BF23: 0 | BG23: 6.6089281 | BH23: 0 | BI23: 0 | BJ23: 0 | BK23: 0 | BL23: 2.3 | BM23: 0 | BN23: 0 | BO23: 0 | BP23: 0 | BQ23: 33.472362 | BR23: 5.7972918 | BS23: 5.149202 | BT23: 6.2167648 | BU23: 8.1914346 | BV23: 17.754444 | BW23: 2.9030418 | BX23: 4.5830637 | BY23: 4.0503263 | BZ23: 7.5817809 | CA23: -13.520088 | CB23: 1.3522738 | CC23: 2.7461575 | CD23: 2.1903376 | CE23: 4.4788525
A24: 39995 | B24: 0 | C24: 18 | D24: 0 | E24: 0 | F24: 0 | G24: 0 | H24: 33.017533 | I24: 4.1536439 | J24: 4.111469 | K24: 4.6516004 | L24: 6.5805748 | M24: 19.28901 | N24: 20.524996 | O24: 20.974014 | P24: 65.578866 | Q24: 0 | R24: 0 | S24: 0 | T24: 0 | U24: 11 | V24: 0 | W24: 0 | X24: 0 | Y24: 0 | Z24: 9.8431005 | AA24: 0.85959769 | AB24: 1.0490691 | AC24: 1.0556935 | AD24: 1.7002581 | AE24: 19.452636 | AF24: 23.628536 | AG24: 27.533209 | AH24: 4.0901649 | AI24: 0.63172254 | AJ24: 0.60794305 | AK24: 0.69930816 | AL24: 0.96325995 | AM24: 0.90755502 | AN24: 0.059516628 | AO24: 0.066425217 | AP24: 0.070286382 | AQ24: 0.10663403 | AR24: 16.962057 | AS24: 3.6699026 | AT24: 3.2617675 | AU24: 3.9346937 | AV24: 5.2144027 | AW24: 39.7539 | AX24: 4.7035623 | AY24: 4.9167232 | AZ24: 5.389758 | BA24: 7.8916043 | BB24: 135.5174 | BC24: 0 | BD24: 0 | BE24: 0 | BF24: 0 | BG24: 6.6089281 | BH24: 0 | BI24: 0 | BJ24: 0 | BK24: 0 | BL24: 2.3 | BM24: 0 | BN24: 0 | BO24: 0 | BP24: 0 | BQ24: 35.034236 | BR24: 6.007433 | BS24: 5.4438921 | BT24: 6.4913385 | BU24: 8.6698817 | BV24: 17.857477 | BW24: 1.9250285 | BX24: 3.7161281 | BY24: 3.0075933 | BZ24: 6.1645958 | CA24: -13.503865 | CB24: 0.78469407 | CC24: 2.1175961 | CD24: 1.5200208 | CE24: 3.5563451
A25: 40087 | B25: 0 | C25: 18 | D25: 0 | E25: 0 | F25: 0 | G25: 0 | H25: 33.985371 | I25: 4.0650396 | J25: 4.1070094 | K25: 4.5915707 | L25: 6.5766694 | M25: 18.321155 | N25: 19.842669 | O25: 20.585503 | P25: 65.578866 | Q25: 0 | R25: 0 | S25: 0 | T25: 0 | U25: 11 | V25: 0 | W25: 0 | X25: 0 | Y25: 0 | Z25: 9.9756437 | AA25: 0.73380567 | AB25: 0.94798792 | AC25: 0.9259694 | AD25: 1.5377394 | AE25: 17.303479 | AF25: 21.541238 | AG25: 25.545464 | AH25: 4.2364872 | AI25: 0.61838676 | AJ25: 0.61433548 | AK25: 0.69364467 | AL25: 0.97359414 | AM25: 0.91762818 | AN25: 0.053815353 | AO25: 0.061722199 | AP25: 0.063753236 | AQ25: 0.099585136 | AR25: 17.949348 | AS25: 3.8008143 | AT25: 3.4444426 | AU25: 4.1065436 | AV25: 5.5009332 | AW25: 40.751356 | AX25: 4.4492728 | AY25: 4.7769633 | AZ25: 5.1580327 | BA25: 7.6673054 | BB25: 135.5174 | BC25: 0 | BD25: 0 | BE25: 0 | BF25: 0 | BG25: 6.6089281 | BH25: 0 | BI25: 0 | BJ25: 0 | BK25: 0 | BL25: 2.3 | BM25: 0 | BN25: 0 | BO25: 0 | BP25: 0 | BQ25: 36.604066 | BR25: 6.1522252 | BS25: 5.6888396 | BT25: 6.7001956 | BU25: 9.0670341 | BV25: 17.731436 | BW25: 0.94356988 | BX25: 2.8233609 | BY25: 1.9525197 | BZ25: 4.7170088 | CA25: -13.550337 | CB25: 0.33272084 | CC25: 1.5281863 | CD25: 0.94414933 | CE25: 2.6934051
A26: 40179 | B26: 0 | C26: 18 | D26: 0 | E26: 0 | F26: 0 | G26: 0 | H26: 34.902723 | I26: 3.9297913 | J26: 4.0610543 | K26: 4.4821699 | L26: 6.5063099 | M26: 17.244043 | N26: 19.031898 | O26: 20.060285 | P26: 65.578866 | Q26: 0 | R26: 0 | S26: 0 | T26: 0 | U26: 11 | V26: 0 | W26: 0 | X26: 0 | Y26: 0 | Z26: 10.070303 | AA26: 0.59692993 | AB26: 0.83543195 | AC26: 0.78363124 | AD26: 1.3573024 | AE26: 15.162489 | AF26: 19.43402 | AG26: 23.521355 | AH26: 4.373471 | AI26: 0.59503589 | AJ26: 0.61118629 | AK26: 0.67704462 | AL26: 0.9695322 | AM26: 0.92259383 | AN26: 0.043619457 | AO26: 0.054696954 | AP26: 0.053288336 | AQ26: 0.087984441 | AR26: 18.94564 | AS26: 3.8937017 | AT26: 3.6004304 | AU26: 4.2417248 | AV26: 5.7464491 | AW26: 41.649106 | AX26: 4.1350788 | AY26: 4.5818979 | AZ26: 4.8615418 | BA26: 7.3559996 | BB26: 135.5174 | BC26: 0 | BD26: 0 | BE26: 0 | BF26: 0 | BG26: 6.6089281 | BH26: 0 | BI26: 0 | BJ26: 0 | BK26: 0 | BL26: 2.3 | BM26: 0 | BN26: 0 | BO26: 0 | BP26: 0 | BQ26: 38.161891 | BR26: 6.2231346 | BS26: 5.8781909 | BT26: 6.8358105 | BU26: 9.3726266 | BV26: 17.414994 | BW26: 0.015762775 | BX26: 1.9256248 | BY26: 0.93023765 | BZ26: 3.2864992 | CA26: -13.620875 | CB26: 0.014808494 | CC26: 1.0123469 | CD26: 0.49156489 | CE26: 1.9329848
A27: 40269 | B27: 0 | C27: 18 | D27: 0 | E27: 0 | F27: 0 | G27: 0 | H27: 35.761231 | I27: 3.7517466 | J27: 3.973482 | K27: 4.3254144 | L27: 6.3703063 | M27: 16.085193 | N27: 18.105774 | O27: 19.407961 | P27: 65.578866 | Q27: 0 | R27: 0 | S27: 0 | T27: 0 | U27: 11 | V27: 0 | W27: 0 | X27: 0 | Y27: 0 | Z27: 10.125509 | AA27: 0.45070224 | AB27: 0.71192102 | AC27: 0.62997987 | AD27: 1.1600048 | AE27: 13.046139 | AF27: 17.319264 | AG27: 21.472102 | AH27: 4.4992102 | AI27: 0.56254376 | AJ27: 0.59859693 | AK27: 0.64998718 | AL27: 0.95096305 | AM27: 0.92069773 | AN27: 0.026669934 | AO27: 0.044745144 | AP27: 0.037717994 | AQ27: 0.070590366 | AR27: 19.943464 | AS27: 3.9504857 | AT27: 3.7269652 | AU27: 4.3394413 | AV27: 5.947202 | AW27: 42.43595 | AX27: 3.7660772 | AY27: 4.3311623 | AZ27: 4.5029112 | BA27: 6.9583538 | BB27: 135.5174 | BC27: 0 | BD27: 0 | BE27: 0 | BF27: 0 | BG27: 6.6089281 | BH27: 0 | BI27: 0 | BJ27: 0 | BK27: 0 | BL27: 2.3 | BM27: 0 | BN27: 0 | BO27: 0 | BP27: 0 | BQ27: 39.691145 | BR27: 6.2187833 | BS27: 6.0080376 | BT27: 6.8955169 | BU27: 9.5813675 | BV27: 16.955552 | BW27: -0.79889224 | BX27: 1.0520748 | BY27: -0.010610318 | BZ27: 1.9229442 | CA27: -13.677579 | CB27: -0.15749119 | CC27: 0.5973913 | CD27: 0.18177469 | CE27: 1.3123018
A28: 40360 | B28: 0 | C28: 18 | D28: 0 | E28: 0 | F28: 0 | G28: 0 | H28: 36.554604 | I28: 3.537071 | J28: 3.8453574 | K28: 4.1254177 | L28: 6.1717442 | M28: 14.876536 | N28: 17.082773 | O28: 18.642176 | P28: 65.578866 | Q28: 0 | R28: 0 | S28: 0 | T28: 0 | U28: 11 | V28: 0 | W28: 0 | X28: 0 | Y28: 0 | Z28: 10.140435 | AA28: 0.29733464 | AB28: 0.57846617 | AC28: 0.4669256 | AD28: 0.94761746 | AE28: 10.971571 | AF28: 15.212104 | AG28: 19.409548 | AH28: 4.612257 | AI28: 0.52209202 | AJ28: 0.57690728 | AK28: 0.61338474 | AL28: 0.91840799 | AM28: 0.90984307 | AN28: 0.0022880495 | AO28: 0.030902339 | AP28: 0.015677054 | AQ28: 0.045957749 | AR28: 20.937001 | AS28: 3.9749444 | AT28: 3.8224235 | AU28: 4.4012367 | AV28: 6.1020499 | AW28: 43.103345 | AX28: 3.3494448 | AY28: 4.0265035 | AZ28: 4.0875161 | BA28: 6.4780576 | BB28: 135.5174 | BC28: 0 | BD28: 0 | BE28: 0 | BF28: 0 | BG28: 6.6089281 | BH28: 0 | BI28: 0 | BJ28: 0 | BK28: 0 | BL28: 2.3 | BM28: 0 | BN28: 0 | BO28: 0 | BP28: 0 | BQ28: 41.178947 | BR28: 6.1447108 | BS28: 6.0760719 | BT28: 6.8813093 | BU28: 9.692737 | BV28: 16.396819 | BW28: -1.4606583 | BX28: 0.2321851 | BY28: -0.83236215 | BZ28: 0.66694143 | CA28: -13.6867 | CB28: -0.18283507 | CC28: 0.3009295 | CD28: 0.023305615 | CE28: 0.85861187
A29: 40452 | B29: 0 | C29: 18 | D29: 0 | E29: 0 | F29: 0 | G29: 0 | H29: 37.278067 | I29: 3.2926959 | J29: 3.6788677 | K29: 3.8875408 | L29: 5.915206 | M29: 13.650734 | N29: 15.985945 | O29: 17.77869 | P29: 65.578866 | Q29: 0 | R29: 0 | S29: 0 | T29: 0 | U29: 11 | V29: 0 | W29: 0 | X29: 0 | Y29: 0 | Z29: 10.115162 | AA29: 0.13951831 | AB29: 0.43666199 | AC29: 0.29703595 | AD29: 0.7227216 | AE29: 8.9580943 | AF29: 13.130787 | AG29: 17.346857 | AH29: 4.7115903 | AI29: 0.47510311 | AJ29: 0.54674494 | AK29: 0.56849128 | AL29: 0.87290985 | AM29: 0.88812123 | AN29: -0.029506951 | AO29: 0.012154201 | AP29: -0.013770374 | AQ29: 0.012974366 | AR29: 21.921607 | AS29: 3.9722583 | AT29: 3.8865363 | AU29: 4.4302365 | AV29: 6.2117823 | AW29: 43.645928 | AX29: 2.8945719 | AY29: 3.6719224 | AZ29: 3.6234729 | BA29: 5.922066 | BB29: 135.5174 | BC29: 0 | BD29: 0 | BE29: 0 | BF29: 0 | BG29: 6.6089281 | BH29: 0 | BI29: 0 | BJ29: 0 | BK29: 0 | BL29: 2.3 | BM29: 0 | BN29: 0 | BO29: 0 | BP29: 0 | BQ29: 42.614913 | BR29: 6.0108472 | BS29: 6.0815362 | BT29: 6.7982579 | BU29: 9.709329 | BV29: 15.773994 | BW29: -1.9574414 | BX29: -0.50693578 | BY29: -1.5132331 | BZ29: -0.45351643 | CA29: -13.619283 | CB29: -0.06894516 | CC29: 0.13188784 | CD29: 0.015490676 | CE29: 0.58833288
A30: 40544 | B30: 0 | C30: 18 | D30: 0 | E30: 0 | F30: 0 | G30: 0 | H30: 37.928505 | I30: 3.0257828 | J30: 3.4777871 | K30: 3.6182623 | L30: 5.6067515 | M30: 12.439938 | N30: 14.84199 | O30: 16.834578 | P30: 65.578866 | Q30: 0 | R30: 0 | S30: 0 | T30: 0 | U30: 11 | V30: 0 | W30: 0 | X30: 0 | Y30: 0 | Z30: 10.050922 | AA30: -0.019380532 | AB30: 0.2887747 | AC30: 0.12363043 | AD30: 0.48885707 | AE30: 7.0305762 | AF30: 11.096533 | AG30: 15.299539 | AH30: 4.7965919 | AI30: 0.42312085 | AJ30: 0.50907837 | AK30: 0.51680662 | AL30: 0.81593024 | AM30: 0.85582766 | AN30: -0.066766172 | AO30: -0.011573357 | AP30: -0.049102495 | AQ30: -0.027147325 | AR30: 22.893237 | AS30: 3.9475965 | AT30: 3.9206491 | AU30: 4.4302324 | AV30: 6.2783171 | AW30: 44.062218 | AX30: 2.4131121 | AY30: 3.2740954 | AZ30: 3.1217824 | BA30: 5.3009812 | BB30: 135.5174 | BC30: 0 | BD30: 0 | BE30: 0 | BF30: 0 | BG30: 6.6089281 | BH30: 0 | BI30: 0 | BJ30: 0 | BK30: 0 | BL30: 2.3 | BM30: 0 | BN30: 0 | BO30: 0 | BP30: 0 | BQ30: 43.990984 | BR30: 5.8290933 | BS30: 6.026114 | BT30: 6.6539447 | BU30: 9.636356 | BV30: 15.11626 | BW30: -2.2987335 | BX30: -1.1414854 | BY30: -2.0442331 | BZ30: -1.4186904 | CA30: -13.451705 | CB30: 0.16917008 | CC30: 0.091989286 | CD30: 0.15009608 | CE30: 0.50695796
A31: 40634 | B31: 1 | C31: 18 | D31: 0 | E31: 0 | F31: 0 | G31: 0 | H31: 38.505143 | I31: 2.7439125 | J31: 3.2478296 | K31: 3.3254534 | L31: 5.2543984 | M31: 11.276851 | N31: 13.681022 | O31: 15.829466 | P31: 65.578866 | Q31: 0 | R31: 0 | S31: 0 | T31: 0 | U31: 11 | V31: 0 | W31: 0 | X31: 0 | Y31: 0 | Z31: 9.9504669 | AA31: -0.17504222 | AB31: 0.13783001 | AC31: -0.049018313 | AD31: 0.25077839 | AE31: 5.2226414 | AF31: 9.1343903 | AG31: 13.287056 | AH31: 4.8670241 | AI31: 0.36781388 | AJ31: 0.46517882 | AK31: 0.45996918 | AL31: 0.74923795 | AM31: 0.8139066 | AN31: -0.10679112 | AO31: -0.040060595 | AP31: -0.088130212 | AQ31: -0.072620694 | AR31: 23.847835 | AS31: 3.904371 | AT31: 3.9274284 | AU31: 4.4046688 | AV31: 6.3038776 | AW31: 44.355466 | AX31: 1.9195161 | AY31: 2.8427966 | AZ31: 2.5965063 | BA31: 4.6294867 | BB31: 135.5174 | BC31: 0 | BD31: 0 | BE31: 0 | BF31: 0 | BG31: 6.6089281 | BH31: 0 | BI31: 0 | BJ31: 0 | BK31: 0 | BL31: 2.3 | BM31: 0 | BN31: 0 | BO31: 0 | BP31: 0 | BQ31: 45.302002 | BR31: 5.6108571 | BS31: 5.9148202 | BT31: 6.4584341 | BU31: 9.4819176 | BV31: 14.454706 | BW31: -2.5008461 | BX31: -1.6498692 | BY31: -2.4204161 | BZ31: -2.2096211 | CA31: -13.166616 | CB31: 0.51096242 | CC31: 0.17673562 | CD31: 0.41218764 | CE31: 0.60922485
A32: 40725 | B32: 0 | C32: 18 | D32: 0 | E32: 0 | F32: 0 | G32: 0 | H32: 39.009715 | I32: 2.455111 | J32: 2.996091 | K32: 3.0180682 | L32: 4.8680642 | M32: 10.192032 | N32: 12.534284 | O32: 14.785859 | P32: 65.578866 | Q32: 0 | R32: 0 | S32: 0 | T32: 0 | U32: 11 | V32: 0 | W32: 0 | X32: 0 | Y32: 0 | Z32: 9.8183363 | AA32: -0.3220988 | AB32: -0.012382079 | AC32: -0.21560641 | AD32: 0.014581142 | AE32: 3.5793049 | AF32: 7.275438 | AG32: 11.334504 | AH32: 3.9867485 | AI32: -0.62550845 | AJ32: -0.051708215 | AK32: -0.53660106 | AL32: -0.26145491 | AM32: 0.76332214 | AN32: -0.14652094 | AO32: -0.072116443 | AP32: -0.12869953 | AQ32: -0.12176342 | AR32: 24.780968 | AS32: 3.8439672 | AT32: 3.9094558 | AU32: 4.3559446 | AV32: 6.2904854 | AW32: 44.533957 | AX32: 1.4306122 | AY32: 2.3900285 | AZ32: 2.0642988 | BA32: 3.9261583 | BB32: 135.5174 | BC32: 0 | BD32: 0 | BE32: 0 | BF32: 0 | BG32: 6.6089281 | BH32: 0 | BI32: 0 | BJ32: 0 | BK32: 0 | BL32: 2.3 | BM32: 0 | BN32: 0 | BO32: 0 | BP32: 0 | BQ32: 46.54594 | BR32: 5.3669933 | BS32: 5.755852 | BT32: 6.223667 | BU32: 9.2569445 | BV32: 13.821145 | BW32: -2.5756738 | BX32: -2.0181661 | BY32: -2.6415097 | BZ32: -2.8101239 | CA32: -12.755235 | CB32: 0.93146452 | CC32: 0.37431473 | CD32: 0.77938458 | CE32: 0.87846027
A33: 40817 | B33: 0 | C33: 18 | D33: 0 | E33: 0 | F33: 0 | G33: 0 | H33: 39.447544 | I33: 2.1694772 | J33: 2.7310866 | K33: 2.7068742 | L33: 4.4604075 | M33: 9.2129298 | N33: 11.431832 | O33: 13.728273 | P33: 65.578866 | Q33: 0 | R33: 0 | S33: 0 | T33: 0 | U33: 11 | V33: 0 | W33: 0 | X33: 0 | Y33: 0 | Z33: 9.6606845 | AA33: -0.4544775 | AB33: -0.1574796 | AC33: -0.3701627 | AD33: -0.21264013 | AE33: 2.150351 | AF33: 5.5542227 | AG33: 9.4706414 | AH33: 4.0207108 | AI33: -0.69087955 | AJ33: -0.10788822 | AK33: -0.48971174 | AL33: -0.27151815 | AM33: 0.70537448 | AN33: -0.18274675 | AO33: -0.10612685 | AP33: -0.16861808 | AQ33: -0.17265139 | AR33: 25.689258 | AS33: 3.767651 | AT33: 3.8699546 | AU33: 4.28687 | AV33: 6.2413736 | AW33: 44.611858 | AX33: 0.9659297 | AY33: 1.9302508 | AZ33: 1.5446919 | BA33: 3.2137568 | BB33: 135.5174 | BC33: 0 | BD33: 0 | BE33: 0 | BF33: 0 | BG33: 6.6089281 | BH33: 0 | BI33: 0 | BJ33: 0 | BK33: 0 | BL33: 2.3 | BM33: 0 | BN33: 0 | BO33: 0 | BP33: 0 | BQ33: 47.723456 | BR33: 5.108543 | BS33: 5.5596951 | BT33: 5.9622202 | BU33: 8.9745327 | BV33: 13.2487 | BW33: -2.5252947 | BX33: -2.2413681 | BY33: -2.7094137 | BZ33: -3.2066275 | CA33: -12.216663 | CB33: 1.4026192 | CC33: 0.66683701 | CD33: 1.224378 | CE33: 1.2892554
A34: 40909 | B34: 0 | C34: 18 | D34: 0 | E34: 0 | F34: 0 | G34: 0 | H34: 39.827311 | I34: 1.8988059 | J34: 2.4622943 | K34: 2.4038696 | L34: 4.0462402 | M34: 8.3620968 | N34: 10.401017 | O34: 12.682026 | P34: 65.578866 | Q34: 0 | R34: 0 | S34: 0 | T34: 0 | U34: 11 | V34: 0 | W34: 0 | X34: 0 | Y34: 0 | Z34: 9.4848348 | AA34: -0.56608722 | AB34: -0.29273387 | AC34: -0.50664254 | AD34: -0.42339374 | AE34: 0.97826104 | AF34: 4.0044186 | AG34: 7.7237754 | AH34: 4.0440643 | AI34: -0.75252757 | AJ34: -0.16470336 | AK34: -0.43938614 | AL34: -0.28171546 | AM34: 0.641177 | AN34: -0.21465066 | AO34: -0.14070842 | AP34: -0.20628385 | AQ34: -0.22364568 | AR34: 26.569822 | AS34: 3.6765851 | AT34: 3.8120908 | AU34: 4.1999455 | AV34: 6.1602107 | AW34: 44.608378 | AX34: 0.54615996 | AY34: 1.479636 | AZ34: 1.0586495 | BA34: 2.517796 | BB34: 135.5174 | BC34: 0 | BD34: 0 | BE34: 0 | BF34: 0 | BG34: 6.6089281 | BH34: 0 | BI34: 0 | BJ34: 0 | BK34: 0 | BL34: 2.3 | BM34: 0 | BN34: 0 | BO34: 0 | BP34: 0 | BQ34: 48.837625 | BR34: 4.8466411 | BS34: 5.3378672 | BT34: 5.6864655 | BU34: 8.6494004 | BV34: 12.766546 | BW34: -2.3497139 | BX34: -2.3242237 | BY34: -2.6312249 | BZ34: -3.3938501 | CA34: -11.557031 | CB34: 1.894674 | CC34: 1.031922 | CD34: 1.7173009 | CE34: 1.8100213
... A83: 45383 | B83: 0 | C83: 18 | D83: 0 | E83: 0 | F83: 0 | G83: 0 | H83: 28.992522 | I83: -1.691539 | J83: -1.8995734 | K83: -2.0012014 | L83: -3.0736376 | M83: -3.673878 | N83: -4.4584763 | O83: -4.9561048 | P83: 65.578866 | Q83: 0 | R83: 0 | S83: 0 | T83: 0 | U83: 11 | V83: 0 | W83: 0 | X83: 0 | Y83: 0 | Z83: 9.5532172 | AA83: 0.09258255 | AB83: 0.053372426 | AC83: 0.085215359 | AD83: 0.088663463 | AE83: 5.9495563 | AF83: 5.3618133 | AG83: 5.0002473 | AH83: 3.8851421 | AI83: -0.12829959 | AJ83: -0.12320148 | AK83: -0.14199791 | AL83: -0.19539748 | AM83: 0.34008627 | AN83: -0.37025238 | AO83: 0.70277655 | AP83: -0.13835462 | AQ83: 0.034274542 | AR83: 34.221446 | AS83: -1.7405548 | AT83: -1.7460708 | AU83: -1.9597949 | AV83: -2.8140251 | AW83: 36.973091 | AX83: -0.53698062 | AY83: -0.68860806 | AZ83: -0.67629862 | BA83: -1.1155199 | BB83: 135.5174 | BC83: 0 | BD83: 0 | BE83: 0 | BF83: 0 | BG83: 6.6089281 | BH83: 0 | BI83: 0 | BJ83: 0 | BK83: 0 | BL83: 2.3 | BM83: 0 | BN83: 0 | BO83: 0 | BP83: 0 | BQ83: 48.658297 | BR83: -4.0645898 | BS83: -4.2718356 | BT83: -4.6717869 | BU83: -6.8551969 | BV83: -14.145148 | BW83: 0.34808416 | BX83: -0.55107146 | BY83: -0.030871527 | BZ83: -1.039386 | CA83: 8.0309764 | CB83: 2.0473294 | CC83: 1.2718664 | CD83: 1.9289268 | CE83: 2.0057985
A84: 45474 | B84: 0 | C84: 18 | D84: 0 | E84: 0 | F84: 0 | G84: 0 | H84: 28.651184 | I84: -1.5651016 | J84: -1.792587 | K84: -1.8676456 | L84: -2.9092139 | M84: -3.2273675 | N84: -4.0628981 | O84: -4.672711 | P84: 65.578866 | Q84: 0 | R84: 0 | S84: 0 | T84: 0 | U84: 11 | V84: 0 | W84: 0 | X84: 0 | Y84: 0 | Z84: 9.5841647 | AA84: 0.10706635 | AB84: 0.070427478 | AC84: 0.10281972 | AD84: 0.11184379 | AE84: 6.1411485 | AF84: 5.6107891 | AG84: 5.1539989 | AH84: 3.8536429 | AI84: -0.12793902 | AJ84: -0.12526842 | AK84: -0.14269678 | AL84: -0.19942838 | AM84: 0.33608646 | AN84: -0.36546867 | AO84: -0.16047196 | AP84: -0.31804857 | AQ84: 0.034513992 | AR84: 33.818962 | AS84: -1.6983601 | AT84: -1.7325618 | AU84: -1.9257617 | AV84: -2.7899302 | AW84: 36.883228 | AX84: -0.46436366 | AY84: -0.61600238 | AZ84: -0.59401003 | BA84: -1.008489 | BB84: 135.5174 | BC84: 0 | BD84: 0 | BE84: 0 | BF84: 0 | BG84: 6.6089281 | BH84: 0 | BI84: 0 | BJ84: 0 | BK84: 0 | BL84: 2.3 | BM84: 0 | BN84: 0 | BO84: 0 | BP84: 0 | BQ84: 47.769032 | BR84: -3.8760667 | BS84: -4.1557273 | BT84: -4.4930934 | BU84: -6.6815753 | CA84: 8.6562215 | CB84: 2.2749518 | CC84: 1.6011192 | CD84: 2.2362053 | CE84: 2.4750586
A85: 45566 | B85: 0 | C85: 18 | D85: 0 | E85: 0 | F85: 0 | G85: 0 | H85: 28.346675 | I85: -1.4305177 | J85: -1.675201 | K85: -1.7240078 | L85: -2.7265177 | M85: -2.7655721 | N85: -3.6400509 | O85: -4.3436657 | P85: 65.578866 | Q85: 0 | R85: 0 | S85: 0 | T85: 0 | U85: 11 | V85: 0 | W85: 0 | X85: 0 | Y85: 0 | Z85: 9.6158166 | AA85: 0.11723936 | AB85: 0.085901301 | AC85: 0.11686475 | AD85: 0.13324286 | AE85: 6.2570212 | AF85: 5.8271052 | AG85: 5.3261699 | AH85: 3.8230183 | AI85: -0.12638298 | AJ85: -0.12603563 | AK85: -0.14200425 | AL85: -0.20130046 | AM85: 0.33233079 | AN85: -0.36050706 | AO85: -0.19775404 | AP85: -0.28168624 | AQ85: 0.035008501 | AR85: 33.441045 | AS85: -1.6349508 | AT85: -1.7034661 | AU85: -1.870538 | AV85: -2.7401698 | AW85: 36.809838 | AX85: -0.39471267 | AY85: -0.54248341 | AZ85: -0.51339917 | BA85: -0.89772686 | BB85: 135.5174 | BC85: 0 | BD85: 0 | BE85: 0 | BF85: 0 | BG85: 6.6089281 | BH85: 0 | BI85: 0 | BJ85: 0 | BK85: 0 | BL85: 2.3 | BM85: 0 | BN85: 0 | BO85: 0 | BP85: 0 | BQ85: 46.9462 | BR85: -3.6575301 | BS85: -4.0028994 | BT85: -4.2769931 | BU85: -6.4500969 | CA85: 9.2817947 | CB85: 2.4117007 | CC85: 1.881627 | CD85: 2.4614987 | CE85: 2.8760896
A86: 45658 | B86: 0 | C86: 18 | D86: 0 | E86: 0 | F86: 0 | G86: 0 | H86: 28.080377 | I86: -1.2882235 | J86: -1.5490823 | K86: -1.571506 | L86: -2.5277391 | M86: -2.2901643 | N86: -3.1971181 | O86: -3.9752868 | P86: 65.578866 | Q86: 0 | R86: 0 | S86: 0 | T86: 0 | U86: 11 | V86: 0 | W86: 0 | X86: 0 | Y86: 0 | Z86: 9.6468589 | AA86: 0.12256866 | AB86: 0.098620347 | AC86: 0.12643179 | AD86: 0.15109895 | AE86: 6.2911823 | AF86: 5.9931621 | AG86: 5.4991392 | AH86: 3.7936346 | AI86: -0.12352919 | AJ86: -0.1255413 | AK86: -0.13987907 | AL86: -0.20100136 | AM86: 0.32888136 | AN86: -0.35539163 | AO86: -0.19511935 | AP86: -0.23569717 | AQ86: 0.035788945 | AR86: 33.093943 | AS86: -1.5484432 | AT86: -1.6563154 | AU86: -1.7917735 | AV86: -2.6616371 | AW86: 36.752129 | AX86: -0.32785414 | AY86: -0.47022435 | AZ86: -0.43548784 | BA86: -0.78589908 | BB86: 135.5174 | BC86: 0 | BD86: 0 | BE86: 0 | BF86: 0 | BG86: 6.6089281 | BH86: 0 | BI86: 0 | BJ86: 0 | BK86: 0 | BL86: 2.3 | BM86: 0 | BN86: 0 | BO86: 0 | BP86: 0 | BQ86: 46.197858 | BR86: -3.4079057 | BS86: -3.815441 | BT86: -4.0246107 | BU86: -6.1621312 | CA86: 9.8872972 | CB86: 2.4594566 | CC86: 2.0967597 | CD86: 2.5965945 | CE86: 3.1885962
A87: 45748 | B87: 0 | C87: 18 | D87: 0 | E87: 0 | F87: 0 | G87: 0 | H87: 27.853042 | I87: -1.13948 | J87: -1.4155095 | K87: -1.4115705 | L87: -2.3153369 | M87: -1.8045539 | N87: -2.739216 | O87: -3.5738355 | P87: 65.578866 | Q87: 0 | R87: 0 | S87: 0 | T87: 0 | U87: 11 | V87: 0 | W87: 0 | X87: 0 | Y87: 0 | Z87: 9.6761487 | AA87: 0.12293152 | AB87: 0.10775703 | AC87: 0.13106649 | AD87: 0.16414271 | AE87: 6.2452687 | AF87: 6.0974125 | AG87: 5.6562985 | AH87: 3.7658744 | AI87: -0.11926769 | AJ87: -0.12378364 | AK87: -0.13625389 | AL87: -0.19850541 | AM87: 0.32580612 | AN87: -0.01428015 | AO87: -0.19226626 | AP87: -0.18999256 | AQ87: -0.10460321 | AR87: 32.784495 | AS87: -1.4369512 | AT87: -1.588753 | AU87: -1.6871425 | AV87: -2.5509487 | AW87: 36.70935 | AX87: -0.26374125 | AY87: -0.40036093 | AZ87: -0.36071031 | BA87: -0.67510039 | BB87: 135.5174 | BC87: 0 | BD87: 0 | BE87: 0 | BF87: 0 | BG87: 6.6089281 | BH87: 0 | BI87: 0 | BJ87: 0 | BK87: 0 | BL87: 2.3 | BM87: 0 | BN87: 0 | BO87: 0 | BP87: 0 | BQ87: 45.531049 | BR87: -3.1272483 | BS87: -3.595919 | BT87: -3.7375594 | BU87: -5.8199561 | CA87: 10.45448 | CB87: 2.4235039 | CC87: 2.2354167 | CD87: 2.6395877 | CE87: 3.3984231
A88: 45839 | B88: 0 | C88: 18 | D88: 0 | E88: 0 | F88: 0 | G88: 0 | H88: 27.665142 | I88: -0.98604209 | J88: -1.2755719 | K88: -1.2455927 | L88: -2.0916842 | M88: -1.3115407 | N88: -2.2694541 | O88: -3.1457789 | P88: 65.578866 | Q88: 0 | R88: 0 | S88: 0 | T88: 0 | U88: 11 | V88: 0 | W88: 0 | X88: 0 | Y88: 0 | Z88: 9.7028504 | AA88: 0.11868569 | AB88: 0.11287602 | AC88: 0.13082887 | AD88: 0.17170465 | AE88: 6.1287385 | AF88: 6.1349435 | AG88: 5.7834389 | AH88: 3.7400895 | AI88: -0.11355333 | AJ88: -0.12074617 | AK88: -0.13109285 | AL88: -0.19381773 | AM88: 0.3231699 | AN88: -0.012916557 | AO88: -0.18919262 | AP88: -0.14456222 | AQ88: -0.22317884 | AR88: 32.519223 | AS88: -1.2997386 | AT88: -1.4990493 | AU88: -1.5552263 | AV88: -2.4054629 | AW88: 36.681231 | AX88: -0.20199703 | AY88: -0.33318034 | AZ88: -0.28873929 | BA88: -0.56647314 | BB88: 135.5174 | BC88: 0 | BD88: 0 | BE88: 0 | BF88: 0 | BG88: 6.6089281 | BH88: 0 | BI88: 0 | BJ88: 0 | BK88: 0 | BL88: 2.3 | BM88: 0 | BN88: 0 | BO88: 0 | BP88: 0 | BQ88: 44.952048 | BR88: -2.8169834 | BS88: -3.346525 | BT88: -3.4175801 | BU88: -5.42638 | CA88: 10.968574 | CB88: 2.3123525 | CC88: 2.2936521 | CD88: 2.5948271 | CE88: 3.4985804
A89: 45931 | B89: 0 | C89: 18 | D89: 0 | E89: 0 | F89: 0 | G89: 0 | H89: 27.516875 | I89: -0.82980032 | J89: -1.130159 | K89: -1.074967 | L89: -1.8590168 | M89: -0.8134795 | N89: -1.7895258 | O89: -2.6978605 | P89: 65.578866 | Q89: 0 | R89: 0 | S89: 0 | T89: 0 | U89: 11 | V89: 0 | W89: 0 | X89: 0 | Y89: 0 | Z89: 9.7264615 | AA89: 0.11064493 | AB89: 0.11394215 | AC89: 0.12622101 | AD89: 0.17368741 | AE89: 5.9567366 | AF89: 6.1068789 | AG89: 5.8703156 | AH89: 3.7165488 | AI89: -0.10646952 | AJ89: -0.11642625 | AK89: -0.12444708 | AL89: -0.18701766 | AM89: 0.32102997 | AN89: -0.011300825 | AO89: -0.18590394 | AP89: -0.099404 | AQ89: -0.19749707 | AR89: 32.303891 | AS89: -1.1371543 | AT89: -1.3860525 | AU89: -1.3957963 | AV89: -2.2237235 | AW89: 36.667904 | AX89: -0.14193407 | AY89: -0.26832337 | AZ89: -0.21877098 | BA89: -0.46029977 | BB89: 135.5174 | BC89: 0 | BD89: 0 | BE89: 0 | BF89: 0 | BG89: 6.6089281 | BH89: 0 | BI89: 0 | BJ89: 0 | BK89: 0 | BL89: 2.3 | BM89: 0 | BN89: 0 | BO89: 0 | BP89: 0 | BQ89: 44.466661 | BR89: -2.4795393 | BS89: -3.0685347 | BT89: -3.0663364 | BU89: -4.9843976 | CA89: 11.418504 | CB89: 2.1367094 | CC89: 2.274205 | CD89: 2.4713442 | CE89: 3.4889612
A90: 46023 | B90: 0 | C90: 18 | D90: 0 | E90: 0 | F90: 0 | G90: 0 | H90: 27.408011 | I90: -0.67236621 | J90: -0.98029488 | K90: -0.90129152 | L90: -1.6195309 | M90: -0.31211935 | N90: -1.3011418 | O90: -2.2354518 | P90: 65.578866 | Q90: 0 | R90: 0 | S90: 0 | T90: 0 | U90: 11 | V90: 0 | W90: 0 | X90: 0 | Y90: 0 | Z90: 9.7467946 | AA90: 0.099935657 | AB90: 0.11125216 | AC90: 0.11806856 | AD90: 0.1704832 | AE90: 5.7476729 | AF90: 6.0194276 | AG90: 5.9113324 | AH90: 3.695413 | AI90: -0.098221579 | AJ90: -0.11087539 | AK90: -0.1164763 | AL90: -0.17827504 | AM90: 0.31943224 | AN90: -0.0094491185 | AO90: -0.18242037 | AP90: -0.054525743 | AQ90: -0.16519406 | AR90: 32.143118 | AS90: -0.95082492 | AT90: -1.2496341 | AU90: -1.2100558 | AV90: -2.0058222 | AW90: 36.669486 | AX90: -0.082642793 | AY90: -0.20524847 | AZ90: -0.15010838 | BA90: -0.35647628 | BB90: 135.5174 | BC90: 0 | BD90: 0 | BE90: 0 | BF90: 0 | BG90: 6.6089281 | BH90: 0 | BI90: 0 | BJ90: 0 | BK90: 0 | BL90: 2.3 | BM90: 0 | BN90: 0 | BO90: 0 | BP90: 0 | BQ90: 44.079246 | BR90: -2.1186118 | BS90: -2.7632587 | BT90: -2.6866176 | BU90: -4.4980343 | CA90: 11.797504 | CB90: 1.9102067 | CC90: 2.1848316 | CD90: 2.2817928 | CE90: 3.3762974
A91: 46113 | B91: 0 | C91: 18 | D91: 0 | E91: 0 | F91: 0 | G91: 0 | H91: 27.337968 | I91: -0.51507369 | J91: -0.82727686 | K91: -0.72626039 | L91: -1.3753626 | M91: 0.1899869 | N91: -0.80728348 | O91: -1.762815 | P91: 65.578866 | Q91: 0 | R91: 0 | S91: 0 | T91: 0 | U91: 11 | V91: 0 | W91: 0 | X91: 0 | Y91: 0 | Z91: 9.763962 | AA91: 0.087813264 | AB91: 0.10537239 | AC91: 0.10742291 | AD91: 0.1628859 | AE91: 5.5212462 | AF91: 5.8832574 | AG91: 5.9053571 | AH91: 3.6767237 | AI91: -0.089150665 | AJ91: -0.10420918 | AK91: -0.10744669 | AL91: -0.1678556 | AM91: 0.31840177 | AN91: -0.0074043548 | AO91: -0.010842252 | AP91: -0.0099511205 | AQ91: -0.13291721 | AR91: 32.039426 | AS91: -0.74506898 | AT91: -1.0910101 | AU91: -1.0013393 | AV91: -1.7542262 | AW91: 36.686089 | AX91: -0.023261064 | AY91: -0.14350115 | AZ91: -0.082193101 | BA91: -0.25461549 | BB91: 135.5174 | BC91: 0 | BD91: 0 | BE91: 0 | BF91: 0 | BG91: 6.6089281 | BH91: 0 | BI91: 0 | BJ91: 0 | BK91: 0 | BL91: 2.3 | BM91: 0 | BN91: 0 | BO91: 0 | BP91: 0 | BQ91: 43.791461 | BR91: -1.739588 | BS91: -2.4334181 | BT91: -2.283588 | BU91: -3.9733616 | CA91: 12.103374 | CB91: 1.6488932 | CC91: 2.0361986 | CD91: 2.0414546 | CE91: 3.1735233

Sheet Deviation_SD
B1: Binary | C1: Corporate | U1: Households | AH1: Government | AW1: Banks | BL1: External | BV1: Недвижимость
B2: Binary | C2: Debt service ratio, % | H2: All Debt to GDP ratio, % | M2: Прирост реального кредита банков ЮЛ (дефлятор ВВП 2018=1) | P2: Складские запасы в промышленности к среднемесячному ОПП, % | U2: Debt_service ratio | Z2: Кредит ФЛ к ВВП | AE2: Прирост реального кредита банков ФЛ (ИПЦ 2018=1) | AH2: Обслуживание внешнего долга органов государственного управления к ВВП, % | AM2: Отношение сальдо консолидированного бюджета к ВВП, % | AR2: Долг сектора государственного управления к ВВП, % (внешний + внутренний) | AW2: Требования банков к экономике к ВВП, % | BB2: Требования банков к депозитам, % | BG2: Леверидж (активы к собственному капиталу), раз | BL2: Счет текущих операций за год, в % к ВВП | BQ2: Валовый внешний долг к ВВП | BV2: Логарифм цен на коммерческую недвижимость, скорректированных на дефлятор ВВП, *100 | CA2: Логарифм цен на жилую недвижимость, скорректированных на ИПЦ
B3: avr | C3: =AVERAGE(C18:C152) | D3: =AVERAGE(D18:D152) | E3: =AVERAGE(E18:E152) | F3: =AVERAGE(F18:F152) | G3: =AVERAGE(G18:G152) | H3: =AVERAGE(H18:H152) | I3: =AVERAGE(I18:I152) | J3: =AVERAGE(J18:J152) | ... CE3: =AVERAGE(CE18:CE152)
B4: SD | C4: =_xlfn.STDEV.S(C18:C152) | D4: =_xlfn.STDEV.S(D18:D152) | E4: =_xlfn.STDEV.S(E18:E152) | F4: =_xlfn.STDEV.S(F18:F152) | G4: =_xlfn.STDEV.S(G18:G152) | H4: =_xlfn.STDEV.S(H18:H152) | I4: =_xlfn.STDEV.S(I18:I152) | J4: =_xlfn.STDEV.S(J18:J152) | ... CE4: =_xlfn.STDEV.S(CE18:CE152)
A5: Date | B5: bnr | C5: dsr | D5: dsr1 | E5: dsr2 | F5: dsr_av2 | G5: dsr_av3 | H5: ggr | I5: ggr1 | J5: ggr2 | K5: ggr_av2 | L5: ggr_av3 | M5: rcgr_c1 | N5: rcgr_c2 | O5: rcgr_c3 | P5: invr | Q5: invr1 | R5: invr2 | S5: invr_av2 | T5: invr_av3 | U5: d_srv | V5: d_srv1 | W5: d_srv2 | X5: d_srv_av2 | Y5: d_srv_av3 | Z5: l_gdp | AA5: l_gdp1 | AB5: l_gdp2 | AC5: l_gdp_av2 | AD5: l_gdp_av3 | AE5: rcgr_h1 | AF5: rcgr_h2 | AG5: rcgr_h3 | AH5: exd_s | AI5: exd_s1 | AJ5: exd_s2 | AK5: exd_s_av2 | AL5: exd_s_av3 | AM5: bb_gdp | AN5: bb_gdp1 | AO5: bb_gdp2 | AP5: bb_gdp_av2 | AQ5: bb_gdp_av3 | AR5: ggd | AS5: ggd1 | AT5: ggd2 | AU5: ggd_av2 | AV5: ggd_av3 | AW5: crr | AX5: crr1 | AY5: crr2 | AZ5: crr_av2 | BA5: crr_av3 | BB5: d_as | BC5: d_as1 | BD5: d_as2 | BE5: d_as_av2 | BF5: d_as_av3 | BG5: lvr | BH5: lvr1 | BI5: lvr2 | BJ5: lvr_av2 | BK5: lvr_av3 | BL5: ca | BM5: ca1 | BN5: ca2 | BO5: ca_av2 | BP5: ca_av3 | BQ5: gd_gdp | BR5: gd_gdp1 | BS5: gd_gdp2 | BT5: gd_gdp_av2 | BU5: gd_gdp_av3 | BV5: cest | BW5: cest1 | BX5: cest2 | BY5: cest_av2 | BZ5: cest_av3 | CA5: pest | CB5: pest1 | CC5: pest2 | CD5: pest_av2 | CE5: pest_av3
A6: 38718 | B6: 0 | C6: -1.0221121 | H6: -0.27864908 | I6: -0.21393939 | M6: -0.13661042 | N6: -0.2847566 | O6: -0.22814981 | P6: -0.48703032 | Q6: -0.10777185 | U6: -4.4296503 | Z6: -0.16977479 | AA6: -0.1116929 | AE6: 0.030829434 | AF6: 0.10830189 | AG6: 0.16618793 | AH6: -0.6432996 | AI6: -0.34002315 | AM6: 0.042006473 | AN6: 0.48201991 | AR6: -0.0032716547 | AS6: -0.12260251 | AW6: -0.33767457 | AX6: -0.25378967 | BB6: -0.14125107 | BC6: -0.12618027 | BG6: -0.9206339 | BL6: -0.18561459 | BM6: -0.23988246 | BQ6: -0.16790964 | BR6: -0.21554996 | BV6: -0.84189246
A7: 38808 | B7: 0 | C7: -1.1394635 | H7: -0.27898617 | I7: -0.14223126 | M7: -0.094189391 | N7: -0.38635653 | O7: -0.32375437 | P7: -0.33903413 | Q7: -0.1523671 | U7: -4.3515269 | Z7: -0.17545179 | AA7: -0.067959507 | AE7: 0.063556057 | AF7: 0.10044108 | AG7: 0.1840362 | AH7: -0.67775059 | AI7: -0.24171479 | AM7: 0.032463621 | AN7: 0.57268258 | AR7: -0.045888056 | AS7: -0.11793555 | AW7: -0.32649428 | AX7: -0.14517023 | BB7: -0.066744678 | BC7: 0.02934659 | BG7: -0.81817325 | BH7: 0.19178565 | BL7: -0.044151432 | BM7: 0.12167468 | BQ7: -0.19847362 | BR7: -0.15951761 | BV7: -0.60692368 | CA7: -0.66325878
A8: 38899 | B8: 0 | C8: -1.0015585 | H8: -0.23413389 | I8: -0.031527582 | M8: 0.13408398 | N8: -0.30172804 | O8: -0.2076745 | P8: -0.53895881 | Q8: -0.14307643 | U8: -4.2786756 | Z8: -0.12850961 | AA8: 0.011797254 | AE8: 0.13643565 | AF8: 0.093049265 | AG8: 0.19326913 | AH8: -0.70791221 | AI8: -0.10660845 | AM8: -0.1827575 | AN8: 0.34094475 | AR8: -0.06801817 | AS8: -0.097283696 | AW8: -0.28485189 | AX8: -0.027025429 | BB8: -0.015272214 | BC8: 0.1237648 | BG8: -0.53732891 | BH8: 0.32448917 | BL8: -0.020486505 | BM8: 0.17234978 | BQ8: -0.19106706 | BR8: -0.10342071 | BV8: 0.86497682 | CA8: -0.64984127
A9: 38991 | B9: 0 | C9: -0.9834686 | D9: 0.057742561 | H9: -0.15384404 | I9: 0.12712828 | M9: 0.4456855 | N9: -0.085070578 | O9: -0.11644018 | P9: -0.54415166 | Q9: 0.039020844 | U9: -4.1919571 | Z9: -0.069944125 | AA9: 0.090022614 | AE9: 0.1647195 | AF9: 0.10814796 | AG9: 0.1797087 | AH9: -0.71844414 | AI9: -0.11442817 | AM9: -0.6567423 | AN9: -0.49855819 | AR9: -0.047485015 | AS9: -0.034541691 | AW9: -0.24657218 | AX9: 0.071956475 | BB9: 0.029306015 | BC9: 0.26499862 | BG9: -0.49093902 | BH9: 0.35150637 | BL9: 0.14440564 | BM9: 0.63125848 | BQ9: -0.16991456 | BR9: -0.038491876 | BV9: 0.81808097 | BW9: 2.0935067 | CA9: -0.63634999
A10: 39083 | B10: 0 | C10: -0.85602967 | D10: 0.16841811 | H10: -0.084933112 | I10: 0.25143065 | J10: 0.02475172 | K10: 0.17638428 | M10: 0.6111886 | N10: 0.27630036 | O10: 0.048370239 | P10: -0.30008777 | Q10: 0.13378575 | R10: 0.023043397 | S10: 0.1016014 | U10: -4.0786878 | V10: 0.46184319 | Z10: -0.07443659 | AA10: 0.10250616 | AB10: -0.0058620994 | AC10: 0.059201022 | AE10: 0.13567834 | AF10: 0.10587565 | AG10: 0.14649456 | AH10: -0.76965438 | AI10: -0.15388374 | AJ10: -0.38841075 | AK10: -0.23904176 | AM10: -1.0755988 | AN10: -0.87844413 | AO10: -0.32627178 | AP10: -0.725218 | AR10: -0.077703381 | AS10: -0.12203953 | AT10: -0.16037362 | AU10: -0.11241952 | AW10: -0.11875774 | AX10: 0.19108781 | AY10: -0.041214306 | AZ10: 0.12106924 | BB10: 0.25555007 | BC10: 0.5572042 | BD10: 0.2951751 | BE10: 0.50910404 | BG10: -0.56103661 | BH10: 0.35728706 | BL10: 0.30321372 | BM10: 0.58941221 | BN10: 0.30226136 | BO10: 0.61042841 | BQ10: -0.13594989 | BR10: 0.047236202 | BS10: -0.10773502 | BT10: 0.0033673562 | BV10: 0.65956916 | BW10: 1.5997263 | CA10: -0.42896173
A11: 39173 | B11: 0 | C11: -0.3924008 | D11: 0.75756897 | H11: -0.066424515 | I11: 0.27589112 | J11: 0.088242193 | K11: 0.19717755 | M11: 0.62352891 | N11: 0.30818252 | O11: -0.015881071 | P11: -0.21440576 | Q11: 0.0891905 | R11: -0.055962536 | S11: 0.17417383 | U11: -3.9700188 | V11: 0.50203919 | Z11: -0.10845563 | AA11: 0.072033246 | AB11: 0.0025994722 | AC11: 0.021997972 | AE11: 0.098568426 | AF11: 0.10308849 | AG11: 0.12281027 | AH11: -0.81502304 | AI11: -0.16718004 | AJ11: -0.32155686 | AK11: -0.23133641 | AM11: -0.99399117 | AN11: -0.80679931 | AO11: -0.19268672 | AP11: -0.58377603 | AR11: -0.15113218 | AS11: -0.17256005 | AT11: -0.19043264 | AU11: -0.20726817 | AW11: -0.12870872 | AX11: 0.17264277 | AY11: 0.018057865 | AZ11: 0.12016029 | BB11: 0.37977927 | BC11: 0.62702697 | BD11: 0.44949971 | BE11: 0.64155456 | BG11: -0.42084451 | BH11: 0.3947761 | BI11: 0.48931477 | BJ11: 0.41290234 | BL11: 0.34260135 | BM11: 0.46633308 | BN11: 0.50848898 | BO11: 0.61523038 | BQ11: -0.090683442 | BR11: 0.15931285 | BS11: -0.00013106211 | BT11: 0.095781426 | BV11: 0.64156897 | BW11: 1.3302015 | CA11: 0.042817806 | CB11: 0.85093725
A12: 39264 | B12: 0 | C12: 0.059740432 | D12: 1.0762245 | H12: -0.084076859 | I12: 0.1947642 | J12: 0.10776876 | K12: 0.15457374 | M12: 0.49557842 | N12: 0.3665907 | O12: -0.0089837175 | P12: -0.35980553 | Q12: 0.12821134 | R12: -0.013167656 | S12: 0.053993886 | U12: -3.8847388 | V12: 0.51839447 | Z12: -0.10976457 | AA12: 0.020154376 | AB12: 0.020388482 | AC12: 0.019985397 | AE12: -0.022318597 | AF12: 0.072562481 | AG12: 0.059371824 | AH12: -0.8618681 | AI12: -0.18749831 | AJ12: -0.23128696 | AK12: -0.2383932 | AM12: -0.98555202 | AN12: -0.63100106 | AO12: -0.23872707 | AP12: -0.53911828 | AR12: -0.19261978 | AS12: -0.20429892 | AT12: -0.19770067 | AU12: -0.24075734 | AW12: -0.18712375 | AX12: 0.0853048 | AY12: 0.038307381 | AZ12: 0.061844052 | BB12: 0.41882292 | BC12: 0.60957393 | BD12: 0.50220724 | BE12: 0.6116523 | BG12: -0.24422159 | BH12: 0.29122425 | BI12: 0.51363333 | BJ12: 0.53958695 | BL12: 0.39845088 | BM12: 0.50514016 | BN12: 0.5858701 | BO12: 0.60744878 | BQ12: -0.097408243 | BR12: 0.13842683 | BS12: 0.022406872 | BT12: 0.085363768 | BV12: -0.53023588 | BW12: -1.4865238 | CA12: 0.48458691 | CB12: 1.3671707
A13: 39356 | B13: 0 | C13: 0.56918226 | D13: 1.5744865 | E13: 1.119288 | F13: 1.5629325 | H13: -0.05947696 | I13: 0.12248229 | J13: 0.16479281 | K13: 0.16696643 | M13: 0.19570441 | N13: 0.37341848 | O13: 0.019645801 | P13: -0.63243009 | Q13: -0.063176604 | R13: -0.02139744 | S13: -0.18752715 | U13: -3.8055171 | V13: 0.50852915 | Z13: -0.096999809 | AA13: -0.029089854 | AB13: 0.038881476 | AC13: 0.030203328 | AE13: -0.16242254 | AF13: 0.0014605406 | AG13: 0.0036665693 | AH13: -0.85923342 | AI13: -0.17146308 | AJ13: -0.22482625 | AK13: -0.1909008 | AM13: -0.3751399 | AN13: 0.22134109 | AO13: -0.22815992 | AP13: 0.1028536 | AR13: -0.16665961 | AS13: -0.1954007 | AT13: -0.15073735 | AU13: -0.15599634 | AW13: -0.21491288 | AX13: 0.027634723 | AY13: 0.065461894 | AZ13: 0.028046405 | BB13: 0.33686093 | BC13: 0.43188104 | BD13: 0.47723922 | BE13: 0.38451646 | BG13: -0.18990306 | BH13: 0.29910196 | BI13: 0.54274296 | BJ13: 0.51107445 | BL13: 0.43249844 | BM13: 0.3473723 | BN13: 0.84628638 | BO13: 0.55232564 | BQ13: -0.033833236 | BR13: 0.20112689 | BS13: 0.10410015 | BT13: 0.17950637 | BV13: -0.3649554 | BW13: -1.2604614 | BX13: 0.78734043 | BY13: -0.46343399 | CA13: 0.82603711 | CB13: 1.7624146
A14: 39448 | B14: 0 | C14: 1.0003187 | D14: 1.882455 | E14: 1.4063698 | F14: 1.8259914 | H14: -0.039843722 | I14: 0.058523078 | J14: 0.20463134 | K14: 0.16081695 | L14: 0.14076134 | M14: 0.084341406 | N14: 0.40493895 | O14: 0.22144315 | P14: -0.72849779 | Q14: -0.30659234 | R14: -0.153074 | S14: -0.26967914 | T14: -0.28394313 | U14: -3.7476787 | V14: 0.43558586 | W14: 0.54214141 | X14: 0.4999459 | Z14: -0.13092935 | AA14: -0.060740145 | AB14: 0.026651088 | AC14: -0.016102663 | AD14: -0.012858665 | AE14: -0.19932932 | AF14: -0.04047312 | AG14: -0.015712909 | AH14: -0.90874526 | AI14: -0.16939465 | AJ14: -0.25422767 | AK14: -0.22008461 | AL14: -0.29661572 | AM14: -0.46861528 | AN14: 0.47709252 | AO14: -0.33032721 | AP14: 0.054560514 | AQ14: 0.036819652 | AR14: -0.06269324 | AS14: 0.024610883 | AT14: -0.063868762 | AU14: 0.054376379 | AV14: -0.0072603015 | AW14: -0.27861377 | AX14: -0.13953491 | AY14: 0.033886037 | AZ14: -0.044873455 | BA14: -0.045394832 | BB14: 0.26296498 | BC14: 0.010412308 | BD14: 0.38871684 | BE14: 0.17482987 | BF14: 0.25467806 | BG14: -0.053200036 | BH14: 0.50457398 | BI14: 0.71897175 | BJ14: 0.57865092 | BL14: 0.35430694 | BM14: 0.061606431 | BN14: 0.56297862 | BO14: 0.27867432 | BP14: 0.41699846 | BQ14: 0.032984615 | BR14: 0.24968357 | BS14: 0.19005374 | BT14: 0.26192077 | BU14: 0.19192901 | BV14: -0.20110122 | BW14: -0.91699785 | BX14: 0.64527072 | BY14: -0.3751902 | CA14: 0.93476224 | CB14: 1.6435094
A15: 39539 | B15: 0 | C15: 0.74722526 | D15: 1.1556531 | E15: 1.3119767 | F15: 1.2472218 | H15: -0.09519623 | I15: -0.037343804 | J15: 0.15748885 | K15: 0.041897539 | L15: 0.071821015 | M15: -0.17558633 | N15: 0.26079306 | O15: 0.14015651 | P15: -0.73628706 | Q15: -0.37348522 | R15: -0.25183141 | S15: -0.24964915 | T15: -0.26234693 | U15: -3.7255425 | V15: 0.3217145 | W15: 0.49763376 | X15: 0.41606932 | Z15: -0.13854067 | AA15: -0.032346972 | AB15: 0.025323995 | AC15: -0.030178422 | AD15: -0.014889388 | AE15: -0.12365103 | AF15: -0.015949028 | AG15: 0.018418687 | AH15: -0.96117177 | AI15: -0.1779902 | AJ15: -0.27144353 | AK15: -0.2479333 | AL15: -0.30568294 | AM15: -0.71227811 | AN15: 0.22142806 | AO15: -0.48178218 | AP15: -0.12128411 | AQ15: -0.19617519 | AR15: -0.15098701 | AS15: 0.00023801013 | AT15: -0.11296468 | AU15: -0.085644184 | AV15: -0.11564918 | AW15: -0.23688128 | AX15: -0.094421505 | AY15: 0.051415309 | AZ15: -0.012745439 | BA15: 0.0015520343 | BB15: 0.40458994 | BC15: 0.034840144 | BD15: 0.45326182 | BE15: 0.31535879 | BF15: 0.40413048 | BG15: 0.15795395 | BH15: 0.57507998 | BI15: 0.80906213 | BJ15: 0.70520758 | BK15: 0.87783681 | BL15: 0.36992746 | BM15: 0.032948878 | BN15: 0.43176194 | BO15: 0.19966171 | BP15: 0.39898988 | BQ15: -0.041084365 | BR15: 0.07330696 | BS15: 0.14889633 | BT15: 0.10787922 | BU15: 0.094460464 | BV15: -0.17540392 | BW15: -0.87044052 | BX15: 0.43453633 | BY15: -0.44779478 | CA15: 0.77060279 | CB15: 0.87709941 | CC15: 1.1512282 | CD15: 1.0380109
A16: 39630 | B16: 0 | C16: 0.41871658 | D16: 0.3640246 | E16: 0.98763929 | F16: 0.60158553 | H16: -0.19650435 | I16: -0.14592353 | J16: 0.032244598 | K16: -0.1315646 | L16: -0.048642082 | M16: -0.21333334 | N16: 0.16432365 | O16: 0.16494899 | P16: -0.82975834 | Q16: -0.33632251 | R16: -0.18434718 | S16: -0.28883826 | T16: -0.29934216 | U16: -3.7284931 | V16: 0.20560882 | W16: 0.43737404 | X16: 0.30815211 | Z16: -0.10373831 | AA16: 0.0064793392 | AB16: 0.016995097 | AC16: 0.0039056181 | AD16: 0.019389418 | AE16: 0.05952538 | AF16: 0.023658309 | AG16: 0.083129161 | AH16: -1.0266679 | AI16: -0.2007048 | AJ16: -0.30528479 | AK16: -0.29144245 | AL16: -0.33831848 | AM16: -0.91463049 | AN16: 0.055744726 | AO16: -0.47345724 | AP16: -0.22811932 | AQ16: -0.38186418 | AR16: -0.25918013 | AS16: -0.10913348 | AT16: -0.20546873 | AU16: -0.25023432 | AV16: -0.24699207 | AW16: -0.26131765 | AX16: -0.064762261 | AY16: 0.013502734 | AZ16: -0.046078235 | BA16: -0.012326514 | BB16: 0.57830431 | BC16: 0.2239502 | BD16: 0.5708165 | BE16: 0.492447 | BF16: 0.57593906 | BG16: 0.30750149 | BH16: 0.54817854 | BI16: 0.70023689 | BJ16: 0.73912649 | BK16: 0.9398614 | BL16: 0.47271806 | BM16: 0.089548785 | BN16: 0.51426663 | BO16: 0.27739638 | BP16: 0.48326787 | BQ16: -0.17493127 | BR16: -0.11457829 | BS16: 0.015265079 | BT16: -0.13055962 | BU16: -0.07650496 | BV16: 0.027606386 | BW16: 0.59435083 | BX16: -0.84322412 | BY16: -0.24884495 | CA16: 0.55586741 | CB16: 0.085904613 | CC16: 0.96804735 | CD16: 0.5149846
A17: 39722 | B17: 0 | C17: 0.10065797 | D17: -0.47511336 | E17: 0.75388633 | F17: 0.034604473 | G17: 0.39174486 | H17: -0.2010348 | I17: -0.18373282 | J17: -0.040437575 | K17: -0.14445285 | L17: -0.054964942 | M17: 0.05319425 | N17: 0.14490929 | O17: 0.27519327 | P17: -0.53895881 | Q17: 0.066892875 | R17: 0.0032919139 | S17: 0.0037737663 | T17: -0.011455378 | U17: -3.6204272 | V17: 0.24356593 | W17: 0.45434443 | X17: 0.36037464 | Z17: 0.00034876873 | AA17: 0.10466769 | AB17: 0.048226565 | AC17: 0.1179283 | AD17: 0.11307771 | AE17: 0.23039327 | AF17: 0.043219875 | AG17: 0.11139756 | AH17: -1.0786335 | AI17: -0.26720079 | AJ17: -0.34496737 | AK17: -0.30898166 | AL17: -0.36164125 | AM17: -0.69942622 | AN17: -0.25489089 | AO17: -0.027612729 | AP17: 0.071763737 | AQ17: -0.16011107 | AR17: -0.26134191 | AS17: -0.15524272 | AT17: -0.22986218 | AU17: -0.21260258 | AV17: -0.22068884 | AW17: -0.2607885 | AX17: -0.040043844 | AY17: -0.00815659 | AZ17: -0.048334813 | BA17: -0.011443518 | BB17: 0.69525316 | BC17: 0.50326886 | BD17: 0.64041216 | BE17: 0.55839649 | BF17: 0.65380542 | BG17: -0.14029676 | BH17: 0.049287603 | BI17: 0.29062951 | BJ17: 0.057336447 | BK17: 0.29077379 | BL17: 0.58156271 | BM17: 0.17973652 | BN17: 0.45582565 | BO17: 0.34928671 | BP17: 0.56185642 | BQ17: -0.25690221 | BR17: -0.3296938 | BS17: -0.082293681 | BT17: -0.26100455 | BU17: -0.17252069 | BV17: 0.2936107 | BW17: 0.70166664 | BX17: -0.52813661 | BY17: 0.24586013 | BZ17: 0.4613861 | CA17: 0.3782375 | CB17: -0.53967145 | CC17: 0.81459869 | CD17: 0.07908052
A18: 39814 | B18: 1 | C18: 0.15011571 | D18: -0.86215978 | E18: 0.69965931 | F18: -0.063849918 | G18: 0.34749919 | H18: -0.032732446 | I18: 0.0092299712 | J18: 0.044730538 | K18: 0.098682503 | L18: 0.12890639 | M18: 0.40260697 | N18: 0.28350231 | O18: 0.43508032 | P18: 0.56452154 | Q18: 0.92535144 | R18: 0.54810366 | S18: 0.99017821 | T18: 0.94197007 | U18: -3.3934125 | V18: 0.46619063 | W18: 0.54476772 | X18: 0.56713955 | Y18: 0.63048315 | Z18: 0.13959806 | AA18: 0.2908669 | AB18: 0.14684494 | AC18: 0.26522613 | AD18: 0.23021466 | AE18: 0.26510776 | AF18: 0.041825887 | AG18: 0.096444934 | AH18: -1.1143411 | AI18: -0.25038909 | AJ18: -0.33011995 | AK18: -0.29550139 | AL18: -0.35888763 | AM18: -0.40292983 | AN18: 0.051629134 | AO18: 0.43515747 | AP18: 0.36689804 | AQ18: 0.16590583 | AR18: -0.020627992 | AS18: 0.068970898 | AT18: 0.061346974 | AU18: 0.25048337 | AV18: 0.14518298 | AW18: 0.10301261 | AX18: 0.33311349 | AY18: 0.12724037 | AZ18: 0.2935964 | BA18: 0.26398973 | BB18: 0.96981395 | BC18: 0.99258589 | BD18: 0.68687624 | BE18: 0.85352524 | BF18: 0.91708149 | BG18: -0.48219764 | BH18: -0.42624151 | BI18: 0.065345609 | BJ18: -0.41788345 | BK18: -0.1859743 | BL18: 0.86606782 | BM18: 0.6170635 | BN18: 0.58689052 | BO18: 0.69943114 | BP18: 0.84963076 | BQ18: -0.2209798 | BR18: -0.37535696 | BS18: -0.080441583 | BT18: -0.18832404 | BU18: -0.11633504 | BV18: 0.74637148 | BW18: 1.009481 | BX18: 0.087409112 | BY18: 0.93761138 | BZ18: 0.88208174 | CA18: 0.3711283 | CB18: -0.67927067 | CC18: 0.64238156 | CD18: -0.098726502
A19: 39904 | B19: 0 | C19: 0.25423114 | D19: -0.49992733 | E19: 0.44965873 | F19: -0.08862164 | G19: 0.35373373 | H19: 0.097369859 | I19: 0.24993819 | J19: 0.14035473 | K19: 0.27116117 | L19: 0.25174217 | M19: 0.53134984 | N19: 0.20712622 | O19: 0.38799427 | P19: 1.4343237 | Q19: 1.5534012 | R19: 1.0451827 | S19: 1.6714882 | T19: 1.620842 | U19: -3.1687505 | V19: 0.73270102 | W19: 0.63697773 | X19: 0.75188106 | Y19: 0.77803288 | Z19: 0.23206305 | AA19: 0.39846739 | AB19: 0.23362313 | AC19: 0.33941621 | AD19: 0.29200477 | AE19: 0.2224238 | AF19: 0.062805664 | AG19: 0.094474649 | AH19: -1.1583383 | AI19: -0.24012321 | AJ19: -0.32880639 | AK19: -0.29682004 | AL19: -0.36499746 | AM19: 0.060421243 | AN19: 0.6073461 | AO19: 0.68211178 | AP19: 0.73774964 | AQ19: 0.6281988 | AR19: -0.022263574 | AS19: 0.21105715 | AT19: 0.13851327 | AU19: 0.235298 | AV19: 0.14491701 | AW19: 0.171731 | AX19: 0.3566689 | AY19: 0.17237679 | AZ19: 0.33194164 | BA19: 0.2885972 | BB19: 1.0403281 | BC19: 0.89272917 | BD19: 0.6352208 | BE19: 0.82457213 | BF19: 0.88850005 | BG19: -0.38407417 | BH19: -0.53854587 | BI19: 0.03047706 | BJ19: -0.30913674 | BK19: -0.11268088 | BL19: 1.0473369 | BM19: 0.81679676 | BN19: 0.73483093 | BO19: 0.86838287 | BP19: 0.98141998 | BQ19: -0.12924419 | BR19: -0.13029938 | BS19: -0.036479962 | BT19: -0.029337948 | BU19: 0.0028204106 | BV19: 0.88859028 | BW19: 1.1336284 | BX19: 0.24874813 | BY19: 1.1129363 | BZ19: 0.89455309 | CA19: 0.26188151 | CB19: -0.61309197 | CC19: 0.17588331 | CD19: -0.37653445 | CE19: 0.11151462
A20: 39995 | B20: 0 | C20: 0.46170284 | D20: 0.043590795 | E20: 0.27951899 | F20: 0.056263408 | G20: 0.44229089 | H20: 0.18675925 | I20: 0.49745108 | J20: 0.23207836 | K20: 0.36734705 | L20: 0.3167706 | M20: 0.49413609 | N20: 0.16348392 | O20: 0.30760113 | P20: 1.0708243 | Q20: 1.3601551 | R20: 0.90692228 | S20: 1.1620297 | T20: 1.177087 | U20: -2.9640944 | V20: 1.0058977 | W20: 0.73187718 | X20: 0.89076357 | Y20: 0.89121255 | Z20: 0.25622457 | AA20: 0.38702653 | AB20: 0.25109792 | AC20: 0.31863809 | AD20: 0.28292578 | AE20: 0.021309314 | AF20: 0.051399557 | AG20: 0.028013856 | AH20: -1.1670679 | AI20: -0.17098895 | AJ20: -0.29230175 | AK20: -0.24735463 | AL20: -0.32465833 | AM20: 0.16218442 | AN20: 0.84638266 | AO20: 0.74248419 | AP20: 0.70837782 | AQ20: 0.72005467 | AR20: 0.060112152 | AS20: 0.52351707 | AT20: 0.27164667 | AU20: 0.35004036 | AV20: 0.25793926 | AW20: 0.2888264 | AX20: 0.48020895 | AY20: 0.27307561 | AZ20: 0.40633711 | BA20: 0.34672448 | BB20: 1.2186912 | BC20: 0.89925721 | BD20: 0.76919827 | BE20: 0.97234611 | BF20: 0.9999884 | BG20: -0.25530437 | BH20: -0.55919012 | BI20: -0.0091859522 | BJ20: -0.15615527 | BK20: -0.0024858327 | BL20: 0.99372256 | BM20: 0.62820915 | BN20: 0.62069248 | BO20: 0.65252298 | BP20: 0.77792516 | BQ20: 0.024027852 | BR20: 0.29405967 | BS20: 0.11488325 | BT20: 0.21620118 | BU20: 0.18560038 | BV20: 0.72298059 | BW20: 0.74088369 | BX20: 1.2619772 | BY20: 0.85070352 | BZ20: 0.52757944 | CA20: 0.11956309 | CB20: -0.52581775 | CC20: -0.29307273 | CD20: -0.60182754 | CE20: -0.14226794
A21: 40087 | B21: 0 | C21: 0.82067066 | D21: 0.73013856 | E21: 0.17488149 | F21: 0.40945609 | G21: 0.6721227 | H21: 0.24952588 | I21: 0.58479829 | J21: 0.26478327 | K21: 0.40770014 | L21: 0.34780441 | M21: 0.39606803 | N21: 0.26156139 | O21: 0.25553489 | P21: 0.37757899 | Q21: 0.6559218 | R21: 0.64027725 | S21: 0.38202126 | T21: 0.45896628 | U21: -2.8139386 | V21: 1.0612851 | W21: 0.78826708 | X21: 0.93738027 | Y21: 0.93453296 | Z21: 0.30502266 | AA21: 0.32758066 | AB21: 0.27581967 | AC21: 0.32208105 | AD21: 0.2984344 | AE21: -0.060326026 | AF21: 0.10813898 | AG21: 0.0036598071 | AH21: -1.2516129 | AI21: -0.21066657 | AJ21: -0.37579718 | AK21: -0.31448835 | AL21: -0.38426936 | AM21: -0.31493917 | AN21: 0.30220901 | AO21: 0.038944557 | AP21: 0.10155791 | AQ21: 0.25273659 | AR21: 0.17201074 | AS21: 0.71053241 | AT21: 0.36401682 | AU21: 0.48909305 | AV21: 0.40021828 | AW21: 0.34419505 | AX21: 0.52807718 | AY21: 0.32078725 | AZ21: 0.40247883 | BA21: 0.35254064 | BB21: 1.1882104 | BC21: 0.69223054 | BD21: 0.81870549 | BE21: 0.7710901 | BF21: 0.82738207 | BG21: -0.18677235 | BH21: -0.046177004 | BI21: 0.0025948883 | BJ21: -0.070017228 | BK21: 0.051103318 | BL21: 1.0096452 | BM21: 0.51616706 | BN21: 0.60179358 | BO21: 0.56343134 | BP21: 0.68137323 | BQ21: 0.23203488 | BR21: 0.72264432 | BS21: 0.25152153 | BT21: 0.5156892 | BU21: 0.42114328 | BV21: 0.4052456 | BW21: 0.11894096 | BX21: 0.77558513 | BY21: 0.21758477 | BZ21: 0.14079758 | CA21: -0.044725916 | CB21: -0.50973978 | CC21: -0.69912397 | CD21: -0.75936021 | CE21: -0.40645171
A22: 40179 | B22: 0 | C22: 1.0912605 | D22: 0.9543805 | E22: 0.063239623 | F22: 0.68305891 | G22: 0.78871623 | H22: 0.2690549 | I22: 0.39170023 | J22: 0.26469397 | K22: 0.38104708 | L22: 0.33201962 | M22: 0.27878899 | N22: 0.39671008 | O22: 0.30338406 | P22: 0.20621498 | Q22: -0.25642269 | R22: 0.5925445 | S22: 0.1158256 | T22: 0.24356762 | U22: -2.7020446 | V22: 0.90979401 | W22: 0.83123926 | X22: 0.92136085 | Y22: 0.93139563 | Z22: 0.39830828 | AA22: 0.27816123 | AB22: 0.36309948 | AC22: 0.37066689 | AD22: 0.35591991 | AE22: 0.036672532 | AF22: 0.19189005 | AG22: 0.049047133 | AH22: -1.2824865 | AI22: -0.20477929 | AJ22: -0.3579466 | AK22: -0.28819077 | AL22: -0.36680784 | AM22: 0.01836962 | AN22: 0.33114377 | AO22: 0.31503625 | AP22: 0.42011256 | AQ22: 0.53433201 | AR22: 0.16237983 | AS22: 0.30006275 | AT22: 0.24191779 | AU22: 0.39911555 | AV22: 0.36097006 | AW22: 0.47349626 | AX22: 0.32338724 | AY22: 0.43152188 | AZ22: 0.45804851 | BA22: 0.41412431 | BB22: 1.2643846 | BC22: 0.41364803 | BD22: 0.96302134 | BE22: 0.7244345 | BF22: 0.80096734 | BG22: -0.19381695 | BH22: 0.28652799 | BI22: -0.1165502 | BJ22: -0.079178293 | BK22: 0.012554544 | BL22: 0.84286563 | BM22: -0.027976391 | BN22: 0.50942236 | BO22: 0.1994821 | BP22: 0.34512871 | BQ22: 0.25170079 | BR22: 0.69861737 | BS22: 0.20691397 | BT22: 0.49461682 | BU22: 0.40400582 | BV22: -0.17144808 | BW22: -0.97788722 | BX22: 0.02986043 | BY22: -0.68056194 | BZ22: -0.54487378 | CA22: -0.25441663 | CB22: -0.75388349 | CC22: -0.95477578 | CD22: -0.89324102 | CE22: -0.70601328 | CG22: -1
A23: 40269 | B23: 0 | C23: 1.5101555 | D23: 1.273587 | E23: 0.53053094 | F23: 1.1492888 | G23: 1.0375447 | H23: 0.197124 | I23: 0.12947436 | J23: 0.25048802 | K23: 0.22676018 | L23: 0.2183502 | M23: 0.046307487 | N23: 0.33631324 | O23: 0.15929996 | P23: 0.019272428 | Q23: -1.0126838 | R23: 0.47897347 | S23: -0.15588558 | T23: 0.044694752 | U23: -2.7164319 | V23: 0.595221 | W23: 0.80220439 | X23: 0.72852685 | Y23: 0.793662 | Z23: 0.49018726 | AA23: 0.27753116 | AB23: 0.4313578 | AC23: 0.39971067 | AD23: 0.40455181 | AE23: 0.11887061 | AF23: 0.2170155 | AG23: 0.10419407 | AH23: -1.3232521 | AI23: -0.20084364 | AJ23: -0.34677844 | AK23: -0.27957807 | AL23: -0.3642699 | AM23: -0.021940329 | AN23: -0.064736665 | AO23: 0.44658762 | AP23: 0.32117472 | AQ23: 0.41287725 | AR23: 0.11588314 | AS23: 0.22650771 | AT23: 0.28684301 | AU23: 0.2698914 | AV23: 0.26749079 | AW23: 0.56595863 | AX23: 0.34411286 | AY23: 0.46062806 | AZ23: 0.45659747 | BA23: 0.44727931 | BB23: 1.4469216 | BC23: 0.57095506 | BD23: 1.0023646 | BE23: 0.81291806 | BF23: 0.92845938 | BG23: -0.037930173 | BH23: 0.3439202 | BI23: -0.16235838 | BJ23: 0.13452882 | BK23: 0.16165353 | BL23: 0.87704874 | BM23: -0.20532752 | BN23: 0.52877766 | BO23: 0.15852579 | BP23: 0.32994401 | BQ23: 0.17074582 | BR23: 0.44338235 | BS23: 0.20039955 | BT23: 0.32642037 | BU23: 0.26365937 | BV23: -0.39514279 | BW23: -1.3677483 | BX23: -0.22127497 | BY23: -0.98405264 | BZ23: -0.74015155 | CA23: -0.29359416 | CB23: -0.66943863 | CC23: -0.85442947 | CD23: -0.74791046 | CE23: -0.76815145 | CG23: -1
A24: 40360 | B24: 0 | C24: 1.5670241 | D24: 1.1208659 | E24: 0.79851685 | F24: 1.1052457 | G24: 0.93895437 | H24: 0.21664997 | I24: 0.038796203 | J24: 0.35403026 | K24: 0.20301339 | L24: 0.21561979 | M24: -0.032509696 | N24: 0.26875981 | O24: 0.09837336 | P24: -0.41692686 | Q24: -1.0647116 | R24: 0.26170715 | S24: -0.63050925 | T24: -0.35079747 | U24: -2.8209077 | V24: 0.18842406 | W24: 0.72149578 | X24: 0.42202843 | Y24: 0.57076064 | Z24: 0.61987039 | AA24: 0.39098637 | AB24: 0.49645363 | AC24: 0.45739584 | AD24: 0.47849194 | AE24: 0.30466269 | AF24: 0.20727259 | AG24: 0.18455209 | AH24: -1.2345697 | AI24: -0.082208408 | AJ24: -0.19911561 | AK24: -0.085763222 | AL24: -0.19549784 | AM24: 0.19915859 | AN24: 0.029061906 | AO24: 0.72052324 | AP24: 0.45299009 | AQ24: 0.54229575 | AR24: 0.058992565 | AS24: -0.0018356929 | AT24: 0.34198509 | AU24: 0.11362359 | AV24: 0.1562469 | AW24: 0.69187694 | AX24: 0.35181418 | AY24: 0.54689381 | AZ24: 0.48050726 | BA24: 0.49960185 | BB24: 1.4753943 | BC24: 0.36047276 | BD24: 0.86269206 | BE24: 0.65585105 | BF24: 0.85018334 | BG24: 0.24956182 | BH24: 0.50162269 | BI24: -0.048023236 | BJ24: 0.51888439 | BK24: 0.4658164 | BL24: 1.0623498 | BM24: 0.082748297 | BN24: 0.61481165 | BO24: 0.34423153 | BP24: 0.52807888 | BQ24: 0.15868265 | BR24: 0.19901849 | BS24: 0.31561167 | BT24: 0.26655935 | BU24: 0.22171505 | BV24: -0.27944981 | BW24: -1.0680355 | BX24: -0.30920269 | BY24: -0.79299031 | BZ24: -0.48463487 | CA24: -0.32692157 | CB24: -0.53808671 | CC24: -0.70877944 | CD24: -0.61555389 | CE24: -0.77427364 | CG24: -1
A25: 40452 | B25: 0 | C25: 1.8476022 | D25: 1.0413737 | E25: 1.2148003 | F25: 1.2620253 | G25: 1.0892197 | H25: 0.30418073 | I25: 0.070938418 | J25: 0.43291713 | K25: 0.25310068 | L25: 0.28562824 | M25: 0.035175943 | N25: 0.2510711 | O25: 0.19193374 | P25: -0.34682341 | Q25: -0.51841978 | R25: 0.12180081 | S25: -0.61396274 | T25: -0.28582106 | U25: -2.922161 | V25: -0.14241344 | W25: 0.555095 | X25: 0.1366794 | Y25: 0.3681666 | Z25: 0.81863276 | AA25: 0.55222565 | AB25: 0.56140847 | AC25: 0.5796838 | AD25: 0.60632682 | AE25: 0.4800771 | AF25: 0.26690296 | AG25: 0.31124854 | AH25: -1.1583052 | AI25: 0.11363672 | AJ25: -0.076304734 | AK25: 0.062195777 | AL25: -0.057266576 | AM25: 0.24968903 | AN25: 0.44380099 | AO25: 0.61399381 | AP25: 0.36626498 | AQ25: 0.49777313 | AR25: -0.0010828705 | AS25: -0.28380725 | AT25: 0.27973711 | AU25: -0.059262706 | AV25: 0.042330514 | AW25: 0.84246866 | AX25: 0.43493236 | AY25: 0.63299196 | AZ25: 0.50991585 | BA25: 0.55908665 | BB25: 1.4340441 | BC25: 0.34520958 | BD25: 0.71046286 | BE25: 0.41908091 | BF25: 0.68264384 | BG25: 0.39728371 | BH25: 0.5803038 | BI25: 0.44557308 | BJ25: 0.70980011 | BK25: 0.59264681 | BL25: 1.2110592 | BM25: 0.24285794 | BN25: 0.65637883 | BO25: 0.45848668 | BP25: 0.65952416 | BQ25: 0.19837242 | BR25: -0.0497528 | BS25: 0.43070741 | BT25: 0.26343449 | BU25: 0.24445226 | BV25: 0.088536244 | BW25: -0.33743672 | BX25: -0.20650804 | BY25: -0.25064994 | BZ25: -0.045778468 | CA25: -0.38418003 | CB25: -0.40909748 | CC25: -0.61213482 | CD25: -0.54507216 | CE25: -0.76228246 | CG25: -1
A26: 40544 | B26: 0 | C26: 1.6742322 | D26: 0.5911704 | E26: 1.0598491 | F26: 0.81385918 | G26: 0.81781428 | H26: 0.32695953 | I26: 0.075156423 | J26: 0.30821859 | K26: 0.19675126 | L26: 0.27719407 | M26: -0.13583045 | N26: 0.083230748 | O26: 0.21615229 | P26: -0.3779805 | Q26: -0.41808047 | R26: -0.59748237 | S26: -0.66331199 | T26: -0.3335205 | U26: -3.0025377 | V26: -0.3954289 | W26: 0.31073056 | X26: -0.086149146 | Y26: 0.20388837 | Z26: 0.96302676 | AA26: 0.6071766 | AB26: 0.56493816 | AC26: 0.62722606 | AD26: 0.66942102 | AE26: 0.62441853 | AF26: 0.42036143 | AG26: 0.4434062 | AH26: -1.195147 | AI26: 0.10636822 | AJ26: -0.077390936 | AK26: 0.023296308 | AL26: -0.072618358 | AM26: -0.020752207 | AN26: -0.030749979 | AO26: 0.2472352 | AP26: -0.014182065 | AQ26: 0.19984032 | AR26: -0.037317815 | AS26: -0.32742767 | AT26: -0.017938909 | AU26: -0.17833414 | AV26: -0.027997212 | AW26: 0.89690298 | AX26: 0.36958265 | AY26: 0.45549328 | AZ26: 0.43184236 | BA26: 0.53318216 | BB26: 1.572421 | BC26: 0.43255715 | BD26: 0.57950077 | BE26: 0.49008434 | BF26: 0.74342645 | BG26: 0.60167124 | BH26: 0.79037758 | BI26: 0.89836371 | BJ26: 0.87881783 | BK26: 0.77765061 | BL26: 1.4549657 | BM26: 0.73804905 | BN26: 0.61404652 | BO26: 0.71016406 | BP26: 0.91151654 | BQ26: 0.21388509 | BR26: -0.055891241 | BS26: 0.41139901 | BT26: 0.19913972 | BU26: 0.23969661 | BV26: 0.033673493 | BW26: 0.21854597 | BX26: -0.71768014 | BY26: -0.28965833 | BZ26: -0.16292965 | CA26: -0.52520314 | CB26: -0.32634184 | CC26: -0.71965251 | CD26: -0.60577059 | CE26: -0.80874668 | CG26: -1
A27: 40634 | B27: 1 | C27: 1.3486252 | D27: -0.16380203 | E27: 0.76102617 | F27: 0.22339241 | G27: 0.44764035 | H27: 0.46707503 | I27: 0.35037877 | J27: 0.31679886 | K27: 0.3295592 | L27: 0.39996185 | M27: -0.1962541 | N27: -0.087299216 | O27: 0.15111142 | P27: -0.60127299 | Q27: -0.44409436 | R27: -1.2904302 | S27: -0.75765615 | T27: -0.55267502 | U27: -3.0879822 | V27: -0.48893533 | W27: 0.064207709 | X27: -0.26464562 | Y27: 0.046491313 | Z27: 0.86987811 | AA27: 0.40823774 | AB27: 0.43759231 | AC27: 0.40584666 | AD27: 0.49863564 | AE27: 0.26145522 | AF27: 0.24183402 | AG27: 0.28855891 | AH27: -1.2107512 | AI27: 0.13701142 | AJ27: -0.05019796 | AK27: 0.015332708 | AL27: -0.061976237 | AM27: -0.52903485 | AN27: -0.39857918 | AO27: -0.38132607 | AP27: -0.5578982 | AQ27: -0.30418543 | AR27: 0.10412318 | AS27: -0.019281828 | AT27: 0.13584568 | AU27: 0.070184946 | AV27: 0.16784366 | AW27: 1.0470104 | AX27: 0.41989979 | AY27: 0.50219011 | AZ27: 0.47942296 | BA27: 0.57328985 | BB27: 1.6025197 | BC27: 0.2184971 | BD27: 0.540635 | BE27: 0.42031622 | BF27: 0.64111076 | BG27: 1.2370587 | BH27: 1.2667977 | BI27: 1.3436744 | BJ27: 1.4946982 | BK27: 1.4688651 | BL27: 1.1943182 | BM27: 0.38255245 | BN27: 0.15325805 | BO27: 0.20098905 | BP27: 0.41553217 | BQ27: 0.18349412 | BR27: 0.018841865 | BS27: 0.29586254 | BT27: 0.06751257 | BU27: 0.18335687 | BV27: 0.060739609 | BW27: 0.48571809 | BX27: -0.83363781 | BY27: -0.13463961 | BZ27: -0.1534447 | CA27: -0.48292672 | CB27: -0.22817656 | CC27: -0.59799655 | CD27: -0.40090044 | CE27: -0.61912673 | CG27: -1
A28: 40725 | B28: 0 | C28: 1.5640429 | D28: -0.0030231177 | E28: 0.76655173 | F28: 0.31333554 | G28: 0.60792193 | H28: 0.4373617 | I28: 0.28646938 | J28: 0.21474022 | K28: 0.22358742 | L28: 0.31415297 | M28: -0.30968068 | N28: -0.19922392 | O28: 0.06020068 | P28: -0.59608015 | Q28: -0.12821134 | R28: -1.0567044 | S28: -0.52542438 | T28: -0.55793323 | U28: -3.1141025 | V28: -0.38582467 | W28: -0.11925071 | X28: -0.31277892 | Y28: -0.038053922 | Z28: 0.6297359 | AA28: 0.010607248 | AB28: 0.25625874 | AC28: 0.044701087 | AD28: 0.19824927 | AE28: -0.400353 | AF28: -0.060845653 | AG28: -0.035608981 | AH28: -0.93987349 | AI28: 0.35890172 | AJ28: 0.21759295 | AK28: 0.41677327 | AL28: 0.31370071 | AM28: -0.74502154 | AN28: -0.74213096 | AO28: -0.5868822 | AP28: -0.69704517 | AQ28: -0.51781902 | AR28: 0.048848088 | AS28: -0.016633058 | AT28: -0.012107079 | AU28: -0.052879554 | AV28: 0.060265038 | AW28: 0.89888783 | AX28: 0.18069537 | AY28: 0.35002173 | AZ28: 0.2385486 | BA28: 0.37707766 | BB28: 1.3255433 | BC28: -0.21042673 | BD28: 0.10275497 | BE28: -0.11535667 | BF28: 0.1532389 | BG28: 1.8593205 | BH28: 1.5994168 | BI28: 1.7527049 | BJ28: 2.0116693 | BK28: 2.1023865 | BL28: 0.84933999 | BM28: -0.25683979 | BN28: -0.15054836 | BO28: -0.35250007 | BP28: -0.1667479 | BQ28: 0.16508533 | BR28: 0.0094631036 | BS28: 0.13344583 | BT28: -0.021794622 | BU28: 0.13735465 | BV28: -0.1831938 | BW28: 0.10255558 | BX28: -0.91250906 | BY28: -0.32208749 | BZ28: -0.48675526 | CA28: -0.43079908 | CB28: -0.12518931 | CC28: -0.44187841 | CD28: -0.20809696 | CE28: -0.43801014 | CG28: -1
A29: 40817 | B29: 0 | C29: 1.6224535 | D29: -0.228315 | E29: 0.5575485 | F29: 0.22251904 | G29: 0.57201324 | H29: 0.42805047 | I29: 0.16077482 | J29: 0.15297699 | K29: 0.16687037 | L29: 0.24452194 | M29: -0.96716175 | N29: -0.54260399 | O29: -0.21232987 | P29: -0.50520529 | Q29: -0.11334626 | R29: -0.55962536 | S29: -0.25777726 | T29: -0.49596151 | U29: -3.1943692 | V29: -0.35820771 | W29: -0.30242776 | X29: -0.39453635 | Y29: -0.17830345 | Z29: 0.13122948 | AA29: -0.73908539 | AB29: -0.11923607 | AC29: -0.57084725 | AD29: -0.32030988 | AE29: -1.2208858 | AF29: -0.47105069 | AG29: -0.3835333 | AH29: -1.0182116 | AI29: 0.17061582 | AJ29: 0.22353756 | AK29: 0.26232412 | AL29: 0.2034858 | AM29: -1.035562 | AN29: -1.0102146 | AO29: -0.46617935 | AP29: -0.87025417 | AQ29: -0.79927523 | AR29: 0.37504913 | AS29: 0.61671245 | AT29: 0.218234 | AU29: 0.51437938 | AV29: 0.48270085 | AW29: 0.56711892 | AX29: -0.24034689 | AY29: 0.1279022 | AZ29: -0.14308532 | BA29: 0.047547382 | BB29: 0.90223465 | BC29: -0.74678835 | BD29: -0.27501038 | BE29: -0.78896221 | BF29: -0.47547062 | BG29: 0.90277855 | BH29: 0.50224729 | BI29: 0.90307325 | BJ29: 0.50756024 | BK29: 0.81012908 | BL29: 0.56286257 | BM29: -0.78157298 | BN29: -0.46586232 | BO29: -0.76139652 | BP29: -0.61416188 | BQ29: 0.21468153 | BR29: 0.024104705 | BS29: -0.016416947 | BT29: 0.027849946 | BU29: 0.16370106 | BV29: -0.543757 | BW29: -0.67367433 | BX29: -0.95563665 | BY29: -0.65212352 | BZ29: -0.92043938 | CA29: -0.18792569 | CB29: 0.23651843 | CC29: -0.11497318 | CD29: 0.20566983 | CE29: -0.061991275 | CG29: -1
A30: 40909 | B30: 0 | C30: 1.3978931 | D30: -0.28022541 | E30: 0.21322803 | F30: -0.14904787 | G30: 0.23130634 | H30: 0.23256392 | I30: -0.12251933 | J30: -0.031268974 | K30: -0.13711947 | L30: -0.033303681 | M30: -0.5757724 | N30: -0.41429659 | O30: -0.17148024 | P30: -0.686955 | Q30: -0.22111811 | R30: -0.56620919 | S30: -0.321641 | T30: -0.65614901 | U30: -3.4284491 | V30: -0.56047085 | W30: -0.57746385 | X30: -0.6424389 | Y30: -0.46589995 | Z30: -0.24567298 | AA30: -1.2995753 | AB30: -0.44182282 | AC30: -0.97185842 | AD30: -0.67965849 | AE30: -1.4949461 | AF30: -0.55353374 | AG30: -0.39919775 | AH30: -0.98081229 | AI30: 0.26103186 | AJ30: 0.28892519 | AK30: 0.27422448 | AL30: 0.24517065 | AM30: -1.1573543 | AN30: -0.89337572 | AO30: -0.76058962 | AP30: -0.90126491 | AQ30: -0.88590949 | AR30: 0.33454724 | AS30: 0.6097163 | AT30: 0.18505261 | AU30: 0.40030446 | AV30: 0.35122631 | AW30: -0.15852011 | AX30: -0.9212562 | AY30: -0.36261834 | AZ30: -0.84785038 | BA30: -0.56361712 | BB30: 0.36967546 | BC30: -1.6889439 | BD30: -0.86040255 | BE30: -1.5553513 | BF30: -1.1873416 | BG30: 0.11892737 | BH30: -0.47964249 | BI30: 0.25921784 | BJ30: -0.62593312 | BK30: -0.22615933 | BL30: 0.059215198 | BM30: -1.6829475 | BN30: -0.81711586 | BO30: -1.4435256 | BP30: -1.3208875 | BQ30: 0.29287199 | BR30: 0.11674188 | BS30: 0.038949547 | BT30: 0.15265966 | BU30: 0.21189432 | BV30: -0.57483161 | BW30: -0.64832935 | BX30: -0.4062034 | BY30: -0.535278 | BZ30: -0.87149955 | CA30: -0.0089637387 | CB30: 0.62215254 | CC30: 0.19707084 | CD30: 0.46702087 | CE30: 0.19957407 | CG30: -1
A31: 41000 | B31: 0 | C31: 1.2015209 | D31: -0.14917302 | E31: -0.21462013 | F31: -0.41755684 | G31: -0.059926835 | H31: -0.20224444 | I31: -0.86873289 | J31: -0.3422172 | K31: -0.73762193 | L31: -0.5453561 | M31: -0.93908868 | N31: -0.66099882 | O31: -0.43147425 | P31: -0.88428325 | Q31: -0.20253676 | R31: -0.57279302 | S31: -0.39827748 | T31: -0.73690003 | U31: -3.7614375 | V31: -0.88622221 | W31: -0.8307396 | X31: -0.96431876 | Y31: -0.81802152 | Z31: -0.59773952 | AA31: -1.5779598 | AB31: -0.74640506 | AC31: -1.278471 | AD31: -0.97613781 | AE31: -1.269544 | AF31: -0.64100343 | AG31: -0.42570216 | AH31: -0.89057104 | AI31: 0.38993795 | AJ31: 0.41439552 | AK31: 0.35023829 | AL31: 0.34706879 | AM31: -0.85782226 | AN31: -0.25842878 | AO31: -0.54074184 | AP31: -0.46467506 | AQ31: -0.55112618 | AR31: 0.2067961 | AS31: 0.16834427 | AT31: 0.097716989 | AU31: 0.14183812 | AV31: 0.13005226 | AW31: -0.64727816 | AX31: -1.4789082 | AY31: -0.69609259 | AZ31: -1.2311019 | BA31: -0.92276684 | BB31: 0.2954509 | BC31: -1.8354388 | BD31: -1.1073188 | BE31: -1.4973273 | BF31: -1.2186917 | BG31: -0.042356606 | BH31: -1.2711957 | BI31: -0.0036688454 | BJ31: -0.87279713 | BK31: -0.47771514 | BL31: -0.1994873 | BM31: -1.6806022 | BN31: -1.122509 | BO31: -1.6883889 | BP31: -1.5903877 | BQ31: 0.22858859 | BR31: 0.066649203 | BS31: 0.054721505 | BT31: 0.04482551 | BU31: 0.079174672 | BV31: -0.57538001 | BW31: -0.67775113 | BX31: -0.18149718 | BY31: -0.46871526 | BZ31: -0.7329824 | CA31: -0.039420628 | CB31: 0.53449705 | CC31: 0.20407252 | CD31: 0.38585429 | CE31: 0.20098222 | CG31: -1
A32: 41091 | B32: 0 | C32: 0.72656084 | D32: -0.84925996 | E32: -0.58444629 | F32: -0.91679642 | G32: -0.59700816 | H32: -0.34456012 | I32: -1.0148834 | J32: -0.48089865 | K32: -0.86657856 | L32: -0.67686427 | M32: -0.33665296 | N32: -0.37629673 | O32: -0.26895677 | P32: -0.68435857 | Q32: -0.063176604 | R32: -0.16953357 | S32: -0.1184382 | T32: -0.39568001 | U32: -3.9776708 | V32: -1.1363982 | W32: -0.91958252 | X32: -1.0780955 | Y32: -0.99601145 | Z32: -0.69105825 | AA32: -1.4200975 | AB32: -0.89940223 | AC32: -1.2302924 | AD32: -0.99853264 | AE32: -0.73570076 | AF32: -0.72237126 | AG32: -0.39801816 | AH32: -0.85210623 | AI32: 0.10688913 | AJ32: 0.36630016 | AK32: 0.32763567 | AL32: 0.36787102 | AM32: -0.75921684 | AN32: -0.011157582 | AO32: -0.61998432 | AP32: -0.26609092 | AQ32: -0.38934624 | AR32: 0.10593034 | AS32: 0.093593041 | AT32: 0.050450653 | AU32: -0.052489239 | AV32: -0.038558374 | AW32: -0.78767008 | AX32: -1.4721603 | AY32: -0.84888764 | AZ32: -1.2205677 | BA32: -0.97825183 | BB32: 0.23646955 | BC32: -1.5293214 | BD32: -1.1914195 | BE32: -1.3662785 | BF32: -1.2146886 | BG32: -0.00420305 | BH32: -1.8515514 | BI32: -0.21033278 | BJ32: -0.82511037 | BK32: -0.46619866 | BL32: -0.041454665 | BM32: -1.0740893 | BN32: -1.1509419 | BO32: -1.2426744 | BP32: -1.2216962 | BQ32: 0.12605178 | BR32: -0.057691208 | BS32: -0.030870061 | BT32: -0.12565819 | BU32: -0.084836074 | BV32: -0.061270947 | BW32: 0.12990223 | BX32: 0.21970405 | BY32: 0.24748481 | BZ32: 0.071309545 | CA32: -0.061590967 | CB32: 0.44495589 | CC32: 0.21303038 | CD32: 0.31424163 | CE32: 0.20438063 | CG32: -1
A33: 41183 | B33: 0 | C33: 0.62154982 | D33: -1.0149799 | E33: -0.8525795 | F33: -0.91674278 | G33: -0.72023173 | H33: -0.35734236 | I33: -1.0193885 | J33: -0.56685644 | K33: -0.78650771 | L33: -0.64156946 | M33: -0.20518618 | N33: -0.68254329 | O33: -0.45054594 | P33: -0.53376596 | Q33: -0.02043949 | R33: -0.1185089 | S33: 0.046156064 | T33: -0.13802791 | U33: -4.0700994 | V33: -1.1524024 | W33: -0.9125672 | X33: -1.0087632 | Y33: -1.0045074 | Z33: -0.63486659 | AA33: -0.82369467 | AB33: -0.99721718 | AC33: -0.98183805 | AD33: -0.87331782 | AE33: 0.0030496117 | AF33: -0.77437343 | AG33: -0.353193 | AH33: -0.51938316 | AI33: 0.60750837 | AJ33: 0.61192059 | AK33: 0.73990816 | AL33: 0.76261057 | AM33: -0.32783998 | AN33: 0.55627351 | AO33: -0.3736103 | AP33: 0.27285246 | AQ33: 0.080088741 | AR33: -0.019278941 | AS33: -0.64654703 | AT33: -0.019557884 | AU33: -0.27944976 | AV33: -0.21992282 | AW33: -0.73660756 | AX33: -1.1379949 | AY33: -0.90599236 | AZ33: -0.99982752 | BA33: -0.8699828 | BB33: 0.24132954 | BC33: -0.92806966 | BD33: -1.1469813 | BE33: -1.1198837 | BF33: -1.1024173 | BG33: 0.10284042 | BH33: -0.79479893 | BI33: -0.24404905 | BJ33: -0.65415335 | BK33: -0.36371116 | BL33: 0.053456146 | BM33: -0.61422458 | BN33: -1.2070379 | BO33: -0.88792067 | BP33: -0.96667885 | BQ33: -0.043908107 | BR33: -0.38219299 | BS33: -0.22920675 | BT33: -0.38329456 | BU33: -0.3059792 | BV33: -0.085159137 | BW33: 0.48861127 | BX33: -0.17490961 | BY33: 0.17920575 | BZ33: 0.12373921 | CA33: -0.23922569 | CB33: -0.06182485 | CC33: 0.1163819 | CD33: 0.034385207 | CE33: 0.016381889 | CG33: -1
... A79: 45383 | B79: 0 | C79: 1.2516697 | D79: -0.24727787 | E79: 0.040808041 | F79: -0.067070489 | G79: 0.026898756 | H79: -0.018206041 | I79: 0.090289394 | J79: -0.055065303 | K79: 0.047323647 | L79: 0.0071092606 | M79: 0.1508823 | N79: -0.046868106 | O79: -0.089053983 | P79: 0.034850974 | Q79: -0.28986912 | R79: 0.014813612 | S79: -0.12656631 | T79: 0.079812057 | U79: -3.0899598 | V79: -0.085089085 | W79: -0.18781575 | X79: -0.13527118 | Y79: -0.1827528 | Z79: -0.066154995 | AA79: 0.19945112 | AB79: 0.11590313 | AC79: 0.17048616 | AD79: 0.090205429 | AE79: 0.350118 | AF79: 0.21630466 | AG79: -0.098434026 | AH79: -0.093127891 | AI79: 0.35525167 | AJ79: 0.11992097 | AK79: 0.29043333 | AL79: 0.18010977 | AM79: -0.3392319 | AN79: -0.055199435 | AO79: -0.46502381 | AP79: -0.21745209 | AQ79: -0.22780112 | AR79: 0.032196441 | AS79: -0.011318285 | AT79: 0.08643742 | AU79: -0.037864063 | AV79: -0.0026579626 | AW79: 0.016775942 | AX79: 0.15272173 | AY79: 0.031908265 | AZ79: 0.13730198 | BA79: 0.072392825 | BB79: -0.083991978 | BC79: -0.039149799 | BD79: -0.34486315 | BE79: -0.13617571 | BF79: -0.23018728 | BG79: -0.52641235 | BH79: 0.029943402 | BI79: -0.34729825 | BJ79: -0.053406066 | BK79: -0.25666198 | BL79: -0.16433618 | BM79: 0.18865826 | BN79: 0.42249079 | BO79: 0.35094455 | BP79: 0.36648234 | BQ79: 0.036407847 | BR79: 0.28625205 | BS79: -0.036497743 | BT79: 0.082829642 | BU79: 0.020551003 | BV79: -0.047726497 | BW79: -0.12570969 | BX79: 0.23338521 | BY79: 0.008343425 | BZ79: 0.019278989 | CA79: 0.09181804 | CB79: 0.82502781 | CC79: 0.27926614 | CD79: 0.59734889 | CE79: 0.36207818 | CG79: -1
A80: 45474 | B80: 0 | C80: 1.3698376 | D80: -0.035338257 | E80: 0.079224468 | F80: 0.059726809 | G80: 0.11665438 | H80: -0.091815043 | I80: -0.092519284 | J80: 0.040365979 | K80: -0.044202267 | L80: -0.062278239 | M80: -0.040477664 | N80: 0.12912572 | O80: -0.0744766 | P80: -0.14170588 | Q80: -0.26013896 | R80: -0.19422292 | S80: -0.28709652 | T80: -0.10065709 | U80: -3.083667 | V80: -0.058966323 | W80: -0.13066601 | X80: -0.087657953 | Y80: -0.1384756 | Z80: 0.0011684057 | AA80: 0.20340778 | AB80: 0.2085201 | AC80: 0.22265522 | AD80: 0.16287682 | AE80: 0.37853674 | AF80: 0.37230356 | AG80: -0.010535656 | AH80: -0.26446479 | AI80: 0.088671243 | AJ80: 0.057277677 | AK80: 0.019860836 | AL80: -0.034096108 | AM80: -0.49574785 | AN80: -0.12279622 | AO80: -0.33131647 | AP80: -0.28263428 | AQ80: -0.33726907 | AR80: 0.013224941 | AS80: -0.12424362 | AT80: -0.02854039 | AU80: -0.0881192 | AV80: -0.024204238 | AW80: -0.042586129 | AX80: 0.022152974 | AY80: 0.12073303 | AZ80: 0.075277614 | BA80: 0.034862372 | BB80: -0.094816624 | BC80: -0.019556003 | BD80: -0.28467695 | BE80: -0.083723653 | BF80: -0.20570406 | BG80: -0.5692787 | BH80: -0.055611363 | BI80: -0.018578023 | BJ80: -0.041689484 | BK80: -0.25678754 | BL80: -0.049106929 | BM80: 0.16612545 | BN80: 0.67637627 | BO80: 0.44931994 | BP80: 0.49809782 | BQ80: -0.012163531 | BR80: 0.12092307 | BS80: -0.10552464 | BT80: 0.014881447 | BU80: -0.023855356 | CA80: 0.084715969 | CB80: 0.52505475 | CC80: 0.38470911 | CD80: 0.53019892 | CE80: 0.37682028 | CG80: -1
A81: 45566 | B81: 0 | C81: 1.4854585 | D81: 0.20645152 | E81: 0.19791816 | F81: 0.17571001 | G81: 0.20020309 | H81: -0.081967673 | I81: -0.13931371 | J81: 0.086625268 | K81: -0.038676672 | L81: -0.039145147 | M81: -0.10980667 | N81: 0.15209161 | O81: 0.0042774568 | P81: -0.154688 | Q81: -0.13750202 | R81: -0.16459569 | S81: -0.26445393 | T81: -0.1438495 | U81: -3.0605101 | V81: -0.0056468878 | W81: -0.083517357 | X81: -0.029574673 | Y81: -0.083817702 | Z81: 0.092062279 | AA81: 0.23756112 | AB81: 0.2557315 | AC81: 0.28238455 | AD81: 0.24577871 | AE81: 0.41822395 | AF81: 0.42191694 | AG81: 0.079719513 | AH81: -0.51596975 | AI81: -0.58099016 | AJ81: -0.059859919 | AK81: -0.35488433 | AL81: -0.34053761 | AM81: -0.49835941 | AN81: 0.059566927 | AO81: -0.47182529 | AP81: -0.22258958 | AQ81: -0.30622286 | AR81: 0.058395628 | AS81: 0.00042079568 | AT81: -0.023648178 | AU81: -0.0041584914 | AV81: 0.038256997 | AW81: 0.0078708357 | AX81: -0.019692553 | AY81: 0.21204413 | AZ81: 0.097868679 | BA81: 0.078213993 | BB81: -0.088193327 | BC81: 0.012047402 | BD81: -0.053524251 | BE81: -0.016424415 | BF81: -0.15157773 | BG81: -0.55015073 | BH81: -0.095422485 | BI81: 0.056109286 | BJ81: -0.014672085 | BK81: -0.18521377 | BL81: -0.019791824 | BM81: 0.12711217 | BN81: 0.61009148 | BO81: 0.37046028 | BP81: 0.49183102 | BQ81: -0.069054783 | BR81: -0.11403042 | BS81: -0.061760912 | BT81: -0.051823239 | BU81: -0.076903535 | CA81: 0.13174951 | CB81: 0.25136743 | CC81: 0.5441217 | CD81: 0.51312465 | CE81: 0.43517782 | CG81: -1
A82: 45658 | B82: 0 | C82: 1.2437162 | D82: -0.091192301 | E82: -0.050896977 | F82: -0.14155605 | G82: -0.060755728 | H82: -0.036496419 | I82: -0.083504152 | J82: 0.042313743 | K82: 0.0071513194 | L82: 0.012448825 | M82: 0.038542183 | N82: 0.14768745 | O82: -0.015483984 | P82: 0.23477565 | Q82: 0.10962999 | R82: -0.072422105 | S82: 0.1129227 | T82: 0.15549267 | U82: -3.0042043 | V82: 0.081934762 | W82: -0.011181655 | X82: 0.062711919 | Y82: -0.0038356289 | Z82: 0.16564732 | AA82: 0.27830843 | AB82: 0.28993741 | AC82: 0.31285986 | AD82: 0.29942037 | AE82: 0.42876197 | AF82: 0.46253459 | AG82: 0.18892315 | AH82: -0.41323611 | AI82: -0.28698716 | AJ82: 0.0026959771 | AK82: -0.19492373 | AL82: -0.16215416 | AM82: -0.47962907 | AN82: 0.15357363 | AO82: -0.50171313 | AP82: -0.11512908 | AQ82: -0.26370455 | AR82: -0.031297702 | AS82: -0.18579588 | AT82: -0.13284938 | AU82: -0.15470156 | AV82: -0.10269667 | AW82: 0.085076575 | AX82: 0.051321107 | AY82: 0.17341511 | AZ82: 0.12687155 | BA82: 0.13045699 | BB82: -0.076218267 | BC82: 0.037342293 | BD82: -0.0036333239 | BE82: 0.012780897 | BF82: -0.10293936 | BG82: -0.52219592 | BH82: -0.040984513 | BI82: 0.054111005 | BJ82: 0.0093430988 | BK82: -0.095712581 | BL82: -0.0083304003 | BM82: 0.16959175 | BN82: 0.51652129 | BO82: 0.27650874 | BP82: 0.4447172 | BQ82: -0.052589117 | BR82: -0.13841903 | BS82: 0.048533828 | BT82: -0.013575425 | BU82: -0.044930411 | CA82: 0.21315308 | CB82: 0.23817102 | CC82: 0.70396903 | CD82: 0.50873064 | CE82: 0.50783117 | CG82: -1
A83: 45748 | B83: 0 | C83: 1.234891 | D83: -0.017014688 | E83: -0.18123651 | F83: -0.14118555 | G83: -0.081962661 | H83: -0.035868959 | I83: -0.022925312 | J83: 0.044473741 | K83: -0.00058802476 | L83: 0.020074645 | M83: 0.028145489 | N83: 0.10423034 | O83: -0.020743359 | P83: 0.75925337 | Q83: 0.51841978 | R83: 0.2024527 | S83: 0.59480362 | T83: 0.55887219 | U83: -2.945798 | V83: 0.1897073 | W83: 0.063200391 | X83: 0.14267368 | Y83: 0.070605318 | Z83: 0.17950231 | AA83: 0.26412694 | AB83: 0.2958113 | AC83: 0.2688611 | AD83: 0.28559342 | AE83: 0.31174618 | AF83: 0.42085302 | AG83: 0.31209989 | AH83: -0.27726572 | AI83: -0.224256 | AJ83: 0.10301562 | AK83: 0.0013163963 | AL83: 0.033310196 | AM83: -0.55134805 | AN83: -0.1667245 | AO83: -0.18265161 | AP83: -0.090463905 | AQ83: -0.29780377 | AR83: -0.074691492 | AS83: -0.17525528 | AT83: -0.12230718 | AU83: -0.20308675 | AV83: -0.16414554 | AW83: 0.072072402 | AX83: 0.048267096 | AY83: 0.13211117 | AZ83: 0.079371185 | BA83: 0.11779688 | BB83: -0.10104109 | BC83: -0.023941052 | BD83: -0.043206067 | BE83: -0.024782583 | BF83: -0.097489761 | BG83: -0.53374547 | BH83: -0.0072860152 | BI83: 0.018900983 | BJ83: -0.014939718 | BK83: -0.03693231 | BL83: -0.014877118 | BM83: 0.18021255 | BN83: 0.31898684 | BO83: 0.17221268 | BP83: 0.37779369 | BQ83: -0.032123692 | BR83: -0.10128896 | BS83: 0.118392 | BT83: 0.0082503056 | BU83: -0.015768725 | CA83: 0.22647914 | CB83: 0.16228855 | CC83: 0.657756 | CD83: 0.38091916 | CE83: 0.48784989 | CG83: -1
A84: 45839 | B84: 0 | C84: 1.1832305 | D84: -0.18923146 | E84: -0.15399688 | F84: -0.16301637 | G84: -0.13544054 | H84: -0.055473729 | I84: 0.047168649 | J84: -0.029940473 | K84: -0.037005586 | L84: 0.0057550105 | M84: 0.038267293 | N84: -0.0012868827 | O84: 0.10303375 | P84: 0.8475318 | Q84: 0.70794959 | R84: 0.39667562 | S84: 0.63805679 | T84: 0.58140736 | U84: -2.949016 | V84: 0.17719165 | W84: 0.071420517 | X84: 0.12518911 | Y84: 0.075359681 | Z84: 0.16957423 | AA84: 0.18106734 | AB84: 0.24533535 | AC84: 0.19680199 | AD84: 0.24438008 | AE84: 0.17899923 | AF84: 0.35451488 | AG84: 0.36600014 | AH84: -0.22426115 | AI84: 0.048962823 | AJ84: 0.10823609 | AK84: 0.058558907 | AL84: 0.10790437 | AM84: -0.37991052 | AN84: 0.0910488 | AO84: -0.026129299 | AP84: 0.11167931 | AQ84: -0.067763654 | AR84: -0.1126625 | AS84: -0.20640719 | AT84: -0.21675615 | AU84: -0.2442052 | AV84: -0.21441812 | AW84: -0.0030206822 | AX84: 0.034535831 | AY84: 0.037261892 | AZ84: -0.017785318 | BA84: 0.052932936 | BB84: -0.1597564 | BC84: -0.09119106 | BD84: -0.075842137 | BE84: -0.10669413 | BF84: -0.13297932 | BG84: -0.56424194 | BH84: 0.0050043986 | BI84: -0.042216757 | BJ84: -0.056023087 | BK84: -0.030943428 | BL84: -0.089712593 | BM84: -0.0489609 | BN84: 0.10131989 | BO84: -3.4683664e-05 | BP84: 0.20739881 | BQ84: -0.098748806 | BR84: -0.1279722 | BS84: -0.0045120406 | BT84: -0.11952374 | BU84: -0.08726735 | CA84: 0.2639311 | CB84: 0.21598341 | CC84: 0.49368401 | CD84: 0.29468861 | CE84: 0.48466284 | CG84: -1
A85: 45931 | B85: 0 | C85: 1.2278093 | D85: -0.2612727 | E85: -0.037593188 | F85: -0.080346794 | G85: -0.086342778 | H85: -0.045832718 | I85: 0.046900807 | J85: -0.061010966 | K85: -0.017453581 | L85: 0.008766213 | M85: -0.050794018 | N85: -0.093502042 | O85: 0.083376471 | P85: 0.75925337 | Q85: 0.65406367 | R85: 0.45757603 | S85: 0.48913816 | T85: 0.45539821 | U85: -2.9672752 | V85: 0.12269087 | W85: 0.070706863 | X85: 0.08599628 | Y85: 0.058522404 | Z85: 0.16156715 | AA85: 0.074730562 | AB85: 0.19927477 | AC85: 0.13729492 | AD85: 0.20048799 | AE85: 0.070634057 | AF85: 0.3108453 | AG85: 0.35147546 | AH85: -0.072548988 | AI85: 0.54002899 | AJ85: -0.032212058 | AK85: 0.25764547 | AL85: 0.29257449 | AM85: -0.23620169 | AN85: 0.20605746 | AO85: 0.21861869 | AP85: 0.2571361 | AQ85: 0.095502892 | AR85: -0.2068223 | AS85: -0.43485584 | AT85: -0.28479128 | AU85: -0.36359618 | AV85: -0.32891543 | AW85: -0.00057528165 | AX85: -0.0073724349 | AY85: -0.017789979 | AZ85: -0.02309107 | BA85: 0.038790848 | BB85: -0.17640113 | BC85: -0.12386495 | BD85: -0.076575232 | BE85: -0.117163 | BF85: -0.115583 | BG85: -0.58451738 | BH85: -0.034145865 | BI85: -0.10808701 | BJ85: -0.073158534 | BK85: -0.05334939 | BL85: -0.10734598 | BM85: -0.10556976 | BN85: 0.018629139 | BO85: -0.045397798 | BP85: 0.11125355 | BQ85: -0.18464609 | BR85: -0.17084284 | BS85: -0.18234295 | BT85: -0.25200825 | BU85: -0.17324849 | CA85: 0.2798504 | CB85: 0.17848569 | CC85: 0.28637069 | CD85: 0.21378357 | CE85: 0.43961737
A86: 46023 | B86: 0 | C86: 1.3455226 | D86: 0.10323815 | E86: 0.008260344 | F86: 0.062053641 | G86: 0.025617075 | H86: -0.024668026 | I86: 0.01535248 | J86: -0.044993708 | K86: 0.024508176 | L86: 0.019669342 | M86: -0.084353002 | N86: -0.02667115 | O86: 0.067083339 | P86: 0.88907459 | Q86: 0.46825012 | R86: 0.51189261 | S86: 0.52455351 | T86: 0.5207502 | U86: -2.9865723 | V86: 0.023202642 | W86: 0.063514036 | X86: 0.045573151 | Y86: 0.03898714 | Z86: 0.14908614 | AA86: -0.017806322 | AB86: 0.1662276 | AC86: 0.082211497 | AD86: 0.15477361 | AE86: 0.014737731 | AF86: 0.28200376 | AG86: 0.35529673 | AH86: -0.13732844 | AI86: 0.33601977 | AJ86: 0.038559478 | AK86: 0.16999299 | AL86: 0.16825378 | AM86: -0.21319758 | AN86: 0.20941666 | AO86: 0.29875444 | AP86: 0.23832436 | AQ86: 0.15271971 | AR86: -0.25601845 | AS86: -0.36845597 | AT86: -0.36333646 | AU86: -0.39143194 | AV86: -0.36442323 | AW86: 0.018797091 | AX86: -0.057853941 | AY86: -0.0042940713 | AZ86: -0.0013466529 | BA86: 0.030544483 | BB86: -0.1836284 | BC86: -0.15082966 | BD86: -0.077718757 | BE86: -0.1129574 | BF86: -0.10941789 | BG86: -0.56507303 | BH86: -0.04260165 | BI86: -0.069728282 | BJ86: -0.029120635 | BK86: -0.033514433 | BL86: -0.11828269 | BM86: -0.13257665 | BN86: 0.032009392 | BO86: -0.065459507 | BP86: 0.037497899 | BQ86: -0.23639929 | BR86: -0.27166967 | BS86: -0.26249141 | BT86: -0.29496847 | BU86: -0.21870129 | CA86: 0.33591569 | CB86: 0.14794893 | CC86: 0.2572354 | CD86: 0.22902522 | CE86: 0.42486786
A87: 46113 | B87: 0 | C87: 1.4468395 | D87: 0.21492924 | E87: 0.13571832 | F87: 0.17626607 | G87: 0.12154533 | H87: -0.07205669 | I87: -0.046969307 | J87: -0.046144402 | K87: -0.032472181 | L87: -0.039153928 | M87: -0.14436661 | N87: -0.067664166 | O87: 0.013732713 | P87: 0.94619593 | Q87: 0.13378575 | R87: 0.57773089 | S87: 0.4853644 | T87: 0.53126661 | U87: -3.0129127 | V87: -0.088318537 | W87: 0.061249463 | X87: -0.0027078111 | Y87: 0.010569744 | Z87: 0.12017421 | AA87: -0.063788648 | AB87: 0.12783679 | AC87: 0.015374851 | AD87: 0.096630112 | AE87: 0.056428927 | AF87: 0.23410786 | AG87: 0.34387391 | AH87: 0.52092481 | AI87: 0.97209255 | AJ87: 0.58810225 | AK87: 1.1152039 | AL87: 0.98616384 | AM87: -0.59914463 | AN87: -0.037568387 | AO87: -0.1681406 | AP87: -0.19550473 | AQ87: -0.16462209 | AR87: -0.39774784 | AS87: -0.5296887 | AT87: -0.46212178 | AU87: -0.56367359 | AV87: -0.5228412 | AW87: -0.032011424 | AX87: -0.090852542 | AY87: -0.02799167 | AZ87: -0.047993669 | BA87: -0.023657257 | BB87: -0.19866622 | BC87: -0.13708915 | BD87: -0.11027719 | BE87: -0.12057115 | BF87: -0.11689142 | BG87: -0.52868736 | BH87: 0.0050256191 | BI87: -0.0018856415 | BJ87: 0.028661912 | BK87: 0.0075651205 | BL87: -0.10850355 | BM87: -0.1128915 | BN87: 0.058216938 | BO87: -0.056408359 | BP87: 0.0060545456 | BQ87: -0.36609705 | BR87: -0.49360942 | BS87: -0.38078521 | BT87: -0.44253969 | BU87: -0.36573455 | CA87: 0.45735852 | CB87: 0.27824724 | CC87: 0.29348755 | CD87: 0.33708313 | CE87: 0.46898925

Sheet Calculation
B1: Binary | C1: Corporate | U1: Households | AH1: Government | AW1: Banking | BL1: External | BV1: Недвижимость
B2: Binary | C2: Debt service ratio, % | H2: All Debt to GDP ratio, % | M2: Прирост реального кредита банков ЮЛ (дефлятор ВВП 2018=1) | P2: Складские запасы в промышленности к среднемесячному ОПП, % | U2: Debt_service ratio_annual | Z2: Кредит ФЛ к ВВП | AE2: Прирост реального кредита банков ФЛ (ИПЦ 2018=1) | AH2: Обслуживание внешнего долга органов государственного управления к ВВП, % | AM2: Отношение сальдо консолидированного бюджета к ВВП, % | AR2: Долг сектора государственного управления к ВВП, % (внешний + внутренний) | AW2: Требования банков к экономике к ВВП, % | BB2: Требования банков к депозитам, % | BG2: Леверидж (активы к собственному капиталу), раз | BL2: Счет текущих операций за год, в % к ВВП | BQ2: Валовый внешний долг к ВВП | BV2: Логарифм цен на коммерческую недвижимость, скорректированных на дефлятор ВВП, *100 | CA2: Логарифм цен на жилую недвижимость, скорректированных на ИПЦ
C3: 0.035811297 | D3: 0.057247908 | E3: 0.042113404 | F3: 0.054971735 | G3: 0.03329897 | H3: 0.053558176 | I3: 0.0451851 | J3: 0.038320244 | K3: 0.050943383 | L3: 0.041881008 | M3: 0.10266962 | N3: 0.082216498 | O3: 0.059519029 | P3: 0.049297866 | Q3: 0.063904642 | R3: 0.050349112 | S3: 0.068164951 | T3: 0.07054706 | U3: 0.052699348 | V3: 0.10740577 | W3: 0.06471644 | X3: 0.06541988 | Y3: 0.072187454 | Z3: 0.060679309 | AA3: 0.10426293 | AB3: 0.033765099 | AC3: 0.073157715 | AD3: 0.045690075 | AE3: 0.12417662 | AF3: 0.097555961 | AG3: 0.098283388 | AH3: 0.056522214 | AI3: 0.04996917 | AJ3: 0.05240669 | AK3: 0.037781567 | AL3: 0.026456363 | AM3: 0.076974331 | AN3: 0.094479667 | AO3: 0.11678787 | AP3: 0.10361281 | AQ3: 0.11212594 | AR3: 0.050917094 | AS3: 0.04008367 | AT3: 0.063556089 | AU3: 0.048698822 | AV3: 0.069627704 | AW3: 0.076951447 | AX3: 0.073055171 | AY3: 0.059887202 | AZ3: 0.062773332 | BA3: 0.053293887 | BB3: 0.065457433 | BC3: 0.094114268 | BD3: 0.045122312 | BE3: 0.070220194 | BF3: 0.05113862 | BG3: 0.061366344 | BH3: 0.071025861 | BI3: 0.06515439 | BJ3: 0.075760918 | BK3: 0.07467862 | BL3: 0.10214402 | BM3: 0.15955375 | BN3: 0.095977604 | BO3: 0.12819975 | BP3: 0.094311605 | BQ3: 0.088981461 | BR3: 0.10184758 | BS3: 0.075798103 | BT3: 0.077975613 | BU3: 0.07521052 | BV3: 0.10242341 | BW3: 0.12604441 | BX3: 0.083572654 | BY3: 0.120496 | BZ3: 0.10773425 | CA3: 0.063876965 | CB3: 0.10078366 | CC3: 0.098074101 | CD3: 0.13443918 | CE3: 0.062555373
A4: Date | B4: bnr | C4: dsr | D4: dsr1 | E4: dsr2 | F4: dsr_av2 | G4: dsr_av3 | H4: ggr | I4: ggr1 | J4: ggr2 | K4: ggr_av2 | L4: ggr_av3 | M4: rcgr_c1 | N4: rcgr_c2 | O4: rcgr_c3 | P4: invr | Q4: invr1 | R4: invr2 | S4: invr_av2 | T4: invr_av3 | U4: d_srv | V4: d_srv1 | W4: d_srv2 | X4: d_srv_av2 | Y4: d_srv_av3 | Z4: l_gdp | AA4: l_gdp1 | AB4: l_gdp2 | AC4: l_gdp_av2 | AD4: l_gdp_av3 | AE4: rcgr_h1 | AF4: rcgr_h2 | AG4: rcgr_h3 | AH4: exd_s | AI4: exd_s1 | AJ4: exd_s2 | AK4: exd_s_av2 | AL4: exd_s_av3 | AM4: bb_gdp | AN4: bb_gdp1 | AO4: bb_gdp2 | AP4: bb_gdp_av2 | AQ4: bb_gdp_av3 | AR4: ggd | AS4: ggd1 | AT4: ggd2 | AU4: ggd_av2 | AV4: ggd_av3 | AW4: crr | AX4: crr1 | AY4: crr2 | AZ4: crr_av2 | BA4: crr_av3 | BB4: d_as | BC4: d_as1 | BD4: d_as2 | BE4: d_as_av2 | BF4: d_as_av3 | BG4: lvr | BH4: lvr1 | BI4: lvr2 | BJ4: lvr_av2 | BK4: lvr_av3 | BL4: ca | BM4: ca1 | BN4: ca2 | BO4: ca_av2 | BP4: ca_av3 | BQ4: gd_gdp | BR4: gd_gdp1 | BS4: gd_gdp2 | BT4: gd_gdp_av2 | BU4: gd_gdp_av3 | BV4: cest | BW4: cest1 | BX4: cest2 | BY4: cest_av2 | BZ4: cest_av3 | CA4: pest | CB4: pest1 | CC4: pest2 | CD4: pest_av2 | CE4: pest_av3
A5: 38718 | B5: 0 | C5: -0.035811297 | D5: -0.057247908 | E5: -0.042113404 | F5: -0.054971735 | G5: -0.03329897 | H5: -0.014923936 | I5: -0.0096668727 | J5: -0.038320244 | K5: -0.050943383 | L5: -0.041881008 | M5: -0.01402574 | N5: -0.02341169 | O5: -0.013579255 | P5: -0.024009556 | Q5: -0.0068871217 | R5: -0.050349112 | S5: -0.068164951 | T5: -0.07054706 | U5: -0.052699348 | V5: -0.10740577 | W5: -0.06471644 | X5: -0.06541988 | Y5: -0.072187454 | Z5: -0.010301817 | AA5: -0.011645429 | AB5: -0.033765099 | AC5: -0.073157715 | AD5: -0.045690075 | AE5: 0.003828295 | AF5: 0.010565495 | AG5: 0.016333513 | AH5: -0.036360718 | AI5: -0.016990675 | AJ5: -0.05240669 | AK5: -0.037781567 | AL5: -0.026456363 | AM5: 0.0032334201 | AN5: 0.045541081 | AO5: -0.11678787 | AP5: -0.10361281 | AQ5: -0.11212594 | AR5: -0.00016658315 | AS5: -0.0049143585 | AT5: -0.063556089 | AU5: -0.048698822 | AV5: -0.069627704 | AW5: -0.025984547 | AX5: -0.018540648 | AY5: -0.059887202 | AZ5: -0.062773332 | BA5: -0.053293887 | BB5: -0.0092459327 | BC5: -0.011875363 | BD5: -0.045122312 | BE5: -0.070220194 | BF5: -0.05113862 | BG5: -0.056495936 | BH5: -0.071025861 | BI5: -0.06515439 | BJ5: -0.075760918 | BK5: -0.07467862 | BL5: -0.018959419 | BM5: -0.038274145 | BN5: -0.095977604 | BO5: -0.12819975 | BP5: -0.094311605 | BQ5: -0.014940845 | BR5: -0.021953242 | BS5: -0.075798103 | BT5: -0.077975613 | BU5: -0.07521052 | BV5: -0.086229496 | BW5: -0.12604441 | BX5: -0.083572654 | BY5: -0.120496 | BZ5: -0.10773425 | CA5: -0.063876965 | CB5: -0.10078366 | CC5: -0.098074101 | CD5: -0.13443918 | CE5: -0.062555373
A6: 38808 | B6: 0 | C6: -0.035811297 | D6: -0.057247908 | E6: -0.042113404 | F6: -0.054971735 | G6: -0.03329897 | H6: -0.01494199 | I6: -0.0064267336 | J6: -0.038320244 | K6: -0.050943383 | L6: -0.041881008 | M6: -0.009670389 | N6: -0.03176488 | O6: -0.019269546 | P6: -0.016713659 | Q6: -0.0097369652 | R6: -0.050349112 | S6: -0.068164951 | T6: -0.07054706 | U6: -0.052699348 | V6: -0.10740577 | W6: -0.06471644 | X6: -0.06541988 | Y6: -0.072187454 | Z6: -0.010646294 | AA6: -0.0070856575 | AB6: -0.033765099 | AC6: -0.073157715 | AD6: -0.045690075 | AE6: 0.0078921766 | AF6: 0.0097986263 | AG6: 0.018087701 | AH6: -0.038307964 | AI6: -0.012078288 | AJ6: -0.05240669 | AK6: -0.037781567 | AL6: -0.026456363 | AM6: 0.0024988655 | AN6: 0.05410686 | AO6: -0.11678787 | AP6: -0.10361281 | AQ6: -0.11212594 | AR6: -0.0023364865 | AS6: -0.0047272896 | AT6: -0.063556089 | AU6: -0.048698822 | AV6: -0.069627704 | AW6: -0.025124207 | AX6: -0.010605436 | AY6: -0.059887202 | AZ6: -0.062773332 | BA6: -0.053293887 | BB6: -0.0043689353 | BC6: 0.0027619329 | BD6: -0.045122312 | BE6: -0.070220194 | BF6: -0.05113862 | BG6: -0.050208301 | BH6: 0.013621741 | BI6: -0.06515439 | BJ6: -0.075760918 | BK6: -0.07467862 | BL6: -0.0045098047 | BM6: 0.019413652 | BN6: -0.095977604 | BO6: -0.12819975 | BP6: -0.094311605 | BQ6: -0.017660473 | BR6: -0.016246482 | BS6: -0.075798103 | BT6: -0.077975613 | BU6: -0.07521052 | BV6: -0.062163193 | BW6: -0.12604441 | BX6: -0.083572654 | BY6: -0.120496 | BZ6: -0.10773425 | CA6: -0.042366958 | CB6: -0.10078366 | CC6: -0.098074101 | CD6: -0.13443918 | CE6: -0.062555373
A7: 38899 | B7: 0 | C7: -0.035811297 | D7: -0.057247908 | E7: -0.042113404 | F7: -0.054971735 | G7: -0.03329897 | H7: -0.012539784 | I7: -0.0014245769 | J7: -0.038320244 | K7: -0.050943383 | L7: -0.041881008 | M7: 0.013766351 | N7: -0.024807023 | O7: -0.012360584 | P7: -0.026569519 | Q7: -0.0091432478 | R7: -0.050349112 | S7: -0.068164951 | T7: -0.07054706 | U7: -0.052699348 | V7: -0.10740577 | W7: -0.06471644 | X7: -0.06541988 | Y7: -0.072187454 | Z7: -0.0077978741 | AA7: 0.0012300163 | AB7: -0.033765099 | AC7: -0.073157715 | AD7: -0.045690075 | AE7: 0.016942119 | AF7: 0.0090775105 | AG7: 0.018995145 | AH7: -0.040012765 | AI7: -0.0053271355 | AJ7: -0.05240669 | AK7: -0.037781567 | AL7: -0.026456363 | AM7: -0.014067636 | AN7: 0.032212347 | AO7: -0.11678787 | AP7: -0.10361281 | AQ7: -0.11212594 | AR7: -0.0034632876 | AS7: -0.0038994876 | AT7: -0.063556089 | AU7: -0.048698822 | AV7: -0.069627704 | AW7: -0.021919765 | AX7: -0.0019743474 | AY7: -0.059887202 | AZ7: -0.062773332 | BA7: -0.053293887 | BB7: -0.00099967994 | BC7: 0.011648034 | BD7: -0.045122312 | BE7: -0.070220194 | BF7: -0.05113862 | BG7: -0.032973911 | BH7: 0.023047123 | BI7: -0.06515439 | BJ7: -0.075760918 | BK7: -0.07467862 | BL7: -0.0020925739 | BM7: 0.027499054 | BN7: -0.095977604 | BO7: -0.12819975 | BP7: -0.094311605 | BQ7: -0.017001426 | BR7: -0.010533149 | BS7: -0.075798103 | BT7: -0.077975613 | BU7: -0.07521052 | BV7: 0.088593875 | BW7: -0.12604441 | BX7: -0.083572654 | BY7: -0.120496 | BZ7: -0.10773425 | CA7: -0.041509888 | CB7: -0.10078366 | CC7: -0.098074101 | CD7: -0.13443918 | CE7: -0.062555373
A8: 38991 | B8: 0 | C8: -0.035219286 | D8: 0.0033056408 | E8: -0.042113404 | F8: -0.054971735 | G8: -0.03329897 | H8: -0.0082396061 | I8: 0.0057443039 | J8: -0.038320244 | K8: -0.050943383 | L8: -0.041881008 | M8: 0.045758361 | N8: -0.006994205 | O8: -0.0069304062 | P8: -0.026825516 | Q8: 0.002493613 | R8: -0.050349112 | S8: -0.068164951 | T8: -0.07054706 | U8: -0.052699348 | V8: -0.10740577 | W8: -0.06471644 | X8: -0.06541988 | Y8: -0.072187454 | Z8: -0.0042441611 | AA8: 0.0093860218 | AB8: -0.033765099 | AC8: -0.073157715 | AD8: -0.045690075 | AE8: 0.020454311 | AF8: 0.010550478 | AG8: 0.01766238 | AH8: -0.040608054 | AI8: -0.0057178808 | AJ8: -0.05240669 | AK8: -0.037781567 | AL8: -0.026456363 | AM8: -0.050552299 | AN8: -0.047103611 | AO8: -0.11678787 | AP8: -0.10361281 | AQ8: -0.11212594 | AR8: -0.002417799 | AS8: -0.0013845577 | AT8: -0.063556089 | AU8: -0.048698822 | AV8: -0.069627704 | AW8: -0.018974086 | AX8: 0.0052567926 | AY8: -0.059887202 | AZ8: -0.062773332 | BA8: -0.053293887 | BB8: 0.0019182965 | BC8: 0.024940151 | BD8: -0.045122312 | BE8: -0.070220194 | BF8: -0.05113862 | BG8: -0.030127133 | BH8: 0.024966043 | BI8: -0.06515439 | BJ8: -0.075760918 | BK8: -0.07467862 | BL8: 0.014750173 | BM8: 0.10071966 | BN8: -0.095977604 | BO8: -0.12819975 | BP8: -0.094311605 | BQ8: -0.015119246 | BR8: -0.0039203044 | BS8: -0.075798103 | BT8: -0.077975613 | BU8: -0.07521052 | BV8: 0.083790642 | BW8: 0.26387481 | BX8: -0.083572654 | BY8: -0.120496 | BZ8: -0.10773425 | CA8: -0.040648106 | CB8: -0.10078366 | CC8: -0.098074101 | CD8: -0.13443918 | CE8: -0.062555373
A9: 39083 | B9: 0 | C9: -0.030655533 | D9: 0.0096415847 | E9: -0.042113404 | F9: -0.054971735 | G9: -0.03329897 | H9: -0.0045488625 | I9: 0.011360919 | J9: 0.00094849194 | K9: 0.0089856118 | L9: -0.041881008 | M9: 0.062750501 | N9: 0.022716448 | O9: 0.0028789496 | P9: -0.014793687 | Q9: 0.0085495304 | R9: 0.0011602146 | S9: 0.0069256544 | T9: -0.07054706 | U9: -0.052699348 | V9: 0.049604624 | W9: -0.06471644 | X9: -0.06541988 | Y9: -0.072187454 | Z9: -0.0045167608 | AA9: 0.010687593 | AB9: -0.00019793437 | AC9: 0.0043310115 | AD9: -0.045690075 | AE9: 0.016848078 | AF9: 0.010328801 | AG9: 0.014397982 | AH9: -0.04350257 | AI9: -0.0076894426 | AJ9: -0.020355322 | AK9: -0.0090313725 | AL9: -0.026456363 | AM9: -0.076974331 | AN9: -0.082995108 | AO9: -0.038104585 | AP9: -0.075141875 | AQ9: -0.11212594 | AR9: -0.0039564304 | AS9: -0.0048917922 | AT9: -0.01019272 | AU9: -0.0054746981 | AV9: -0.069627704 | AW9: -0.0091385798 | AX9: 0.013959953 | AY9: -0.0024682095 | AZ9: 0.0075999194 | BA9: -0.053293887 | BB9: 0.016727652 | BC9: 0.052440865 | BD9: 0.013318983 | BE9: 0.035749385 | BF9: -0.05113862 | BG9: -0.034428766 | BH9: 0.025376621 | BI9: -0.06515439 | BJ9: -0.075760918 | BK9: -0.07467862 | BL9: 0.030971468 | BM9: 0.094042926 | BN9: 0.029010321 | BO9: 0.078256769 | BP9: -0.094311605 | BQ9: -0.01209702 | BR9: 0.0048108928 | BS9: -0.0081661102 | BT9: 0.00026257167 | BU9: -0.07521052 | BV9: 0.067555322 | BW9: 0.20163656 | BX9: -0.083572654 | BY9: -0.120496 | BZ9: -0.10773425 | CA9: -0.027400773 | CB9: -0.10078366 | CC9: -0.098074101 | CD9: -0.13443918 | CE9: -0.062555373
A10: 39173 | B10: 0 | C10: -0.014052381 | D10: 0.043369239 | E10: -0.042113404 | F10: -0.054971735 | G10: -0.03329897 | H10: -0.0035575759 | I10: 0.012466168 | J10: 0.0033814623 | K10: 0.010044892 | L10: -0.041881008 | M10: 0.064017475 | N10: 0.025337687 | O10: -0.00094522592 | P10: -0.010569747 | Q10: 0.0056996869 | R10: -0.002817664 | S10: 0.01187255 | T10: -0.07054706 | U10: -0.052699348 | V10: 0.053921907 | W10: -0.06471644 | X10: -0.06541988 | Y10: -0.072187454 | Z10: -0.0065810124 | AA10: 0.0075103976 | AB10: 8.7771437e-05 | AC10: 0.0016093214 | AD10: -0.045690075 | AE10: 0.012239894 | AF10: 0.010056897 | AG10: 0.012070209 | AH10: -0.046066906 | AI10: -0.0083538479 | AJ10: -0.016851731 | AK10: -0.008740252 | AL10: -0.026456363 | AM10: -0.076511805 | AN10: -0.07622613 | AO10: -0.022503471 | AP10: -0.060486675 | AQ10: -0.11212594 | AR10: -0.0076952112 | AS10: -0.0069168403 | AT10: -0.012103154 | AU10: -0.010093716 | AV10: -0.069627704 | AW10: -0.0099043226 | AX10: 0.012612447 | AY10: 0.001081435 | AZ10: 0.0075428617 | BA10: -0.053293887 | BB10: 0.024859376 | BC10: 0.059012184 | BD10: 0.020282466 | BE10: 0.045050086 | BF10: -0.05113862 | BG10: -0.025825689 | BH10: 0.028039313 | BI10: 0.031881005 | BJ10: 0.03128186 | BK10: -0.07467862 | BL10: 0.034994678 | BM10: 0.07440519 | BN10: 0.048803554 | BO10: 0.078872381 | BP10: -0.094311605 | BQ10: -0.0080691452 | BR10: 0.016225628 | BS10: -9.9342591e-06 | BT10: 0.0074686154 | BU10: -0.07521052 | BV10: 0.065711681 | BW10: 0.16766447 | BX10: -0.083572654 | BY10: -0.120496 | BZ10: -0.10773425 | CA10: 0.0027350715 | CB10: 0.085760566 | CC10: -0.098074101 | CD10: -0.13443918 | CE10: -0.062555373
A11: 39264 | B11: 0 | C11: 0.0021393823 | D11: 0.061611602 | E11: -0.042113404 | F11: -0.054971735 | G11: -0.03329897 | H11: -0.0045030032 | I11: 0.0088004401 | J11: 0.004129725 | K11: 0.0078745094 | L11: -0.041881008 | M11: 0.050880848 | N11: 0.030139803 | O11: -0.00053470214 | P11: -0.017737645 | Q11: 0.0081933 | R11: -0.00066297976 | S11: 0.0036804906 | T11: -0.07054706 | U11: -0.052699348 | V11: 0.055678559 | W11: -0.06471644 | X11: -0.06541988 | Y11: -0.072187454 | Z11: -0.0066604381 | AA11: 0.0021013543 | AB11: 0.00068841913 | AC11: 0.001462086 | AD11: -0.045690075 | AE11: -0.002771448 | AF11: 0.0070789026 | AG11: 0.005835264 | AH11: -0.048714693 | AI11: -0.009369135 | AJ11: -0.012120984 | AK11: -0.0090068688 | AL11: -0.026456363 | AM11: -0.075862207 | AN11: -0.05961677 | AO11: -0.027880425 | AP11: -0.05585956 | AQ11: -0.11212594 | AR11: -0.0098076394 | AS11: -0.0081890505 | AT11: -0.012565081 | AU11: -0.011724599 | AV11: -0.069627704 | AW11: -0.014399443 | AX11: 0.0062319568 | AY11: 0.0022941219 | AZ11: 0.0038821572 | BA11: -0.053293887 | BB11: 0.027415074 | BC11: 0.057369604 | BD11: 0.022660751 | BE11: 0.042950344 | BF11: -0.05113862 | BG11: -0.014986986 | BH11: 0.020684453 | BI11: 0.033465466 | BJ11: 0.040879603 | BK11: -0.07467862 | BL11: 0.040699374 | BM11: 0.080597005 | BN11: 0.056230409 | BO11: 0.077874782 | BP11: -0.094311605 | BQ11: -0.0086675278 | BR11: 0.014098438 | BS11: 0.0016983983 | BT11: 0.0066562922 | BU11: -0.07521052 | BV11: -0.054308566 | BW11: -0.12604441 | BX11: -0.083572654 | BY11: -0.120496 | BZ11: -0.10773425 | CA11: 0.030953941 | CB11: 0.13778846 | CC11: -0.098074101 | CD11: -0.13443918 | CE11: -0.062555373
A12: 39356 | B12: 0 | C12: 0.020383155 | D12: 0.090136059 | E12: 0.047137028 | F12: 0.085917113 | G12: -0.03329897 | H12: -0.0031854775 | I12: 0.0055343747 | J12: 0.0063149005 | K12: 0.0085058349 | L12: -0.041881008 | M12: 0.020092897 | N12: 0.03070116 | O12: 0.001169299 | P12: -0.031177454 | Q12: -0.0040372782 | R12: -0.0010773421 | S12: -0.012782779 | T12: -0.07054706 | U12: -0.052699348 | V12: 0.054618967 | W12: -0.06471644 | X12: -0.06541988 | Y12: -0.072187454 | Z12: -0.0058858814 | AA12: -0.0030329935 | AB12: 0.0013128369 | AC12: 0.0022096065 | AD12: -0.045690075 | AE12: -0.020169083 | AF12: 0.00014248444 | AG12: 0.00036036285 | AH12: -0.048565775 | AI12: -0.0085678677 | AJ12: -0.0117824 | AK12: -0.0072125313 | AL12: -0.026456363 | AM12: -0.028876143 | AN12: 0.020912233 | AO12: -0.02664631 | AP12: 0.01065695 | AQ12: -0.11212594 | AR12: -0.008485823 | AS12: -0.007832377 | AT12: -0.0095802764 | AU12: -0.0075968381 | AV12: -0.069627704 | AW12: -0.016537857 | AX12: 0.0020188594 | AY12: 0.0039203297 | AZ12: 0.0017605663 | BA12: -0.053293887 | BB12: 0.022050052 | BC12: 0.040646167 | BD12: 0.021534137 | BE12: 0.027000821 | BF12: -0.05113862 | BG12: -0.011653657 | BH12: 0.021243974 | BI12: 0.035362086 | BJ12: 0.03871947 | BK12: -0.07467862 | BL12: 0.044177128 | BM12: 0.055424552 | BN12: 0.08122454 | BO12: 0.070808009 | BP12: -0.094311605 | BQ12: -0.0030105307 | BR12: 0.020484287 | BS12: 0.0078905935 | BT12: 0.013997119 | BU12: -0.07521052 | BV12: -0.037379976 | BW12: -0.12604441 | BX12: 0.065800129 | BY12: -0.055841944 | BZ12: -0.10773425 | CA12: 0.052764744 | CB12: 0.17762258 | CC12: -0.098074101 | CD12: -0.13443918 | CE12: -0.062555373
A13: 39448 | B13: 0 | C13: 0.035822709 | D13: 0.10776661 | E13: 0.059227021 | F13: 0.10037791 | G13: -0.03329897 | H13: -0.0021339571 | I13: 0.0026443711 | J13: 0.0078415227 | K13: 0.0081925594 | L13: 0.0058952268 | M13: 0.0086593 | N13: 0.033292662 | O13: 0.013180081 | P13: -0.035913387 | Q13: -0.019592674 | R13: -0.0077071397 | S13: -0.018382666 | T13: -0.020031353 | U13: -0.052699348 | V13: 0.046784436 | W13: 0.035085462 | X13: 0.032706401 | Y13: -0.072187454 | Z13: -0.0079447025 | AA13: -0.0063329457 | AB13: 0.00089987663 | AC13: -0.001178034 | AD13: -0.00058751335 | AE13: -0.024752042 | AF13: -0.0039483942 | AG13: -0.001544318 | AH13: -0.051364294 | AI13: -0.0084645101 | AJ13: -0.013323231 | AK13: -0.0083151414 | AL13: -0.007847373 | AM13: -0.036071348 | AN13: 0.045075542 | AO13: -0.03857821 | AP13: 0.0056531682 | AQ13: 0.0041284381 | AR13: -0.0031921576 | AS13: 0.00098649453 | AT13: -0.0040592487 | AU13: 0.0026480656 | AV13: -0.00050551812 | AW13: -0.021439733 | AX13: -0.010193746 | AY13: 0.0020293399 | AZ13: -0.0028168563 | BA13: -0.0024192671 | BB13: 0.017213012 | BC13: 0.0009799467 | BD13: 0.017539802 | BE13: 0.012276588 | BF13: 0.013023885 | BG13: -0.0032646917 | BH13: 0.035837802 | BI13: 0.046844166 | BJ13: 0.043839125 | BK13: -0.07467862 | BL13: 0.036190334 | BM13: 0.0098295368 | BN13: 0.05403334 | BO13: 0.035725979 | BP13: 0.039327794 | BQ13: 0.0029350192 | BR13: 0.025429668 | BS13: 0.014405713 | BT13: 0.020423433 | BU13: 0.014435081 | BV13: -0.020597473 | BW13: -0.11558245 | BX13: 0.053926987 | BY13: -0.04520892 | BZ13: -0.10773425 | CA13: 0.059709775 | CB13: 0.16563889 | CC13: -0.098074101 | CD13: -0.13443918 | CE13: -0.062555373
A14: 39539 | B14: 0 | C14: 0.026759106 | D14: 0.066158725 | E14: 0.055251806 | F14: 0.068561944 | G14: -0.03329897 | H14: -0.0050985364 | I14: -0.0016873835 | J14: 0.0060350111 | K14: 0.0021344023 | L14: 0.0030079365 | M14: -0.018027382 | N14: 0.021441492 | O14: 0.0083419795 | P14: -0.036297381 | Q14: -0.023867439 | R14: -0.012679488 | S14: -0.017017322 | T14: -0.018507804 | U14: -0.052699348 | V14: 0.034553995 | W14: 0.032205085 | X14: 0.027219205 | Y14: -0.072187454 | Z14: -0.0084065519 | AA14: -0.0033725902 | AB14: 0.00085506722 | AC14: -0.0022077844 | AD14: -0.00068029725 | AE14: -0.015354568 | AF14: -0.0015559228 | AG14: 0.001810251 | AH14: -0.054327556 | AI14: -0.0088940226 | AJ14: -0.014225457 | AK14: -0.0093673087 | AL14: -0.0080872586 | AM14: -0.054827131 | AN14: 0.02092045 | AO14: -0.056266313 | AP14: -0.012566587 | AQ14: -0.021996328 | AR14: -0.00768782 | AS14: 9.5403194e-06 | AT14: -0.0071795932 | AU14: -0.0041707709 | AV14: -0.0080523868 | AW14: -0.018228357 | AX14: -0.0068979792 | AY14: 0.003079119 | AZ14: -0.00080007368 | BA14: 8.2713939e-05 | BB14: 0.026483419 | BC14: 0.0032789546 | BD14: 0.020452221 | BE14: 0.022144556 | BF14: 0.020666675 | BG14: 0.0096930567 | BH14: 0.040845551 | BI14: 0.052713949 | BJ14: 0.053427174 | BK14: 0.065555641 | BL14: 0.037785877 | BM14: 0.0052571169 | BN14: 0.041439477 | BO14: 0.025596581 | BP14: 0.037629376 | BQ14: -0.0036557468 | BR14: 0.0074661365 | BS14: 0.011286059 | BT14: 0.0084119485 | BU14: 0.0071044206 | BV14: -0.017965467 | BW14: -0.10971416 | BX14: 0.036315354 | BY14: -0.053957482 | BZ14: -0.10773425 | CA14: 0.049223768 | CB14: 0.088397285 | CC14: 0.11290567 | CD14: 0.13954933 | CE14: -0.062555373
A15: 39630 | B15: 0 | C15: 0.014994784 | D15: 0.020839647 | E15: 0.041592852 | F15: 0.0330702 | G15: -0.03329897 | H15: -0.010524414 | I15: -0.0065935691 | J15: 0.0012356209 | K15: -0.0067023458 | L15: -0.0020371794 | M15: -0.021902853 | N15: 0.013510115 | O15: 0.0098176035 | P15: -0.040905316 | Q15: -0.021492569 | R15: -0.0092817166 | S15: -0.019688646 | T15: -0.021117709 | U15: -0.052699348 | V15: 0.022083574 | W15: 0.028305291 | X15: 0.020159274 | Y15: -0.072187454 | Z15: -0.006294769 | AA15: 0.00067555491 | AB15: 0.00057384112 | AC15: 0.0002857261 | AD15: 0.00088590398 | AE15: 0.0073916608 | AF15: 0.0023080091 | AG15: 0.0081702155 | AH15: -0.056522214 | AI15: -0.010029052 | AJ15: -0.015998965 | AK15: -0.011011153 | AL15: -0.0089506763 | AM15: -0.07040307 | AN15: 0.0052667431 | AO15: -0.05529406 | AP15: -0.023636084 | AQ15: -0.042816881 | AR15: -0.013196699 | AS15: -0.0043744706 | AT15: -0.013058789 | AU15: -0.012186117 | AV15: -0.01719749 | AW15: -0.020108771 | AX15: -0.0047312181 | AY15: 0.00080864098 | AZ15: -0.0028924844 | BA15: -0.00065692784 | BB15: 0.037854316 | BC15: 0.021076909 | BD15: 0.02575656 | BE15: 0.034579724 | BF15: 0.029452729 | BG15: 0.018870242 | BH15: 0.038934853 | BI15: 0.045623507 | BJ15: 0.055996901 | BK15: 0.070187552 | BL15: 0.048285321 | BM15: 0.014287844 | BN15: 0.049358079 | BO15: 0.035562146 | BP15: 0.045577768 | BQ15: -0.01556564 | BR15: -0.011669522 | BS15: 0.001157064 | BT15: -0.010180466 | BU15: -0.0057539779 | BV15: 0.0028275402 | BW15: 0.074914598 | BX15: -0.070470478 | BY15: -0.029984823 | BZ15: -0.10773425 | CA15: 0.035507123 | CB15: 0.0086577809 | CC15: 0.094940374 | CD15: 0.069234107 | CE15: -0.062555373
A16: 39722 | B16: 0 | C16: 0.0036046926 | D16: -0.027199246 | E16: 0.031748719 | F16: 0.0019022679 | G16: 0.0130447 | H16: -0.010767057 | I16: -0.0083019859 | J16: -0.0015495777 | K16: -0.0073589167 | L16: -0.0023019872 | M16: 0.0054614334 | N16: 0.011913935 | O16: 0.016379236 | P16: -0.026569519 | Q16: 0.0042747652 | R16: 0.00016574494 | S16: 0.00025723859 | T16: -0.00080814321 | U16: -0.052699348 | V16: 0.026160387 | W16: 0.029403554 | X16: 0.023575665 | Y16: -0.072187454 | Z16: 2.1163046e-05 | AA16: 0.01091296 | AB16: 0.0016283748 | AC16: 0.0086273653 | AD16: 0.0051665289 | AE16: 0.028609459 | AF16: 0.0042163564 | AG16: 0.010948529 | AH16: -0.056522214 | AI16: -0.013351802 | AJ16: -0.018078598 | AK16: -0.011673811 | AL16: -0.0095677121 | AM16: -0.053837865 | AN16: -0.024082007 | AO16: -0.0032248317 | AP16: 0.0074356425 | AQ16: -0.017952604 | AR16: -0.013306771 | AS16: -0.0062226978 | AT16: -0.014609141 | AU16: -0.010353495 | AV16: -0.015366057 | AW16: -0.020068053 | AX16: -0.0029254099 | AY16: -0.00048847535 | AZ16: -0.0030341373 | BA16: -0.00060986958 | BB16: 0.045509488 | BC16: 0.04736478 | BD16: 0.028896877 | BE16: 0.03921071 | BF16: 0.033434707 | BG16: -0.0086094994 | BH16: 0.0035006945 | BI16: 0.018935788 | BJ16: 0.0043438619 | BK16: 0.021714586 | BL16: 0.059403152 | BM16: 0.028677635 | BN16: 0.043749054 | BO16: 0.044778469 | BP16: 0.05298958 | BQ16: -0.022859534 | BR16: -0.033578515 | BS16: -0.0062377048 | BT16: -0.02035199 | BU16: -0.012975371 | BV16: 0.030072609 | BW16: 0.088441156 | BX16: -0.044137778 | BY16: 0.029625164 | BZ16: 0.049707087 | CA16: 0.024160663 | CB16: -0.054390061 | CC16: 0.079891035 | CD16: 0.01063152 | CE16: -0.062555373
... A86: 46113 | B86: 0 | C86: 0.051813199 | D86: 0.012304249 | E86: 0.0057155603 | F86: 0.0096896519 | G86: 0.0040473342 | H86: -0.0038592249 | I86: -0.0021223128 | J86: -0.0017682647 | K86: -0.0016542428 | L86: -0.001639806 | M86: -0.014822065 | N86: -0.0055631108 | O86: 0.00081735772 | P86: 0.04664544 | Q86: 0.0085495304 | R86: 0.029088237 | S86: 0.03308484 | T86: 0.037479297 | U86: -0.052699348 | V86: -0.0094859207 | W86: 0.0039638472 | X86: -0.00017714468 | Y86: 0.00076300288 | Z86: 0.0072920883 | AA86: -0.0066507915 | AB86: 0.0043164219 | AC86: 0.001124789 | AD86: 0.0044150371 | AE86: 0.0070071537 | AF86: 0.022838617 | AG86: 0.033797093 | AH86: 0.029443823 | AI86: 0.048574658 | AJ86: 0.030820493 | AK86: 0.042134149 | AL86: 0.026090308 | AM86: -0.046118757 | AN86: -0.0035494487 | AO86: -0.019636782 | AP86: -0.020256794 | AQ86: -0.018458407 | AR86: -0.020252164 | AS86: -0.021231867 | AT86: -0.029370653 | AU86: -0.02745024 | AV86: -0.036404232 | AW86: -0.0024633254 | AX86: -0.006637248 | AY86: -0.0016763428 | AZ86: -0.0030127226 | BA86: -0.0012607872 | BB86: -0.013004181 | BC86: -0.012902045 | BD86: -0.0049759617 | BE86: -0.0084665295 | BF86: -0.0059776661 | BG86: -0.03244361 | BH86: 0.00035694892 | BI86: -0.00012285782 | BJ86: 0.0021714528 | BK86: 0.00056495275 | BL86: -0.011082988 | BM86: -0.018012261 | BN86: 0.0055875223 | BO86: -0.0072315376 | BP86: 0.00057101392 | BQ86: -0.03257585 | BR86: -0.050272924 | BS86: -0.028862796 | BT86: -0.034507304 | BU86: -0.027507086 | BV86: -0.10242341 | BW86: -0.12604441 | BX86: -0.083572654 | BY86: -0.120496 | BZ86: -0.10773425 | CA86: 0.029214674 | CB86: 0.028042774 | CC86: 0.028783528 | CD86: 0.045317178 | CE86: 0.029337797

Sheet Barometr_1
B1: Ффинансовый стресс | C1: Корпоративный сектор | F1: Сектор домохозяйств | I1: Сектор государственного управления | L1: Банковский сектор | O1: Внешний сектор | R1: Рынок недвижимости | U1: Барометр финансовых уязвимостей
B3: Binary | D3: S_Indicator | F3: Total | G3: S_Indicator | H3: (-) | I3: Total | J3: S_Indicator | K3: (-) | L3: Total | M3: S_Indicator | N3: (-) | O3: Total | P3: S_Indicator | Q3: (-) | R3: Total | S3: S_Indicator | T3: (-) | U3: Total | V3: Indicator | W3: (-) | X3: Кредитный разрыв (по Требованиям банков к экономике, % ВВП), левая шкала | Y3: Критическое значение Барометра
A4: 39814 | B4: 1 | C4: 0.34339825 | D4: 0.34339825 | E4: 0 | F4: 0.23539975 | G4: 0.23539975 | H4: 0 | I4: 0.0022279024 | J4: 0.0022279024 | K4: 0 | L4: 0.26595136 | M4: 0.26595136 | N4: 0 | O4: 0.3256198 | P4: 0.3256198 | Q4: 0 | R4: 0.36141928 | S4: 0.36141928 | T4: 0 | U4: 1.5340163 | V4: 1.5340163 | W4: 0 | X4: 0.92540619 | Y4: 1.5 | Z4: 2009 кв.1
A5: 39904 | B5: 0 | C5: 0.59813337 | D5: 0.59813337 | E5: 0 | F5: 0.31729202 | G5: 0.31729202 | H5: 0 | I5: 0.21962804 | J5: 0.21962804 | K5: 0 | L5: 0.27825931 | M5: 0.27825931 | N5: 0 | O5: 0.48210361 | P5: 0.48210361 | Q5: 0 | R5: 0.41370989 | S5: 0.41370989 | T5: 0 | U5: 2.3091262 | V5: 2.3091262 | W5: 0 | X5: 1.5427327 | Y5: 1.5 | Z5: 2009 кв.2
A6: 39995 | B6: 0 | C6: 0.55207961 | D6: 0.55207961 | E6: 0 | F6: 0.33634225 | G6: 0.33634225 | H6: 0 | I6: 0.31129357 | J6: 0.31129357 | K6: 0 | L6: 0.36817755 | M6: 0.36817755 | N6: 0 | O6: 0.48994192 | P6: 0.48994192 | Q6: 0 | R6: 0.26833774 | S6: 0.26833774 | T6: 0 | U6: 2.3261726 | V6: 2.3261726 | W6: 0 | X6: 2.5946506 | Y6: 1.5 | Z6: 2009 кв.3
A7: 40087 | B7: 0 | C7: 0.43727831 | D7: 0.43727831 | E7: 0 | F7: 0.34368008 | G7: 0.34368008 | H7: 0 | I7: 0.050987143 | J7: 0.050987143 | K7: 0 | L7: 0.38859399 | M7: 0.38859399 | N7: 0 | O7: 0.56493429 | P7: 0.56493429 | Q7: 0 | R7: -0.087606847 | S7: 0 | T7: -0.087606847 | U7: 1.697867 | V7: 1.7854738 | W7: -0.087606847 | X7: 3.0920509 | Y7: 1.5 | Z7: 2009 кв.4
A8: 40179 | B8: 0 | C8: 0.3637488 | D8: 0.3637488 | E8: 0 | F8: 0.36322765 | G8: 0.36322765 | H8: 0 | I8: 0.14706876 | J8: 0.14706876 | K8: 0 | L8: 0.38950733 | M8: 0.38950733 | N8: 0 | O8: 0.3668327 | P8: 0.3668327 | Q8: 0 | R8: -0.62914935 | S8: 0 | T8: -0.62914935 | U8: 1.0012359 | V8: 1.6303852 | W8: -0.62914935 | X8: 4.2536187 | Y8: 1.5 | Z8: 2010 кв.1
A9: 40269 | B9: 0 | C9: 0.28933892 | D9: 0.28933892 | E9: 0 | F9: 0.33524306 | G9: 0.33524306 | H9: 0 | I9: 0.083969549 | J9: 0.083969549 | K9: 0 | L9: 0.4808002 | M9: 0.4808002 | N9: 0 | O9: 0.27983916 | P9: 0.27983916 | Q9: 0 | R9: -0.70194315 | S9: 0 | T9: -0.70194315 | U9: 0.76724775 | V9: 1.4691909 | W9: -0.70194315 | X9: 5.0842476 | Y9: 1.5 | Z9: 2010 кв.2
A10: 40360 | B10: 0 | C10: 0.17783755 | D10: 0.17783755 | E10: 0 | F10: 0.30969886 | G10: 0.30969886 | H10: 0 | I10: 0.17156554 | J10: 0.17156554 | K10: 0 | L10: 0.54935412 | M10: 0.54935412 | N10: 0 | O10: 0.37043055 | P10: 0.37043055 | Q10: 0 | R10: -0.60408698 | S10: 0 | T10: -0.60408698 | U10: 0.97479964 | V10: 1.5788866 | W10: -0.60408698 | X10: 6.2154254 | Y10: 1.5 | Z10: 2010 кв.3
A11: 40452 | B11: 0 | C11: 0.2730972 | D11: 0.2730972 | E11: 0 | F11: 0.31600806 | G11: 0.31600806 | H11: 0 | I11: 0.17902107 | J11: 0.17902107 | K11: 0 | L11: 0.61173013 | M11: 0.61173013 | N11: 0 | O11: 0.43058559 | P11: 0.43058559 | Q11: 0 | R11: -0.33262556 | S11: 0 | T11: -0.33262556 | U11: 1.4778165 | V11: 1.810442 | W11: -0.33262556 | X11: 7.5682551 | Y11: 1.5 | Z11: 2010 кв.4
A12: 40544 | B12: 0 | C12: 0.12634115 | D12: 0.12634115 | E12: 0 | F12: 0.31343674 | G12: 0.31343674 | H12: 0 | I12: -0.037793443 | J12: 0 | K12: -0.037793443 | L12: 0.69728201 | M12: 0.69728201 | N12: 0 | O12: 0.58039712 | P12: 0.58039712 | Q12: 0 | R12: -0.35048709 | S12: 0 | T12: -0.35048709 | U12: 1.3291765 | V12: 1.717457 | W12: -0.38828053 | X12: 8.0572618 | Y12: 1.5 | Z12: 2011 кв.1
